Workbook

Sheet WD40_Summary
A1: WD40_Summary | B1: Original researched inputs | C1: Bear | D1: Base | E1: Bull
A2: DCF value / USD per share | B2: ='WD40_DCF_original'!B28+0 -> 88.150296 | C2: ='WD40_DCF_bear'!B28+0 -> 80.578186 | D2: ='WD40_DCF_base'!B28+0 -> 159.17021 | E2: ='WD40_DCF_bull'!B28+0 -> 258.66159
A3: Operating value / USD m | B3: ='WD40_DCF_original'!B26+0 -> 1230.6412 | C3: ='WD40_DCF_bear'!B26+0 -> 1127.4086 | D3: ='WD40_DCF_base'!B26+0 -> 2198.8743 | E3: ='WD40_DCF_bull'!B26+0 -> 3555.2665
A4: Equity value / USD m | B4: ='WD40_DCF_original'!B27+0 -> 1201.7762 | C4: ='WD40_DCF_bear'!B27+0 -> 1098.5436 | D4: ='WD40_DCF_base'!B27+0 -> 2170.0093 | E4: ='WD40_DCF_bull'!B27+0 -> 3526.4015
A5: PV terminal value / USD m | B5: ='WD40_DCF_original'!B22+0 -> 670.76664 | C5: ='WD40_DCF_bear'!B22+0 -> 584.91124 | D5: ='WD40_DCF_base'!B22+0 -> 1490.9939 | E5: ='WD40_DCF_bull'!B22+0 -> 2699.9776
A6: Terminal value share | B6: ='WD40_DCF_original'!B29+0 -> 0.54505461 | C6: ='WD40_DCF_bear'!B29+0 -> 0.51881035 | D6: ='WD40_DCF_base'!B29+0 -> 0.67807143 | E6: ='WD40_DCF_bull'!B29+0 -> 0.75943042
A7: Historical reference / USD per share | B7: 216.04 | C7: 216.04 | D7: 216.04 | E7: 216.04
A8: DCF / historical reference minus 1 | B8: =(B2/B7)-1 -> -0.59197234 | C8: =(C2/C7)-1 -> -0.62702191 | D8: =(D2/D7)-1 -> -0.26323732 | E8: =(E2/E7)-1 -> 0.19728566
A9: EVA minus DCF / USD m | B9: ='WD40_DCF_original'!B35+0 -> 2.2737368e-13 | C9: ='WD40_DCF_bear'!B35+0 -> 2.2737368e-13 | D9: ='WD40_DCF_base'!B35+0 -> 0 | E9: ='WD40_DCF_bull'!B35+0 -> -4.5474735e-13
A10: Scenario input hash | B10: e4c1895827e92d2759c61c3392fe8d9bafdd00069c33ad8ba99cb38a559f8cab | C10: 7c94e410363005ee306c3716110f2043a39411978dbc63b690807a6312846c44 | D10: a3708c72cdd6414155499a3919eb1f26547f3aea16a29781732f53e4221c6525 | E10: f23ba87d738fcf1f513ee37ad47bda6c395533da52e4d31c9cf7907fbb71b2fe
A11: Scenario classification | B11: original_snapshot | C11: analyst_assumption | D11: analyst_assumption | E11: analyst_assumption
A12: Financial basis | B12: FY2025 retrospective; later filings with historical price | C12: FY2025 retrospective; later filings with historical price | D12: FY2025 retrospective; later filings with historical price | E12: FY2025 retrospective; later filings with historical price
A13: Price date | B13: 2025-08-29 | C13: 2025-08-29 | D13: 2025-08-29 | E13: 2025-08-29
A14: Excel calculation status | B14: Python/browser verification; native Excel calculation pending | C14: Python/browser verification; native Excel calculation pending | D14: Python/browser verification; native Excel calculation pending | E14: Python/browser verification; native Excel calculation pending

Sheet WD40_Methods
A1: WD40_Methods | B1: Low / USD per share | C1: Central / USD per share | D1: High / USD per share | E1: Status | F1: Range interpretation | G1: Limitations
A2: Trading peers · EV/EBITDA | B2: Unavailable | C2: Unavailable | D2: Unavailable | E2: missing_data | F2: observed_multiple_percentiles | G2: At least three verified same-date observations are required. Percentiles are descriptive observations, not business scenarios. The WD-40 per-share denominator is a valuation dilution proxy.
A3: Trading peers · P/E | B3: Unavailable | C3: Unavailable | D3: Unavailable | E3: missing_data | F3: observed_multiple_percentiles | G3: At least three verified same-date observations are required. Percentiles are descriptive observations, not business scenarios. The WD-40 per-share denominator is a valuation dilution proxy.
A4: Trading peers · EV/sales | B4: Unavailable | C4: Unavailable | D4: Unavailable | E4: missing_data | F4: observed_multiple_percentiles | G4: At least three verified same-date observations are required. Percentiles are descriptive observations, not business scenarios. The WD-40 per-share denominator is a valuation dilution proxy.
A5: Acquisition context · consideration/EBITDA | B5: ='WD40_Precedents'!B6+0 -> 100.5581 | C5: ='WD40_Precedents'!C6+0 -> 112.87914 | D5: ='WD40_Precedents'!D6+0 -> 174.33224 | E5: indicative | F5: announced_consideration_context | G5: Announced acquisition consideration is not a verified net-debt-adjusted EV. Adjacent oral-care and personal-care brands differ from maintenance products. Periods, growth and deal tax structures differ; no tax shield is subtracted. This contextual range does not establish a WD-40 control valuation.
A6: LBO · sponsor ability to pay | B6: ='WD40_LBO'!B127+0 -> 89.370301 | C6: ='WD40_LBO'!C127+0 -> 100.33908 | D6: ='WD40_LBO'!D127+0 -> 106.93407 | E6: illustrative | F6: buyer_return_hurdles | G6: Leverage, debt pricing, fees and exit multiple are analyst assumptions. Forecast FCFF is a valuation proxy; no lender-approved financing is asserted. Forward reported EBITDA uses an explicit constant-margin R&D and D&A bridge. Entry EBITDA is operating EBIT plus cash-flow D&A, not the issuer adjusted EBITDA measure. No interim sponsor distributions or additional equity contributions are modeled. The per-share denominator is the case dilution proxy.
A7: DDM · assumed dividend policy | B7: ='WD40_DDM'!B72+0 -> 66.255859 | C7: ='WD40_DDM'!C72+0 -> 83.27561 | D7: ='WD40_DDM'!D72+0 -> 105.82183 | E7: illustrative | F7: analyst_dividend_scenarios | G7: Dividend growth and cost of equity are explicit analyst assumptions, not a CAPM estimate. The $3.76 dividend is an annualized quarterly run rate, not total shareholder distributions. Payout coverage uses a constant-debt FCFE proxy; buybacks are not separately valued. Terminal dividend growth uses the operating case terminal growth.
A8: Strategic buyer · incremental synergies | B8: ='WD40_Synergies'!B66+0 -> 192.31365 | C8: ='WD40_Synergies'!C66+0 -> 225.45708 | D8: ='WD40_Synergies'!D66+0 -> 258.60052 | E8: illustrative | F8: buyer_cost_savings_scenarios | G8: No identified buyer or verified synergy plan is asserted. Savings are incremental to standalone margins; no acquired growth is added. A one-year run-rate implementation cost is paid up front without an assumed tax shield. No acquisition premium allocation or negotiated seller share is assumed.

Sheet WD40_Regions_bear
A1: WD40_Regions_bear | B1: americas | C1: eimea | D1: asiaPacific | E1: Consolidated
A2: Reported FY2025 revenue / USD m | B2: 290.599 | C2: 236.434 | D2: 92.952 | E2: =SUM(B2:D2) -> 619.985
A3: Explicit divestment revenue removal / USD m | B3: 0 | C3: 0 | D3: 0 | E3: =SUM(B3:D3) -> 0
A4: Revenue after removal / USD m | B4: =B2-B3 -> 290.599 | C4: =C2-C3 -> 236.434 | D4: =D2-D3 -> 92.952 | E4: =SUM(B4:D4) -> 619.985
A5: Analyst regional growth years 1-5 | B5: 0.01 | C5: 0.04 | D5: 0.06
A6: Terminal growth | B6: ='WD40_Inputs_bear'!B22+0 -> 0.025 | C6: ='WD40_Inputs_bear'!B22+0 -> 0.025 | D6: ='WD40_Inputs_bear'!B22+0 -> 0.025
A7: Y1 revenue growth | B7: =B5+0 -> 0.01 | C7: =C5+0 -> 0.04 | D7: =D5+0 -> 0.06 | E7: =(E8/E2)-1 -> 0.028936942
A8: Y1 regional revenue / USD m | B8: =B4*(1+B7) -> 293.50499 | C8: =C4*(1+C7) -> 245.89136 | D8: =D4*(1+D7) -> 98.52912 | E8: =SUM(B8:D8) -> 637.92547
A9: Y1 compressed Ginzu revenue / USD m | E9: ='WD40_DCF_bear'!C4+0 -> 637.92547
A10: Y1 Ginzu minus regional revenue / USD m | E10: =E9-E8 -> 0
A11: Y2 revenue growth | B11: =B5+0 -> 0.01 | C11: =C5+0 -> 0.04 | D11: =D5+0 -> 0.06 | E11: =(E12/E8)-1 -> 0.029286261
A12: Y2 regional revenue / USD m | B12: =B8*(1+B11) -> 296.44004 | C12: =C8*(1+C11) -> 255.72701 | D12: =D8*(1+D11) -> 104.44087 | E12: =SUM(B12:D12) -> 656.60792
A13: Y2 compressed Ginzu revenue / USD m | E13: ='WD40_DCF_bear'!D4+0 -> 656.94437
A14: Y2 Ginzu minus regional revenue / USD m | E14: =E13-E12 -> 0.33644672
A15: Y3 revenue growth | B15: =B5+0 -> 0.01 | C15: =C5+0 -> 0.04 | D15: =D5+0 -> 0.06 | E15: =(E16/E12)-1 -> 0.029637067
A16: Y3 regional revenue / USD m | B16: =B12*(1+B15) -> 299.40444 | C16: =C12*(1+C15) -> 265.95609 | D16: =D12*(1+D15) -> 110.70732 | E16: =SUM(B16:D16) -> 676.06785
A17: Y3 compressed Ginzu revenue / USD m | E17: ='WD40_DCF_bear'!E4+0 -> 676.53029
A18: Y3 Ginzu minus regional revenue / USD m | E18: =E17-E16 -> 0.46243506
A19: Y4 revenue growth | B19: =B5+0 -> 0.01 | C19: =C5+0 -> 0.04 | D19: =D5+0 -> 0.06 | E19: =(E20/E16)-1 -> 0.02998919
A20: Y4 regional revenue / USD m | B20: =B16*(1+B19) -> 302.39848 | C20: =C16*(1+C19) -> 276.59434 | D20: =D16*(1+D19) -> 117.34976 | E20: =SUM(B20:D20) -> 696.34258
A21: Y4 compressed Ginzu revenue / USD m | E21: ='WD40_DCF_bear'!F4+0 -> 696.70014
A22: Y4 Ginzu minus regional revenue / USD m | E22: =E21-E20 -> 0.3575572
A23: Y5 revenue growth | B23: =B5+0 -> 0.01 | C23: =C5+0 -> 0.04 | D23: =D5+0 -> 0.06 | E23: =(E24/E20)-1 -> 0.030342456
A24: Y5 regional revenue / USD m | B24: =B20*(1+B23) -> 305.42247 | C24: =C20*(1+C23) -> 287.65811 | D24: =D20*(1+D23) -> 124.39074 | E24: =SUM(B24:D24) -> 717.47133
A25: Y5 compressed Ginzu revenue / USD m | E25: ='WD40_DCF_bear'!G4+0 -> 717.47133
A26: Y5 Ginzu minus regional revenue / USD m | E26: =E25-E24 -> -2.2737368e-13
A27: Y6 revenue growth | B27: =B5-(((B5-B6)/5)*1)+0 -> 0.013 | C27: =C5-(((C5-C6)/5)*1)+0 -> 0.037 | D27: =D5-(((D5-D6)/5)*1)+0 -> 0.053 | E27: =(E28/E24)-1 -> 0.029557351
A28: Y6 regional revenue / USD m | B28: =B24*(1+B27) -> 309.39296 | C28: =C24*(1+C27) -> 298.30146 | D28: =D24*(1+D27) -> 130.98345 | E28: =SUM(B28:D28) -> 738.67788
A29: Y6 compressed Ginzu revenue / USD m | E29: ='WD40_DCF_bear'!H4+0 -> 738.17104
A30: Y6 Ginzu minus regional revenue / USD m | E30: =E29-E28 -> -0.50683349
A31: Y7 revenue growth | B31: =B5-(((B5-B6)/5)*2)+0 -> 0.016 | C31: =C5-(((C5-C6)/5)*2)+0 -> 0.034 | D31: =D5-(((D5-D6)/5)*2)+0 -> 0.046 | E31: =(E32/E28)-1 -> 0.028588613
A32: Y7 regional revenue / USD m | B32: =B28*(1+B31) -> 314.34325 | C32: =C28*(1+C31) -> 308.44371 | D32: =D28*(1+D31) -> 137.00869 | E32: =SUM(B32:D32) -> 759.79565
A33: Y7 compressed Ginzu revenue / USD m | E33: ='WD40_DCF_bear'!I4+0 -> 758.75731
A34: Y7 Ginzu minus regional revenue / USD m | E34: =E33-E32 -> -1.0383471
A35: Y8 revenue growth | B35: =B5-(((B5-B6)/5)*3)+0 -> 0.019 | C35: =C5-(((C5-C6)/5)*3)+0 -> 0.031 | D35: =D5-(((D5-D6)/5)*3)+0 -> 0.039 | E35: =(E36/E32)-1 -> 0.027477935
A36: Y8 regional revenue / USD m | B36: =B32*(1+B35) -> 320.31577 | C36: =C32*(1+C35) -> 318.00547 | D36: =D32*(1+D35) -> 142.35203 | E36: =SUM(B36:D36) -> 780.67327
A37: Y8 compressed Ginzu revenue / USD m | E37: ='WD40_DCF_bear'!J4+0 -> 779.1872
A38: Y8 Ginzu minus regional revenue / USD m | E38: =E37-E36 -> -1.4860679
A39: Y9 revenue growth | B39: =B5-(((B5-B6)/5)*4)+0 -> 0.022 | C39: =C5-(((C5-C6)/5)*4)+0 -> 0.028 | D39: =D5-(((D5-D6)/5)*4)+0 -> 0.032 | E39: =(E40/E36)-1 -> 0.026267538
A40: Y9 regional revenue / USD m | B40: =B36*(1+B39) -> 327.36272 | C40: =C36*(1+C39) -> 326.90962 | D40: =D36*(1+D39) -> 146.9073 | E40: =SUM(B40:D40) -> 801.17963
A41: Y9 compressed Ginzu revenue / USD m | E41: ='WD40_DCF_bear'!K4+0 -> 799.41703
A42: Y9 Ginzu minus regional revenue / USD m | E42: =E41-E40 -> -1.7626032
A43: Y10 revenue growth | B43: =B5-(((B5-B6)/5)*5)+0 -> 0.025 | C43: =C5-(((C5-C6)/5)*5)+0 -> 0.025 | D43: =D5-(((D5-D6)/5)*5)+0 -> 0.025 | E43: =(E44/E40)-1 -> 0.025
A44: Y10 regional revenue / USD m | B44: =B40*(1+B43) -> 335.54679 | C44: =C40*(1+C43) -> 335.08236 | D44: =D40*(1+D43) -> 150.57998 | E44: =SUM(B44:D44) -> 821.20913
A45: Y10 compressed Ginzu revenue / USD m | E45: ='WD40_DCF_bear'!L4+0 -> 819.40246
A46: Y10 Ginzu minus regional revenue / USD m | E46: =E45-E44 -> -1.8066683
A47: Consolidated year-one growth | E47: =E7+0 -> 0.028936942
A48: Year-one to year-five revenue CAGR | E48: =(E24/E8)^0.25-1 -> 0.029813668
A49: Basis and compression interpretation | B49: Reported regional base; analyst growth and constant FX. Two Ginzu growth inputs preserve Y1/Y5 endpoints; other years differ.

Sheet WD40_Regions_base
A1: WD40_Regions_base | B1: americas | C1: eimea | D1: asiaPacific | E1: Consolidated
A2: Reported FY2025 revenue / USD m | B2: 290.599 | C2: 236.434 | D2: 92.952 | E2: =SUM(B2:D2) -> 619.985
A3: Explicit divestment revenue removal / USD m | B3: 0 | C3: 0 | D3: 0 | E3: =SUM(B3:D3) -> 0
A4: Revenue after removal / USD m | B4: =B2-B3 -> 290.599 | C4: =C2-C3 -> 236.434 | D4: =D2-D3 -> 92.952 | E4: =SUM(B4:D4) -> 619.985
A5: Analyst regional growth years 1-5 | B5: 0.04 | C5: 0.07 | D5: 0.1
A6: Terminal growth | B6: ='WD40_Inputs_base'!B22+0 -> 0.025 | C6: ='WD40_Inputs_base'!B22+0 -> 0.025 | D6: ='WD40_Inputs_base'!B22+0 -> 0.025
A7: Y1 revenue growth | B7: =B5+0 -> 0.04 | C7: =C5+0 -> 0.07 | D7: =D5+0 -> 0.1 | E7: =(E8/E2)-1 -> 0.060436204
A8: Y1 regional revenue / USD m | B8: =B4*(1+B7) -> 302.22296 | C8: =C4*(1+C7) -> 252.98438 | D8: =D4*(1+D7) -> 102.2472 | E8: =SUM(B8:D8) -> 657.45454
A9: Y1 compressed Ginzu revenue / USD m | E9: ='WD40_DCF_base'!C4+0 -> 657.45454
A10: Y1 Ginzu minus regional revenue / USD m | E10: =E9-E8 -> 0
A11: Y2 revenue growth | B11: =B5+0 -> 0.04 | C11: =C5+0 -> 0.07 | D11: =D5+0 -> 0.1 | E11: =(E12/E8)-1 -> 0.060875
A12: Y2 regional revenue / USD m | B12: =B8*(1+B11) -> 314.31188 | C12: =C8*(1+C11) -> 270.69329 | D12: =D8*(1+D11) -> 112.47192 | E12: =SUM(B12:D12) -> 697.47708
A13: Y2 compressed Ginzu revenue / USD m | E13: ='WD40_DCF_base'!D4+0 -> 697.9172
A14: Y2 Ginzu minus regional revenue / USD m | E14: =E13-E12 -> 0.44011402
A15: Y3 revenue growth | B15: =B5+0 -> 0.04 | C15: =C5+0 -> 0.07 | D15: =D5+0 -> 0.1 | E15: =(E16/E12)-1 -> 0.061318426
A16: Y3 regional revenue / USD m | B16: =B12*(1+B15) -> 326.88435 | C16: =C12*(1+C15) -> 289.64182 | D16: =D12*(1+D15) -> 123.71911 | E16: =SUM(B16:D16) -> 740.24528
A17: Y3 compressed Ginzu revenue / USD m | E17: ='WD40_DCF_base'!E4+0 -> 740.87011
A18: Y3 Ginzu minus regional revenue / USD m | E18: =E17-E16 -> 0.62482677
A19: Y4 revenue growth | B19: =B5+0 -> 0.04 | C19: =C5+0 -> 0.07 | D19: =D5+0 -> 0.1 | E19: =(E20/E16)-1 -> 0.0617663
A20: Y4 regional revenue / USD m | B20: =B16*(1+B19) -> 339.95973 | C20: =C16*(1+C19) -> 309.91674 | D20: =D16*(1+D19) -> 136.09102 | E20: =SUM(B20:D20) -> 785.96749
A21: Y4 compressed Ginzu revenue / USD m | E21: ='WD40_DCF_base'!F4+0 -> 786.46653
A22: Y4 Ginzu minus regional revenue / USD m | E22: =E21-E20 -> 0.49903619
A23: Y5 revenue growth | B23: =B5+0 -> 0.04 | C23: =C5+0 -> 0.07 | D23: =D5+0 -> 0.1 | E23: =(E24/E20)-1 -> 0.06221843
A24: Y5 regional revenue / USD m | B24: =B20*(1+B23) -> 353.55812 | C24: =C20*(1+C23) -> 331.61092 | D24: =D20*(1+D23) -> 149.70013 | E24: =SUM(B24:D24) -> 834.86916
A25: Y5 compressed Ginzu revenue / USD m | E25: ='WD40_DCF_base'!G4+0 -> 834.86916
A26: Y5 Ginzu minus regional revenue / USD m | E26: =E25-E24 -> 0
A27: Y6 revenue growth | B27: =B5-(((B5-B6)/5)*1)+0 -> 0.037 | C27: =C5-(((C5-C6)/5)*1)+0 -> 0.061 | D27: =D5-(((D5-D6)/5)*1)+0 -> 0.085 | E27: =(E28/E24)-1 -> 0.05513969
A28: Y6 regional revenue / USD m | B28: =B24*(1+B27) -> 366.63977 | C28: =C24*(1+C27) -> 351.83918 | D28: =D24*(1+D27) -> 162.42464 | E28: =SUM(B28:D28) -> 880.90359
A29: Y6 compressed Ginzu revenue / USD m | E29: ='WD40_DCF_base'!H4+0 -> 880.14874
A30: Y6 Ginzu minus regional revenue / USD m | E30: =E29-E28 -> -0.75484988
A31: Y7 revenue growth | B31: =B5-(((B5-B6)/5)*2)+0 -> 0.034 | C31: =C5-(((C5-C6)/5)*2)+0 -> 0.052 | D31: =D5-(((D5-D6)/5)*2)+0 -> 0.07 | E31: =(E32/E28)-1 -> 0.047827157
A32: Y7 regional revenue / USD m | B32: =B28*(1+B31) -> 379.10552 | C32: =C28*(1+C31) -> 370.13482 | D32: =D28*(1+D31) -> 173.79436 | E32: =SUM(B32:D32) -> 923.0347
A33: Y7 compressed Ginzu revenue / USD m | E33: ='WD40_DCF_base'!I4+0 -> 921.45117
A34: Y7 Ginzu minus regional revenue / USD m | E34: =E33-E32 -> -1.58353
A35: Y8 revenue growth | B35: =B5-(((B5-B6)/5)*3)+0 -> 0.031 | C35: =C5-(((C5-C6)/5)*3)+0 -> 0.043 | D35: =D5-(((D5-D6)/5)*3)+0 -> 0.055 | E35: =(E36/E32)-1 -> 0.040330833
A36: Y8 regional revenue / USD m | B36: =B32*(1+B35) -> 390.85779 | C36: =C32*(1+C35) -> 386.05062 | D36: =D32*(1+D35) -> 183.35305 | E36: =SUM(B36:D36) -> 960.26146
A37: Y8 compressed Ginzu revenue / USD m | E37: ='WD40_DCF_base'!J4+0 -> 957.95701
A38: Y8 Ginzu minus regional revenue / USD m | E38: =E37-E36 -> -2.3044491
A39: Y9 revenue growth | B39: =B5-(((B5-B6)/5)*4)+0 -> 0.028 | C39: =C5-(((C5-C6)/5)*4)+0 -> 0.034 | D39: =D5-(((D5-D6)/5)*4)+0 -> 0.04 | E39: =(E40/E36)-1 -> 0.032703448
A40: Y9 regional revenue / USD m | B40: =B36*(1+B39) -> 401.80181 | C40: =C36*(1+C39) -> 399.17634 | D40: =D36*(1+D39) -> 190.68717 | E40: =SUM(B40:D40) -> 991.66532
A41: Y9 compressed Ginzu revenue / USD m | E41: ='WD40_DCF_base'!K4+0 -> 988.90753
A42: Y9 Ginzu minus regional revenue / USD m | E42: =E41-E40 -> -2.7577882
A43: Y10 revenue growth | B43: =B5-(((B5-B6)/5)*5)+0 -> 0.025 | C43: =C5-(((C5-C6)/5)*5)+0 -> 0.025 | D43: =D5-(((D5-D6)/5)*5)+0 -> 0.025 | E43: =(E44/E40)-1 -> 0.025
A44: Y10 regional revenue / USD m | B44: =B40*(1+B43) -> 411.84685 | C44: =C40*(1+C43) -> 409.15575 | D44: =D40*(1+D43) -> 195.45435 | E44: =SUM(B44:D44) -> 1016.457
A45: Y10 compressed Ginzu revenue / USD m | E45: ='WD40_DCF_base'!L4+0 -> 1013.6302
A46: Y10 Ginzu minus regional revenue / USD m | E46: =E45-E44 -> -2.8267329
A47: Consolidated year-one growth | E47: =E7+0 -> 0.060436204
A48: Year-one to year-five revenue CAGR | E48: =(E24/E8)^0.25-1 -> 0.061544421
A49: Basis and compression interpretation | B49: Reported regional base; analyst growth and constant FX. Two Ginzu growth inputs preserve Y1/Y5 endpoints; other years differ.

Sheet WD40_Regions_bull
A1: WD40_Regions_bull | B1: americas | C1: eimea | D1: asiaPacific | E1: Consolidated
A2: Reported FY2025 revenue / USD m | B2: 290.599 | C2: 236.434 | D2: 92.952 | E2: =SUM(B2:D2) -> 619.985
A3: Explicit divestment revenue removal / USD m | B3: 0 | C3: 0 | D3: 0 | E3: =SUM(B3:D3) -> 0
A4: Revenue after removal / USD m | B4: =B2-B3 -> 290.599 | C4: =C2-C3 -> 236.434 | D4: =D2-D3 -> 92.952 | E4: =SUM(B4:D4) -> 619.985
A5: Analyst regional growth years 1-5 | B5: 0.06 | C5: 0.09 | D5: 0.13
A6: Terminal growth | B6: ='WD40_Inputs_bull'!B22+0 -> 0.03 | C6: ='WD40_Inputs_bull'!B22+0 -> 0.03 | D6: ='WD40_Inputs_bull'!B22+0 -> 0.03
A7: Y1 revenue growth | B7: =B5+0 -> 0.06 | C7: =C5+0 -> 0.09 | D7: =D5+0 -> 0.13 | E7: =(E8/E2)-1 -> 0.081935466
A8: Y1 regional revenue / USD m | B8: =B4*(1+B7) -> 308.03494 | C8: =C4*(1+C7) -> 257.71306 | D8: =D4*(1+D7) -> 105.03576 | E8: =SUM(B8:D8) -> 670.78376
A9: Y1 compressed Ginzu revenue / USD m | E9: ='WD40_DCF_bull'!C4+0 -> 670.78376
A10: Y1 Ginzu minus regional revenue / USD m | E10: =E9-E8 -> 1.1368684e-13
A11: Y2 revenue growth | B11: =B5+0 -> 0.06 | C11: =C5+0 -> 0.09 | D11: =D5+0 -> 0.13 | E11: =(E12/E8)-1 -> 0.082486971
A12: Y2 regional revenue / USD m | B12: =B8*(1+B11) -> 326.51704 | C12: =C8*(1+C11) -> 280.90724 | D12: =D8*(1+D11) -> 118.69041 | E12: =SUM(B12:D12) -> 726.11468
A13: Y2 compressed Ginzu revenue / USD m | E13: ='WD40_DCF_bull'!D4+0 -> 726.68542
A14: Y2 Ginzu minus regional revenue / USD m | E14: =E13-E12 -> 0.57073582
A15: Y3 revenue growth | B15: =B5+0 -> 0.06 | C15: =C5+0 -> 0.09 | D15: =D5+0 -> 0.13 | E15: =(E16/E12)-1 -> 0.083048075
A16: Y3 regional revenue / USD m | B16: =B12*(1+B15) -> 346.10806 | C16: =C12*(1+C15) -> 306.18889 | D16: =D12*(1+D15) -> 134.12016 | E16: =SUM(B16:D16) -> 786.41711
A17: Y3 compressed Ginzu revenue / USD m | E17: ='WD40_DCF_bull'!E4+0 -> 787.2458
A18: Y3 Ginzu minus regional revenue / USD m | E18: =E17-E16 -> 0.82868791
A19: Y4 revenue growth | B19: =B5+0 -> 0.06 | C19: =C5+0 -> 0.09 | D19: =D5+0 -> 0.13 | E19: =(E20/E16)-1 -> 0.083618609
A20: Y4 regional revenue / USD m | B20: =B16*(1+B19) -> 366.87454 | C20: =C16*(1+C19) -> 333.74589 | D20: =D16*(1+D19) -> 151.55578 | E20: =SUM(B20:D20) -> 852.17621
A21: Y4 compressed Ginzu revenue / USD m | E21: ='WD40_DCF_bull'!F4+0 -> 852.85314
A22: Y4 Ginzu minus regional revenue / USD m | E22: =E21-E20 -> 0.67693211
A23: Y5 revenue growth | B23: =B5+0 -> 0.06 | C23: =C5+0 -> 0.09 | D23: =D5+0 -> 0.13 | E23: =(E24/E20)-1 -> 0.084198377
A24: Y5 regional revenue / USD m | B24: =B20*(1+B23) -> 388.88701 | C24: =C20*(1+C23) -> 363.78302 | D24: =D20*(1+D23) -> 171.25803 | E24: =SUM(B24:D24) -> 923.92807
A25: Y5 compressed Ginzu revenue / USD m | E25: ='WD40_DCF_bull'!G4+0 -> 923.92807
A26: Y5 Ginzu minus regional revenue / USD m | E26: =E25-E24 -> 3.4106051e-13
A27: Y6 revenue growth | B27: =B5-(((B5-B6)/5)*1)+0 -> 0.054 | C27: =C5-(((C5-C6)/5)*1)+0 -> 0.078 | D27: =D5-(((D5-D6)/5)*1)+0 -> 0.11 | E27: =(E28/E24)-1 -> 0.073829728
A28: Y6 regional revenue / USD m | B28: =B24*(1+B27) -> 409.88691 | C28: =C24*(1+C27) -> 392.15809 | D28: =D24*(1+D27) -> 190.09642 | E28: =SUM(B28:D28) -> 992.14142
A29: Y6 compressed Ginzu revenue / USD m | E29: ='WD40_DCF_bull'!H4+0 -> 991.07015
A30: Y6 Ginzu minus regional revenue / USD m | E30: =E29-E28 -> -1.0712686
A31: Y7 revenue growth | B31: =B5-(((B5-B6)/5)*2)+0 -> 0.048 | C31: =C5-(((C5-C6)/5)*2)+0 -> 0.066 | D31: =D5-(((D5-D6)/5)*2)+0 -> 0.09 | E31: =(E32/E28)-1 -> 0.063162047
A32: Y7 regional revenue / USD m | B32: =B28*(1+B31) -> 429.56149 | C32: =C28*(1+C31) -> 418.04053 | D32: =D28*(1+D31) -> 207.2051 | E32: =SUM(B32:D32) -> 1054.8071
A33: Y7 compressed Ginzu revenue / USD m | E33: ='WD40_DCF_bull'!I4+0 -> 1052.5192
A34: Y7 Ginzu minus regional revenue / USD m | E34: =E33-E32 -> -2.2879345
A35: Y8 revenue growth | B35: =B5-(((B5-B6)/5)*3)+0 -> 0.042 | C35: =C5-(((C5-C6)/5)*3)+0 -> 0.054 | D35: =D5-(((D5-D6)/5)*3)+0 -> 0.07 | E35: =(E36/E32)-1 -> 0.052256121
A36: Y8 regional revenue / USD m | B36: =B32*(1+B35) -> 447.60307 | C36: =C32*(1+C35) -> 440.61471 | D36: =D32*(1+D35) -> 221.70945 | E36: =SUM(B36:D36) -> 1109.9272
A37: Y8 compressed Ginzu revenue / USD m | E37: ='WD40_DCF_bull'!J4+0 -> 1106.5504
A38: Y8 Ginzu minus regional revenue / USD m | E38: =E37-E36 -> -3.3768554
A39: Y9 revenue growth | B39: =B5-(((B5-B6)/5)*4)+0 -> 0.036 | C39: =C5-(((C5-C6)/5)*4)+0 -> 0.042 | D39: =D5-(((D5-D6)/5)*4)+0 -> 0.05 | E39: =(E40/E36)-1 -> 0.041178376
A40: Y9 regional revenue / USD m | B40: =B36*(1+B39) -> 463.71678 | C40: =C36*(1+C39) -> 459.12053 | D40: =D36*(1+D39) -> 232.79493 | E40: =SUM(B40:D40) -> 1155.6322
A41: Y9 compressed Ginzu revenue / USD m | E41: ='WD40_DCF_bull'!K4+0 -> 1151.5511
A42: Y9 Ginzu minus regional revenue / USD m | E42: =E41-E40 -> -4.0811481
A43: Y10 revenue growth | B43: =B5-(((B5-B6)/5)*5)+0 -> 0.03 | C43: =C5-(((C5-C6)/5)*5)+0 -> 0.03 | D43: =D5-(((D5-D6)/5)*5)+0 -> 0.03 | E43: =(E44/E40)-1 -> 0.03
A44: Y10 regional revenue / USD m | B44: =B40*(1+B43) -> 477.62828 | C44: =C40*(1+C43) -> 472.89415 | D44: =D40*(1+D43) -> 239.77877 | E44: =SUM(B44:D44) -> 1190.3012
A45: Y10 compressed Ginzu revenue / USD m | E45: ='WD40_DCF_bull'!L4+0 -> 1186.0976
A46: Y10 Ginzu minus regional revenue / USD m | E46: =E45-E44 -> -4.2035825
A47: Consolidated year-one growth | E47: =E7+0 -> 0.081935466
A48: Year-one to year-five revenue CAGR | E48: =(E24/E8)^0.25-1 -> 0.08333782
A49: Basis and compression interpretation | B49: Reported regional base; analyst growth and constant FX. Two Ginzu growth inputs preserve Y1/Y5 endpoints; other years differ.

Sheet WD40_Inputs_original
A1: WD40_Inputs_original | B1: Value
A2: Revenue FY2025 / USD m | B2: 619.985
A3: Reported EBIT FY2025 / USD m | B3: 103.793
A4: Adjusted book equity / USD m | B4: 268.472
A5: Interest-bearing debt / USD m | B5: 86.995
A6: Cash / USD m | B6: 58.13
A7: Nonoperating assets / USD m | B7: 0
A8: Minority interests / USD m | B8: 0
A9: Valuation dilution proxy / million shares | B9: 13.633263
A10: Historical reference price / USD per share | B10: 216.04
A11: Normalized starting tax rate | B11: 0.22200028
A12: Terminal tax rate | B12: 0.25
A13: Revenue growth year 1 | B13: 0.05
A14: Revenue growth years 2-5 | B14: =B13+0 -> 0.05
A15: Adjusted EBIT margin year 1 | B15: =B44/B2 -> 0.17106812
A16: Target adjusted EBIT margin | B16: =B15+0 -> 0.17106812
A17: Margin convergence year | B17: 5
A18: Sales to capital years 1-5 | B18: 2
A19: Sales to capital years 6-10 | B19: =B18+0 -> 2
A20: WACC years 1-5 | B20: 0.09
A21: Terminal WACC | B21: 0.08
A22: Terminal growth | B22: 0.025
A23: Use explicit terminal ROIC / 1=yes | B23: 0
A24: Explicit terminal ROIC | B24: 0.15
A25: Current R&D / USD m | B25: 8.7
A26: R&D amortization life / years | B26: 3
A27: Capitalize R&D / 1=yes | B27: 1
A28: Starting NOL / USD m | B28: 0
A29: Hold starting tax rate / 1=yes | B29: 0
A30: Override reinvestment timing / 1=yes | B30: 0
A31: Reinvestment growth lead / years | B31: 1
... A41: R&D 4 years prior / USD m | B41: 5.6
A42: R&D amortization / USD m | B42: =0+IF(1<=B26,(B38/B26),0)+IF(2<=B26,(B39/B26),0)+IF(3<=B26,(B40/B26),0)+IF(4<=B26,(B41/B26),0) -> 6.4333333
A43: Unamortized R&D asset / USD m | B43: =B25+IF(1<B26,(B38*((B26-1)/B26)),0)+IF(2<B26,(B39*((B26-2)/B26)),0)+IF(3<B26,(B40*((B26-3)/B26)),0)+IF(4<B26,(B41*((B26-4)/B26)),0) -> 16.1
A44: R&D-adjusted base EBIT / USD m | B44: =B3+IF(B27=1,(B25-B42),0) -> 106.05967
A45: Base invested capital / USD m | B45: =B4+B5-B6+IF(B27=1,B43,0) -> 313.437
A46: Effective terminal tax rate | B46: =IF(B29=1,B11,B12) -> 0.25
A47: Effective terminal ROIC | B47: =IF(B23=1,B24,B21) -> 0.08
A48: Cash after explicit haircut / USD m | B48: =B6-IF(B37=1,(B35*(B12-B36)),0) -> 58.13

Sheet WD40_DCF_original
A1: WD40_DCF_original | B1: Base | C1: Y1 | D1: Y2 | E1: Y3 | F1: Y4 | G1: Y5 | H1: Y6 | I1: Y7 | J1: Y8 | K1: Y9 | L1: Y10 | M1: Terminal
A2: Year | B2: 0 | C2: 1 | D2: 2 | E2: 3 | F2: 4 | G2: 5 | H2: 6 | I2: 7 | J2: 8 | K2: 9 | L2: 10 | M2: 11
A3: Revenue growth | C3: ='WD40_Inputs_original'!B13+0 -> 0.05 | D3: ='WD40_Inputs_original'!B14+0 -> 0.05 | E3: ='WD40_Inputs_original'!B14+0 -> 0.05 | F3: ='WD40_Inputs_original'!B14+0 -> 0.05 | G3: ='WD40_Inputs_original'!B14+0 -> 0.05 | H3: ='WD40_Inputs_original'!B14+0-((('WD40_Inputs_original'!B14+0-'WD40_Inputs_original'!B22+0)/5)*1) -> 0.045 | I3: ='WD40_Inputs_original'!B14+0-((('WD40_Inputs_original'!B14+0-'WD40_Inputs_original'!B22+0)/5)*2) -> 0.04 | J3: ='WD40_Inputs_original'!B14+0-((('WD40_Inputs_original'!B14+0-'WD40_Inputs_original'!B22+0)/5)*3) -> 0.035 | K3: ='WD40_Inputs_original'!B14+0-((('WD40_Inputs_original'!B14+0-'WD40_Inputs_original'!B22+0)/5)*4) -> 0.03 | L3: ='WD40_Inputs_original'!B14+0-((('WD40_Inputs_original'!B14+0-'WD40_Inputs_original'!B22+0)/5)*5) -> 0.025 | M3: ='WD40_Inputs_original'!B22+0 -> 0.025
A4: Revenue / USD m | B4: ='WD40_Inputs_original'!B2+0 -> 619.985 | C4: =B4*(1+C3) -> 650.98425 | D4: =C4*(1+D3) -> 683.53346 | E4: =D4*(1+E3) -> 717.71014 | F4: =E4*(1+F3) -> 753.59564 | G4: =F4*(1+G3) -> 791.27542 | H4: =G4*(1+H3) -> 826.88282 | I4: =H4*(1+I3) -> 859.95813 | J4: =I4*(1+J3) -> 890.05667 | ... M4: =L4*(1+M3) -> 963.16926
A5: Adjusted EBIT margin | B5: =B6/B4 -> 0.17106812 | C5: ='WD40_Inputs_original'!B15+0 -> 0.17106812 | D5: =IF(2>'WD40_Inputs_original'!B17+0,'WD40_Inputs_original'!B16+0,'WD40_Inputs_original'!B16+0-((('WD40_Inputs_original'!B16+0-'WD40_Inputs_original'!B15+0)/'WD40_Inputs_original'!B17+0)*('WD40_Inputs_original'!B17+0-2))) -> 0.17106812 | E5: =IF(3>'WD40_Inputs_original'!B17+0,'WD40_Inputs_original'!B16+0,'WD40_Inputs_original'!B16+0-((('WD40_Inputs_original'!B16+0-'WD40_Inputs_original'!B15+0)/'WD40_Inputs_original'!B17+0)*('WD40_Inputs_original'!B17+0-3))) -> 0.17106812 | F5: =IF(4>'WD40_Inputs_original'!B17+0,'WD40_Inputs_original'!B16+0,'WD40_Inputs_original'!B16+0-((('WD40_Inputs_original'!B16+0-'WD40_Inputs_original'!B15+0)/'WD40_Inputs_original'!B17+0)*('WD40_Inputs_original'!B17+0-4))) -> 0.17106812 | G5: =IF(5>'WD40_Inputs_original'!B17+0,'WD40_Inputs_original'!B16+0,'WD40_Inputs_original'!B16+0-((('WD40_Inputs_original'!B16+0-'WD40_Inputs_original'!B15+0)/'WD40_Inputs_original'!B17+0)*('WD40_Inputs_original'!B17+0-5))) -> 0.17106812 | H5: =IF(6>'WD40_Inputs_original'!B17+0,'WD40_Inputs_original'!B16+0,'WD40_Inputs_original'!B16+0-((('WD40_Inputs_original'!B16+0-'WD40_Inputs_original'!B15+0)/'WD40_Inputs_original'!B17+0)*('WD40_Inputs_original'!B17+0-6))) -> 0.17106812 | I5: =IF(7>'WD40_Inputs_original'!B17+0,'WD40_Inputs_original'!B16+0,'WD40_Inputs_original'!B16+0-((('WD40_Inputs_original'!B16+0-'WD40_Inputs_original'!B15+0)/'WD40_Inputs_original'!B17+0)*('WD40_Inputs_original'!B17+0-7))) -> 0.17106812 | J5: =IF(8>'WD40_Inputs_original'!B17+0,'WD40_Inputs_original'!B16+0,'WD40_Inputs_original'!B16+0-((('WD40_Inputs_original'!B16+0-'WD40_Inputs_original'!B15+0)/'WD40_Inputs_original'!B17+0)*('WD40_Inputs_original'!B17+0-8))) -> 0.17106812 | K5: =IF(9>'WD40_Inputs_original'!B17+0,'WD40_Inputs_original'!B16+0,'WD40_Inputs_original'!B16+0-((('WD40_Inputs_original'!B16+0-'WD40_Inputs_original'!B15+0)/'WD40_Inputs_original'!B17+0)*('WD40_Inputs_original'!B17+0-9))) -> 0.17106812 | L5: =IF(10>'WD40_Inputs_original'!B17+0,'WD40_Inputs_original'!B16+0,'WD40_Inputs_original'!B16+0-((('WD40_Inputs_original'!B16+0-'WD40_Inputs_original'!B15+0)/'WD40_Inputs_original'!B17+0)*('WD40_Inputs_original'!B17+0-10))) -> 0.17106812 | M5: =L5 -> 0.17106812
A6: Adjusted EBIT / USD m | B6: ='WD40_Inputs_original'!B44+0 -> 106.05967 | C6: =C5*C4 -> 111.36265 | D6: =D5*D4 -> 116.93078 | E6: =E5*E4 -> 122.77732 | F6: =F5*F4 -> 128.91619 | G6: =G5*G4 -> 135.362 | H6: =H5*H4 -> 141.45329 | I6: =I5*I4 -> 147.11142 | J6: =J5*J4 -> 152.26032 | ... L6: =L5*L4 -> 160.74883 | M6: =L5*M4 -> 164.76755
A7: Tax rate | B7: ='WD40_Inputs_original'!B11+0 -> 0.22200028 | C7: ='WD40_Inputs_original'!B11+0 -> 0.22200028 | D7: ='WD40_Inputs_original'!B11+0 -> 0.22200028 | E7: ='WD40_Inputs_original'!B11+0 -> 0.22200028 | F7: ='WD40_Inputs_original'!B11+0 -> 0.22200028 | G7: ='WD40_Inputs_original'!B11+0 -> 0.22200028 | H7: =G7+(('WD40_Inputs_original'!B46+0-'WD40_Inputs_original'!B11+0)/5) -> 0.22760022 | I7: =H7+(('WD40_Inputs_original'!B46+0-'WD40_Inputs_original'!B11+0)/5) -> 0.23320017 | J7: =I7+(('WD40_Inputs_original'!B46+0-'WD40_Inputs_original'!B11+0)/5) -> 0.23880011 | K7: =J7+(('WD40_Inputs_original'!B46+0-'WD40_Inputs_original'!B11+0)/5) -> 0.24440006 | L7: =K7+(('WD40_Inputs_original'!B46+0-'WD40_Inputs_original'!B11+0)/5) -> 0.25 | M7: ='WD40_Inputs_original'!B46+0 -> 0.25
A8: Opening NOL / USD m | C8: =B12 -> 0 | D8: =C12 -> 0 | E8: =D12 -> 0 | F8: =E12 -> 0 | G8: =F12 -> 0 | H8: =G12 -> 0 | I8: =H12 -> 0 | J8: =I12 -> 0 | ... M8: =L12 -> 0
A9: NOPAT / USD m | B9: =IF(B6>0,(B6*(1-B7)),B6) -> 82.514391 | C9: =IF(C6>0,IF(C6<B12,C6,C6-((C6-B12)*C7)),C6) -> 86.640111 | D9: =IF(D6>0,IF(D6<C12,D6,D6-((D6-C12)*D7)),D6) -> 90.972117 | E9: =IF(E6>0,IF(E6<D12,E6,E6-((E6-D12)*E7)),E6) -> 95.520722 | F9: =IF(F6>0,IF(F6<E12,F6,F6-((F6-E12)*F7)),F6) -> 100.29676 | G9: =IF(G6>0,IF(G6<F12,G6,G6-((G6-F12)*G7)),G6) -> 105.3116 | H9: =IF(H6>0,IF(H6<G12,H6,H6-((H6-G12)*H7)),H6) -> 109.25849 | I9: =IF(I6>0,IF(I6<H12,I6,I6-((I6-H12)*I7)),I6) -> 112.80501 | J9: =IF(J6>0,IF(J6<I12,J6,J6-((J6-I12)*J7)),J6) -> 115.90054 | ... L9: =IF(L6>0,IF(L6<K12,L6,L6-((L6-K12)*L7)),L6) -> 120.56162 | M9: =M6*(1-M7) -> 123.57566
A10: Reinvestment / USD m | C10: =IF('WD40_Inputs_original'!B30+0=1,IF('WD40_Inputs_original'!B31+0=0,((C4-B4)/C20),IF('WD40_Inputs_original'!B31+0=2,((E4-D4)/C20),IF('WD40_Inputs_original'!B31+0=3,((F4-E4)/C20),((D4-C4)/C20)))),((D4-C4)/C20)) -> 16.274606 | D10: =IF('WD40_Inputs_original'!B30+0=1,IF('WD40_Inputs_original'!B31+0=0,((D4-C4)/D20),IF('WD40_Inputs_original'!B31+0=2,((F4-E4)/D20),IF('WD40_Inputs_original'!B31+0=3,((G4-F4)/D20),((E4-D4)/D20)))),((E4-D4)/D20)) -> 17.088337 | E10: =IF('WD40_Inputs_original'!B30+0=1,IF('WD40_Inputs_original'!B31+0=0,((E4-D4)/E20),IF('WD40_Inputs_original'!B31+0=2,((G4-F4)/E20),IF('WD40_Inputs_original'!B31+0=3,((H4-G4)/E20),((F4-E4)/E20)))),((F4-E4)/E20)) -> 17.942753 | F10: =IF('WD40_Inputs_original'!B30+0=1,IF('WD40_Inputs_original'!B31+0=0,((F4-E4)/F20),IF('WD40_Inputs_original'!B31+0=2,((H4-G4)/F20),IF('WD40_Inputs_original'!B31+0=3,((I4-H4)/F20),((G4-F4)/F20)))),((G4-F4)/F20)) -> 18.839891 | G10: =IF('WD40_Inputs_original'!B30+0=1,IF('WD40_Inputs_original'!B31+0=0,((G4-F4)/G20),IF('WD40_Inputs_original'!B31+0=2,((I4-H4)/G20),IF('WD40_Inputs_original'!B31+0=3,((J4-I4)/G20),((H4-G4)/G20)))),((H4-G4)/G20)) -> 17.803697 | H10: =IF('WD40_Inputs_original'!B30+0=1,IF('WD40_Inputs_original'!B31+0=0,((H4-G4)/H20),IF('WD40_Inputs_original'!B31+0=2,((J4-I4)/H20),IF('WD40_Inputs_original'!B31+0=3,((K4-J4)/H20),((I4-H4)/H20)))),((I4-H4)/H20)) -> 16.537656 | I10: =IF('WD40_Inputs_original'!B30+0=1,IF('WD40_Inputs_original'!B31+0=0,((I4-H4)/I20),IF('WD40_Inputs_original'!B31+0=2,((K4-J4)/I20),IF('WD40_Inputs_original'!B31+0=3,((L4-K4)/I20),((J4-I4)/I20)))),((J4-I4)/I20)) -> 15.049267 | J10: =IF('WD40_Inputs_original'!B30+0=1,IF('WD40_Inputs_original'!B31+0=0,((J4-I4)/J20),IF('WD40_Inputs_original'!B31+0=2,((L4-K4)/J20),IF('WD40_Inputs_original'!B31+0=3,((M4-L4)/J20),((K4-J4)/J20)))),((K4-J4)/J20)) -> 13.35085 | K10: =IF('WD40_Inputs_original'!B30+0=1,IF('WD40_Inputs_original'!B31+0=0,((K4-J4)/K20),IF('WD40_Inputs_original'!B31+0=2,((M4-L4)/K20),IF('WD40_Inputs_original'!B31+0=3,((M4*M3)/K20),((L4-K4)/K20)))),((L4-K4)/K20)) -> 11.45948 | L10: =IF('WD40_Inputs_original'!B30+0=1,IF('WD40_Inputs_original'!B31+0=0,((L4-K4)/L20),IF('WD40_Inputs_original'!B31+0=2,((M4*M3)/L20),IF('WD40_Inputs_original'!B31+0=3,((K10*(1+M3)*L20)/L20),((M4-L4)/L20)))),((M4-L4)/L20)) -> 11.745967 | M10: =B30*M9 -> 38.617395
A11: FCFF / USD m | C11: =C9-C10 -> 70.365505 | D11: =D9-D10 -> 73.88378 | E11: =E9-E10 -> 77.577969 | F11: =F9-F10 -> 81.456867 | G11: =G9-G10 -> 87.507899 | H11: =H9-H10 -> 92.720831 | I11: =I9-I10 -> 97.755744 | J11: =J9-J10 -> 102.54969 | ... M11: =M9-M10 -> 84.958269
A12: Closing NOL / USD m | B12: ='WD40_Inputs_original'!B28+0 -> 0 | C12: =IF(C6<0,(B12-C6),IF(B12>C6,(B12-C6),0)) -> 0 | D12: =IF(D6<0,(C12-D6),IF(C12>D6,(C12-D6),0)) -> 0 | E12: =IF(E6<0,(D12-E6),IF(D12>E6,(D12-E6),0)) -> 0 | F12: =IF(F6<0,(E12-F6),IF(E12>F6,(E12-F6),0)) -> 0 | G12: =IF(G6<0,(F12-G6),IF(F12>G6,(F12-G6),0)) -> 0 | H12: =IF(H6<0,(G12-H6),IF(G12>H6,(G12-H6),0)) -> 0 | I12: =IF(I6<0,(H12-I6),IF(H12>I6,(H12-I6),0)) -> 0 | J12: =IF(J6<0,(I12-J6),IF(I12>J6,(I12-J6),0)) -> 0 | ... M12: =IF(M6<0,(L12-M6),IF(L12>M6,(L12-M6),0)) -> 0
A13: WACC | C13: ='WD40_Inputs_original'!B20+0 -> 0.09 | D13: ='WD40_Inputs_original'!B20+0 -> 0.09 | E13: ='WD40_Inputs_original'!B20+0 -> 0.09 | F13: ='WD40_Inputs_original'!B20+0 -> 0.09 | G13: ='WD40_Inputs_original'!B20+0 -> 0.09 | H13: =G13-(('WD40_Inputs_original'!B20+0-'WD40_Inputs_original'!B21+0)/5) -> 0.088 | I13: =H13-(('WD40_Inputs_original'!B20+0-'WD40_Inputs_original'!B21+0)/5) -> 0.086 | J13: =I13-(('WD40_Inputs_original'!B20+0-'WD40_Inputs_original'!B21+0)/5) -> 0.084 | K13: =J13-(('WD40_Inputs_original'!B20+0-'WD40_Inputs_original'!B21+0)/5) -> 0.082 | L13: =K13-(('WD40_Inputs_original'!B20+0-'WD40_Inputs_original'!B21+0)/5) -> 0.08 | M13: ='WD40_Inputs_original'!B21+0 -> 0.08
A14: Cumulative discount factor | C14: =1*(1/(1+C13)) -> 0.91743119 | D14: =C14*(1/(1+D13)) -> 0.84167999 | E14: =D14*(1/(1+E13)) -> 0.77218348 | F14: =E14*(1/(1+F13)) -> 0.70842521 | G14: =F14*(1/(1+G13)) -> 0.64993139 | H14: =G14*(1/(1+H13)) -> 0.59736341 | I14: =H14*(1/(1+I13)) -> 0.55005839 | J14: =I14*(1/(1+J13)) -> 0.50743393 | K14: =J14*(1/(1+K13)) -> 0.46897776 | L14: =K14*(1/(1+L13)) -> 0.43423867
A15: PV FCFF / USD m | C15: =C11*C14 -> 64.555509 | D15: =D11*D14 -> 62.186499 | E15: =E11*E14 -> 59.904426 | F15: =F11*F14 -> 57.706099 | G15: =G11*G14 -> 56.87413 | H15: =H11*H14 -> 55.388032 | I15: =I11*I14 -> 53.771367 | J15: =J11*J14 -> 52.037191 | ... L15: =L11*L14 -> 47.251965
A16: Opening invested capital / USD m | C16: =B17 -> 313.437 | D16: =C17 -> 329.71161 | E16: =D17 -> 346.79994 | F16: =E17 -> 364.7427 | G16: =F17 -> 383.58259 | H16: =G17 -> 401.38628 | I16: =H17 -> 417.92394 | J16: =I17 -> 432.97321 | ... L16: =K17 -> 457.78354
A17: Closing invested capital / USD m | B17: ='WD40_Inputs_original'!B45+0 -> 313.437 | C17: =B17+C10 -> 329.71161 | D17: =C17+D10 -> 346.79994 | E17: =D17+E10 -> 364.7427 | F17: =E17+F10 -> 383.58259 | G17: =F17+G10 -> 401.38628 | H17: =G17+H10 -> 417.92394 | I17: =H17+I10 -> 432.97321 | J17: =I17+J10 -> 446.32406 | ... L17: =K17+L10 -> 469.5295
A18: Economic profit / USD m | C18: =C9-(C13*B17) -> 58.430781 | D18: =D9-(D13*C17) -> 61.298072 | E18: =E9-(E13*D17) -> 64.308728 | F18: =F9-(F13*E17) -> 67.469916 | G18: =G9-(G13*F17) -> 70.789164 | H18: =H9-(H13*G17) -> 73.936495 | I18: =I9-(I13*H17) -> 76.863552 | J18: =J9-(J13*I17) -> 79.530788 | ... L18: =L9-(L13*K17) -> 83.93894
A19: PV economic profit / USD m | C19: =C18*C14 -> 53.606221 | D19: =D18*D14 -> 51.593361 | E19: =E18*E14 -> 49.658137 | F19: =F18*F14 -> 47.797389 | G19: =G18*G14 -> 46.008099 | H19: =H18*H14 -> 44.166956 | I19: =I18*I14 -> 42.279442 | J19: =J18*J14 -> 40.356621 | ... L19: =L18*L14 -> 36.449533
A20: Sales to capital | C20: ='WD40_Inputs_original'!B18+0 -> 2 | D20: ='WD40_Inputs_original'!B18+0 -> 2 | E20: ='WD40_Inputs_original'!B18+0 -> 2 | F20: ='WD40_Inputs_original'!B18+0 -> 2 | G20: ='WD40_Inputs_original'!B18+0 -> 2 | H20: ='WD40_Inputs_original'!B19+0 -> 2 | I20: ='WD40_Inputs_original'!B19+0 -> 2 | J20: ='WD40_Inputs_original'!B19+0 -> 2 | K20: ='WD40_Inputs_original'!B19+0 -> 2 | L20: ='WD40_Inputs_original'!B19+0 -> 2
A21: Terminal value / USD m | B21: =M11/(M13-M3) -> 1544.6958
A22: PV terminal value / USD m | B22: =B21*L14 -> 670.76664
A23: PV forecast FCFF / USD m | B23: =SUM(C15:L15) -> 559.87453
A24: Undistressed operating value / USD m | B24: =B22+B23 -> 1230.6412
A25: Distress proceeds / USD m | B25: =IF('WD40_Inputs_original'!B34+0=1,(('WD40_Inputs_original'!B4+0+'WD40_Inputs_original'!B5+0)*'WD40_Inputs_original'!B33+0),(B24*'WD40_Inputs_original'!B33+0)) -> 615.32058
A26: Operating value / USD m | B26: =(B24*(1-'WD40_Inputs_original'!B32+0))+(B25*'WD40_Inputs_original'!B32+0) -> 1230.6412
A27: Equity value / USD m | B27: =B26-'WD40_Inputs_original'!B5+0-'WD40_Inputs_original'!B8+0+'WD40_Inputs_original'!B48+0+'WD40_Inputs_original'!B7+0 -> 1201.7762
A28: Value per share / USD | B28: =IF('WD40_Inputs_original'!B21+0>'WD40_Inputs_original'!B22+0,IF('WD40_Inputs_original'!B20+0>0,IF('WD40_Inputs_original'!B9+0>0,IF('WD40_Inputs_original'!B18+0>0,IF('WD40_Inputs_original'!B19+0>0,IF(IF('WD40_Inputs_original'!B23+0=1,IF('WD40_Inputs_original'!B24+0>0,1,0),1)=1,IF(IF('WD40_Inputs_original'!B23+0=1,IF('WD40_Inputs_original'!B24+0>='WD40_Inputs_original'!B22+0,1,0),1)=1,B27/'WD40_Inputs_original'!B9+0,"Blocked: terminal reinvestment exceeds NOPAT"),"Blocked: active terminal ROIC must be positive"),"Blocked: years 6-10 sales to capital must be positive"),"Blocked: years 1-5 sales to capital must be positive"),"Blocked: shares must be positive"),"Blocked: starting WACC must be positive"),"Blocked: terminal WACC must exceed growth") -> 88.150296
A29: Terminal value share | B29: =B22/B24 -> 0.54505461
A30: Terminal reinvestment rate | B30: =IF(M3>0,(M3/IF('WD40_Inputs_original'!B23+0=1,'WD40_Inputs_original'!B24+0,L13)),0) -> 0.3125
A31: EVA recurring terminal value / USD m | B31: =IF(M3>0,((M9*(1-(M13/IF('WD40_Inputs_original'!B23+0=1,'WD40_Inputs_original'!B24+0,L13))))/(M13-M3)),(M9/(M13-M3))) -> -4.9889653e-13
A32: EVA terminal capital transition / USD m | B32: =IF(M3>0,((M9/IF('WD40_Inputs_original'!B23+0=1,'WD40_Inputs_original'!B24+0,L13))-L17),(0-L17)) -> 1075.1663
A33: EVA terminal value / USD m | B33: =B31+B32 -> 1075.1663
A34: EVA operating value / USD m | B34: =B17+SUM(C19:L19)+(B33*L14) -> 1230.6412
A35: EVA minus DCF / USD m | B35: =B34-B24 -> 2.2737368e-13

Sheet WD40_Inputs_bear
A1: WD40_Inputs_bear | B1: Value
A2: Revenue FY2025 / USD m | B2: ='WD40_Regions_bear'!E2+0 -> 619.985
A3: Reported EBIT FY2025 / USD m | B3: 103.793
A4: Adjusted book equity / USD m | B4: 268.472
A5: Interest-bearing debt / USD m | B5: 86.995
A6: Cash / USD m | B6: 58.13
A7: Nonoperating assets / USD m | B7: 0
A8: Minority interests / USD m | B8: 0
A9: Valuation dilution proxy / million shares | B9: 13.633263
A10: Historical reference price / USD per share | B10: 216.04
A11: Normalized starting tax rate | B11: 0.22200028
A12: Terminal tax rate | B12: 0.25
A13: Revenue growth year 1 | B13: ='WD40_Regions_bear'!E47+0 -> 0.028936942
A14: Revenue growth years 2-5 | B14: ='WD40_Regions_bear'!E48+0 -> 0.029813668
A15: Adjusted EBIT margin year 1 | B15: =B44/B2 -> 0.17106812
A16: Target adjusted EBIT margin | B16: =B15+0 -> 0.17106812
A17: Margin convergence year | B17: 5
A18: Sales to capital years 1-5 | B18: 2
A19: Sales to capital years 6-10 | B19: =B18+0 -> 2
A20: WACC years 1-5 | B20: 0.09
A21: Terminal WACC | B21: 0.08
A22: Terminal growth | B22: 0.025
A23: Use explicit terminal ROIC / 1=yes | B23: 0
A24: Explicit terminal ROIC | B24: 0.15
A25: Current R&D / USD m | B25: 8.7
A26: R&D amortization life / years | B26: 3
A27: Capitalize R&D / 1=yes | B27: 1
A28: Starting NOL / USD m | B28: 0
A29: Hold starting tax rate / 1=yes | B29: 0
A30: Override reinvestment timing / 1=yes | B30: 0
A31: Reinvestment growth lead / years | B31: 1
... A41: R&D 4 years prior / USD m | B41: 5.6
A42: R&D amortization / USD m | B42: =0+IF(1<=B26,(B38/B26),0)+IF(2<=B26,(B39/B26),0)+IF(3<=B26,(B40/B26),0)+IF(4<=B26,(B41/B26),0) -> 6.4333333
A43: Unamortized R&D asset / USD m | B43: =B25+IF(1<B26,(B38*((B26-1)/B26)),0)+IF(2<B26,(B39*((B26-2)/B26)),0)+IF(3<B26,(B40*((B26-3)/B26)),0)+IF(4<B26,(B41*((B26-4)/B26)),0) -> 16.1
A44: R&D-adjusted base EBIT / USD m | B44: =B3+IF(B27=1,(B25-B42),0) -> 106.05967
A45: Base invested capital / USD m | B45: =B4+B5-B6+IF(B27=1,B43,0) -> 313.437
A46: Effective terminal tax rate | B46: =IF(B29=1,B11,B12) -> 0.25
A47: Effective terminal ROIC | B47: =IF(B23=1,B24,B21) -> 0.08
A48: Cash after explicit haircut / USD m | B48: =B6-IF(B37=1,(B35*(B12-B36)),0) -> 58.13

Sheet WD40_DCF_bear
A1: WD40_DCF_bear | B1: Base | C1: Y1 | D1: Y2 | E1: Y3 | F1: Y4 | G1: Y5 | H1: Y6 | I1: Y7 | J1: Y8 | K1: Y9 | L1: Y10 | M1: Terminal
A2: Year | B2: 0 | C2: 1 | D2: 2 | E2: 3 | F2: 4 | G2: 5 | H2: 6 | I2: 7 | J2: 8 | K2: 9 | L2: 10 | M2: 11
A3: Revenue growth | C3: ='WD40_Inputs_bear'!B13+0 -> 0.028936942 | D3: ='WD40_Inputs_bear'!B14+0 -> 0.029813668 | E3: ='WD40_Inputs_bear'!B14+0 -> 0.029813668 | F3: ='WD40_Inputs_bear'!B14+0 -> 0.029813668 | G3: ='WD40_Inputs_bear'!B14+0 -> 0.029813668 | H3: ='WD40_Inputs_bear'!B14+0-((('WD40_Inputs_bear'!B14+0-'WD40_Inputs_bear'!B22+0)/5)*1) -> 0.028850934 | I3: ='WD40_Inputs_bear'!B14+0-((('WD40_Inputs_bear'!B14+0-'WD40_Inputs_bear'!B22+0)/5)*2) -> 0.027888201 | J3: ='WD40_Inputs_bear'!B14+0-((('WD40_Inputs_bear'!B14+0-'WD40_Inputs_bear'!B22+0)/5)*3) -> 0.026925467 | K3: ='WD40_Inputs_bear'!B14+0-((('WD40_Inputs_bear'!B14+0-'WD40_Inputs_bear'!B22+0)/5)*4) -> 0.025962734 | L3: ='WD40_Inputs_bear'!B14+0-((('WD40_Inputs_bear'!B14+0-'WD40_Inputs_bear'!B22+0)/5)*5) -> 0.025 | M3: ='WD40_Inputs_bear'!B22+0 -> 0.025
A4: Revenue / USD m | B4: ='WD40_Inputs_bear'!B2+0 -> 619.985 | C4: =B4*(1+C3) -> 637.92547 | D4: =C4*(1+D3) -> 656.94437 | E4: =D4*(1+E3) -> 676.53029 | F4: =E4*(1+F3) -> 696.70014 | G4: =F4*(1+G3) -> 717.47133 | H4: =G4*(1+H3) -> 738.17104 | I4: =H4*(1+I3) -> 758.75731 | J4: =I4*(1+J3) -> 779.1872 | ... M4: =L4*(1+M3) -> 839.88752
A5: Adjusted EBIT margin | B5: =B6/B4 -> 0.17106812 | C5: ='WD40_Inputs_bear'!B15+0 -> 0.17106812 | D5: =IF(2>'WD40_Inputs_bear'!B17+0,'WD40_Inputs_bear'!B16+0,'WD40_Inputs_bear'!B16+0-((('WD40_Inputs_bear'!B16+0-'WD40_Inputs_bear'!B15+0)/'WD40_Inputs_bear'!B17+0)*('WD40_Inputs_bear'!B17+0-2))) -> 0.17106812 | E5: =IF(3>'WD40_Inputs_bear'!B17+0,'WD40_Inputs_bear'!B16+0,'WD40_Inputs_bear'!B16+0-((('WD40_Inputs_bear'!B16+0-'WD40_Inputs_bear'!B15+0)/'WD40_Inputs_bear'!B17+0)*('WD40_Inputs_bear'!B17+0-3))) -> 0.17106812 | F5: =IF(4>'WD40_Inputs_bear'!B17+0,'WD40_Inputs_bear'!B16+0,'WD40_Inputs_bear'!B16+0-((('WD40_Inputs_bear'!B16+0-'WD40_Inputs_bear'!B15+0)/'WD40_Inputs_bear'!B17+0)*('WD40_Inputs_bear'!B17+0-4))) -> 0.17106812 | G5: =IF(5>'WD40_Inputs_bear'!B17+0,'WD40_Inputs_bear'!B16+0,'WD40_Inputs_bear'!B16+0-((('WD40_Inputs_bear'!B16+0-'WD40_Inputs_bear'!B15+0)/'WD40_Inputs_bear'!B17+0)*('WD40_Inputs_bear'!B17+0-5))) -> 0.17106812 | H5: =IF(6>'WD40_Inputs_bear'!B17+0,'WD40_Inputs_bear'!B16+0,'WD40_Inputs_bear'!B16+0-((('WD40_Inputs_bear'!B16+0-'WD40_Inputs_bear'!B15+0)/'WD40_Inputs_bear'!B17+0)*('WD40_Inputs_bear'!B17+0-6))) -> 0.17106812 | I5: =IF(7>'WD40_Inputs_bear'!B17+0,'WD40_Inputs_bear'!B16+0,'WD40_Inputs_bear'!B16+0-((('WD40_Inputs_bear'!B16+0-'WD40_Inputs_bear'!B15+0)/'WD40_Inputs_bear'!B17+0)*('WD40_Inputs_bear'!B17+0-7))) -> 0.17106812 | J5: =IF(8>'WD40_Inputs_bear'!B17+0,'WD40_Inputs_bear'!B16+0,'WD40_Inputs_bear'!B16+0-((('WD40_Inputs_bear'!B16+0-'WD40_Inputs_bear'!B15+0)/'WD40_Inputs_bear'!B17+0)*('WD40_Inputs_bear'!B17+0-8))) -> 0.17106812 | K5: =IF(9>'WD40_Inputs_bear'!B17+0,'WD40_Inputs_bear'!B16+0,'WD40_Inputs_bear'!B16+0-((('WD40_Inputs_bear'!B16+0-'WD40_Inputs_bear'!B15+0)/'WD40_Inputs_bear'!B17+0)*('WD40_Inputs_bear'!B17+0-9))) -> 0.17106812 | L5: =IF(10>'WD40_Inputs_bear'!B17+0,'WD40_Inputs_bear'!B16+0,'WD40_Inputs_bear'!B16+0-((('WD40_Inputs_bear'!B16+0-'WD40_Inputs_bear'!B15+0)/'WD40_Inputs_bear'!B17+0)*('WD40_Inputs_bear'!B17+0-10))) -> 0.17106812 | M5: =L5 -> 0.17106812
A6: Adjusted EBIT / USD m | B6: ='WD40_Inputs_bear'!B44+0 -> 106.05967 | C6: =C5*C4 -> 109.12871 | D6: =D5*D4 -> 112.38224 | E6: =E5*E4 -> 115.73276 | F6: =F5*F4 -> 119.18318 | G6: =G5*G4 -> 122.73647 | H6: =H5*H4 -> 126.27753 | I6: =I5*I4 -> 129.79918 | J6: =J5*J4 -> 133.29409 | ... L6: =L5*L4 -> 140.17364 | M6: =L5*M4 -> 143.67798
A7: Tax rate | B7: ='WD40_Inputs_bear'!B11+0 -> 0.22200028 | C7: ='WD40_Inputs_bear'!B11+0 -> 0.22200028 | D7: ='WD40_Inputs_bear'!B11+0 -> 0.22200028 | E7: ='WD40_Inputs_bear'!B11+0 -> 0.22200028 | F7: ='WD40_Inputs_bear'!B11+0 -> 0.22200028 | G7: ='WD40_Inputs_bear'!B11+0 -> 0.22200028 | H7: =G7+(('WD40_Inputs_bear'!B46+0-'WD40_Inputs_bear'!B11+0)/5) -> 0.22760022 | I7: =H7+(('WD40_Inputs_bear'!B46+0-'WD40_Inputs_bear'!B11+0)/5) -> 0.23320017 | J7: =I7+(('WD40_Inputs_bear'!B46+0-'WD40_Inputs_bear'!B11+0)/5) -> 0.23880011 | K7: =J7+(('WD40_Inputs_bear'!B46+0-'WD40_Inputs_bear'!B11+0)/5) -> 0.24440006 | L7: =K7+(('WD40_Inputs_bear'!B46+0-'WD40_Inputs_bear'!B11+0)/5) -> 0.25 | M7: ='WD40_Inputs_bear'!B46+0 -> 0.25
A8: Opening NOL / USD m | C8: =B12 -> 0 | D8: =C12 -> 0 | E8: =D12 -> 0 | F8: =E12 -> 0 | G8: =F12 -> 0 | H8: =G12 -> 0 | I8: =H12 -> 0 | J8: =I12 -> 0 | ... M8: =L12 -> 0
A9: NOPAT / USD m | B9: =IF(B6>0,(B6*(1-B7)),B6) -> 82.514391 | C9: =IF(C6>0,IF(C6<B12,C6,C6-((C6-B12)*C7)),C6) -> 84.902106 | D9: =IF(D6>0,IF(D6<C12,D6,D6-((D6-C12)*D7)),D6) -> 87.433349 | E9: =IF(E6>0,IF(E6<D12,E6,E6-((E6-D12)*E7)),E6) -> 90.040058 | F9: =IF(F6>0,IF(F6<E12,F6,F6-((F6-E12)*F7)),F6) -> 92.724482 | G9: =IF(G6>0,IF(G6<F12,G6,G6-((G6-F12)*G7)),G6) -> 95.488939 | H9: =IF(H6>0,IF(H6<G12,H6,H6-((H6-G12)*H7)),H6) -> 97.536737 | I9: =IF(I6>0,IF(I6<H12,I6,I6-((I6-H12)*I7)),I6) -> 99.529993 | J9: =IF(J6>0,IF(J6<I12,J6,J6-((J6-I12)*J7)),J6) -> 101.46344 | ... L9: =IF(L6>0,IF(L6<K12,L6,L6-((L6-K12)*L7)),L6) -> 105.13023 | M9: =M6*(1-M7) -> 107.75848
A10: Reinvestment / USD m | C10: =IF('WD40_Inputs_bear'!B30+0=1,IF('WD40_Inputs_bear'!B31+0=0,((C4-B4)/C20),IF('WD40_Inputs_bear'!B31+0=2,((E4-D4)/C20),IF('WD40_Inputs_bear'!B31+0=3,((F4-E4)/C20),((D4-C4)/C20)))),((D4-C4)/C20)) -> 9.5094491 | D10: =IF('WD40_Inputs_bear'!B30+0=1,IF('WD40_Inputs_bear'!B31+0=0,((D4-C4)/D20),IF('WD40_Inputs_bear'!B31+0=2,((F4-E4)/D20),IF('WD40_Inputs_bear'!B31+0=3,((G4-F4)/D20),((E4-D4)/D20)))),((E4-D4)/D20)) -> 9.7929607 | E10: =IF('WD40_Inputs_bear'!B30+0=1,IF('WD40_Inputs_bear'!B31+0=0,((E4-D4)/E20),IF('WD40_Inputs_bear'!B31+0=2,((G4-F4)/E20),IF('WD40_Inputs_bear'!B31+0=3,((H4-G4)/E20),((F4-E4)/E20)))),((F4-E4)/E20)) -> 10.084925 | F10: =IF('WD40_Inputs_bear'!B30+0=1,IF('WD40_Inputs_bear'!B31+0=0,((F4-E4)/F20),IF('WD40_Inputs_bear'!B31+0=2,((H4-G4)/F20),IF('WD40_Inputs_bear'!B31+0=3,((I4-H4)/F20),((G4-F4)/F20)))),((G4-F4)/F20)) -> 10.385593 | G10: =IF('WD40_Inputs_bear'!B30+0=1,IF('WD40_Inputs_bear'!B31+0=0,((G4-F4)/G20),IF('WD40_Inputs_bear'!B31+0=2,((I4-H4)/G20),IF('WD40_Inputs_bear'!B31+0=3,((J4-I4)/G20),((H4-G4)/G20)))),((H4-G4)/G20)) -> 10.349859 | H10: =IF('WD40_Inputs_bear'!B30+0=1,IF('WD40_Inputs_bear'!B31+0=0,((H4-G4)/H20),IF('WD40_Inputs_bear'!B31+0=2,((J4-I4)/H20),IF('WD40_Inputs_bear'!B31+0=3,((K4-J4)/H20),((I4-H4)/H20)))),((I4-H4)/H20)) -> 10.293131 | I10: =IF('WD40_Inputs_bear'!B30+0=1,IF('WD40_Inputs_bear'!B31+0=0,((I4-H4)/I20),IF('WD40_Inputs_bear'!B31+0=2,((K4-J4)/I20),IF('WD40_Inputs_bear'!B31+0=3,((L4-K4)/I20),((J4-I4)/I20)))),((J4-I4)/I20)) -> 10.214947 | J10: =IF('WD40_Inputs_bear'!B30+0=1,IF('WD40_Inputs_bear'!B31+0=0,((J4-I4)/J20),IF('WD40_Inputs_bear'!B31+0=2,((L4-K4)/J20),IF('WD40_Inputs_bear'!B31+0=3,((M4-L4)/J20),((K4-J4)/J20)))),((K4-J4)/J20)) -> 10.114915 | K10: =IF('WD40_Inputs_bear'!B30+0=1,IF('WD40_Inputs_bear'!B31+0=0,((K4-J4)/K20),IF('WD40_Inputs_bear'!B31+0=2,((M4-L4)/K20),IF('WD40_Inputs_bear'!B31+0=3,((M4*M3)/K20),((L4-K4)/K20)))),((L4-K4)/K20)) -> 9.9927129 | L10: =IF('WD40_Inputs_bear'!B30+0=1,IF('WD40_Inputs_bear'!B31+0=0,((L4-K4)/L20),IF('WD40_Inputs_bear'!B31+0=2,((M4*M3)/L20),IF('WD40_Inputs_bear'!B31+0=3,((K10*(1+M3)*L20)/L20),((M4-L4)/L20)))),((M4-L4)/L20)) -> 10.242531 | M10: =B30*M9 -> 33.674526
A11: FCFF / USD m | C11: =C9-C10 -> 75.392656 | D11: =D9-D10 -> 77.640388 | E11: =E9-E10 -> 79.955133 | F11: =F9-F10 -> 82.338889 | G11: =G9-G10 -> 85.13908 | H11: =H9-H10 -> 87.243606 | I11: =I9-I10 -> 89.315045 | J11: =J9-J10 -> 91.34853 | ... M11: =M9-M10 -> 74.083957
A12: Closing NOL / USD m | B12: ='WD40_Inputs_bear'!B28+0 -> 0 | C12: =IF(C6<0,(B12-C6),IF(B12>C6,(B12-C6),0)) -> 0 | D12: =IF(D6<0,(C12-D6),IF(C12>D6,(C12-D6),0)) -> 0 | E12: =IF(E6<0,(D12-E6),IF(D12>E6,(D12-E6),0)) -> 0 | F12: =IF(F6<0,(E12-F6),IF(E12>F6,(E12-F6),0)) -> 0 | G12: =IF(G6<0,(F12-G6),IF(F12>G6,(F12-G6),0)) -> 0 | H12: =IF(H6<0,(G12-H6),IF(G12>H6,(G12-H6),0)) -> 0 | I12: =IF(I6<0,(H12-I6),IF(H12>I6,(H12-I6),0)) -> 0 | J12: =IF(J6<0,(I12-J6),IF(I12>J6,(I12-J6),0)) -> 0 | ... M12: =IF(M6<0,(L12-M6),IF(L12>M6,(L12-M6),0)) -> 0
A13: WACC | C13: ='WD40_Inputs_bear'!B20+0 -> 0.09 | D13: ='WD40_Inputs_bear'!B20+0 -> 0.09 | E13: ='WD40_Inputs_bear'!B20+0 -> 0.09 | F13: ='WD40_Inputs_bear'!B20+0 -> 0.09 | G13: ='WD40_Inputs_bear'!B20+0 -> 0.09 | H13: =G13-(('WD40_Inputs_bear'!B20+0-'WD40_Inputs_bear'!B21+0)/5) -> 0.088 | I13: =H13-(('WD40_Inputs_bear'!B20+0-'WD40_Inputs_bear'!B21+0)/5) -> 0.086 | J13: =I13-(('WD40_Inputs_bear'!B20+0-'WD40_Inputs_bear'!B21+0)/5) -> 0.084 | K13: =J13-(('WD40_Inputs_bear'!B20+0-'WD40_Inputs_bear'!B21+0)/5) -> 0.082 | L13: =K13-(('WD40_Inputs_bear'!B20+0-'WD40_Inputs_bear'!B21+0)/5) -> 0.08 | M13: ='WD40_Inputs_bear'!B21+0 -> 0.08
A14: Cumulative discount factor | C14: =1*(1/(1+C13)) -> 0.91743119 | D14: =C14*(1/(1+D13)) -> 0.84167999 | E14: =D14*(1/(1+E13)) -> 0.77218348 | F14: =E14*(1/(1+F13)) -> 0.70842521 | G14: =F14*(1/(1+G13)) -> 0.64993139 | H14: =G14*(1/(1+H13)) -> 0.59736341 | I14: =H14*(1/(1+I13)) -> 0.55005839 | J14: =I14*(1/(1+J13)) -> 0.50743393 | K14: =J14*(1/(1+K13)) -> 0.46897776 | L14: =K14*(1/(1+L13)) -> 0.43423867
A15: PV FCFF / USD m | C15: =C11*C14 -> 69.167575 | D15: =D11*D14 -> 65.348361 | E15: =E11*E14 -> 61.740033 | F15: =F11*F14 -> 58.330945 | G15: =G11*G14 -> 55.33456 | H15: =H11*H14 -> 52.116138 | I15: =I11*I14 -> 49.12849 | J15: =J11*J14 -> 46.353344 | ... L15: =L11*L14 -> 41.203906
A16: Opening invested capital / USD m | C16: =B17 -> 313.437 | D16: =C17 -> 322.94645 | E16: =D17 -> 332.73941 | F16: =E17 -> 342.82433 | G16: =F17 -> 353.20993 | H16: =G17 -> 363.55979 | I16: =H17 -> 373.85292 | J16: =I17 -> 384.06787 | ... L16: =K17 -> 404.17549
A17: Closing invested capital / USD m | B17: ='WD40_Inputs_bear'!B45+0 -> 313.437 | C17: =B17+C10 -> 322.94645 | D17: =C17+D10 -> 332.73941 | E17: =D17+E10 -> 342.82433 | F17: =E17+F10 -> 353.20993 | G17: =F17+G10 -> 363.55979 | H17: =G17+H10 -> 373.85292 | I17: =H17+I10 -> 384.06787 | J17: =I17+J10 -> 394.18278 | ... L17: =K17+L10 -> 414.41802
A18: Economic profit / USD m | C18: =C9-(C13*B17) -> 56.692776 | D18: =D9-(D13*C17) -> 58.368168 | E18: =E9-(E13*D17) -> 60.093511 | F18: =F9-(F13*E17) -> 61.870292 | G18: =G9-(G13*F17) -> 63.700045 | H18: =H9-(H13*G17) -> 65.543476 | I18: =I9-(I13*H17) -> 67.378642 | J18: =J9-(J13*I17) -> 69.201744 | ... L18: =L9-(L13*K17) -> 72.796187
A19: PV economic profit / USD m | C19: =C18*C14 -> 52.011721 | D19: =D18*D14 -> 49.12732 | E19: =E18*E14 -> 46.403216 | F19: =F18*F14 -> 43.830475 | G19: =G18*G14 -> 41.400659 | H19: =H18*H14 -> 39.153274 | I19: =I18*I14 -> 37.062187 | J19: =J18*J14 -> 35.115313 | ... L19: =L18*L14 -> 31.610919
A20: Sales to capital | C20: ='WD40_Inputs_bear'!B18+0 -> 2 | D20: ='WD40_Inputs_bear'!B18+0 -> 2 | E20: ='WD40_Inputs_bear'!B18+0 -> 2 | F20: ='WD40_Inputs_bear'!B18+0 -> 2 | G20: ='WD40_Inputs_bear'!B18+0 -> 2 | H20: ='WD40_Inputs_bear'!B19+0 -> 2 | I20: ='WD40_Inputs_bear'!B19+0 -> 2 | J20: ='WD40_Inputs_bear'!B19+0 -> 2 | K20: ='WD40_Inputs_bear'!B19+0 -> 2 | L20: ='WD40_Inputs_bear'!B19+0 -> 2
A21: Terminal value / USD m | B21: =M11/(M13-M3) -> 1346.981
A22: PV terminal value / USD m | B22: =B21*L14 -> 584.91124
A23: PV forecast FCFF / USD m | B23: =SUM(C15:L15) -> 542.49735
A24: Undistressed operating value / USD m | B24: =B22+B23 -> 1127.4086
A25: Distress proceeds / USD m | B25: =IF('WD40_Inputs_bear'!B34+0=1,(('WD40_Inputs_bear'!B4+0+'WD40_Inputs_bear'!B5+0)*'WD40_Inputs_bear'!B33+0),(B24*'WD40_Inputs_bear'!B33+0)) -> 563.7043
A26: Operating value / USD m | B26: =(B24*(1-'WD40_Inputs_bear'!B32+0))+(B25*'WD40_Inputs_bear'!B32+0) -> 1127.4086
A27: Equity value / USD m | B27: =B26-'WD40_Inputs_bear'!B5+0-'WD40_Inputs_bear'!B8+0+'WD40_Inputs_bear'!B48+0+'WD40_Inputs_bear'!B7+0 -> 1098.5436
A28: Value per share / USD | B28: =IF('WD40_Inputs_bear'!B21+0>'WD40_Inputs_bear'!B22+0,IF('WD40_Inputs_bear'!B20+0>0,IF('WD40_Inputs_bear'!B9+0>0,IF('WD40_Inputs_bear'!B18+0>0,IF('WD40_Inputs_bear'!B19+0>0,IF(IF('WD40_Inputs_bear'!B23+0=1,IF('WD40_Inputs_bear'!B24+0>0,1,0),1)=1,IF(IF('WD40_Inputs_bear'!B23+0=1,IF('WD40_Inputs_bear'!B24+0>='WD40_Inputs_bear'!B22+0,1,0),1)=1,B27/'WD40_Inputs_bear'!B9+0,"Blocked: terminal reinvestment exceeds NOPAT"),"Blocked: active terminal ROIC must be positive"),"Blocked: years 6-10 sales to capital must be positive"),"Blocked: years 1-5 sales to capital must be positive"),"Blocked: shares must be positive"),"Blocked: starting WACC must be positive"),"Blocked: terminal WACC must exceed growth") -> 80.578186
A29: Terminal value share | B29: =B22/B24 -> 0.51881035
A30: Terminal reinvestment rate | B30: =IF(M3>0,(M3/IF('WD40_Inputs_bear'!B23+0=1,'WD40_Inputs_bear'!B24+0,L13)),0) -> 0.3125
A31: EVA recurring terminal value / USD m | B31: =IF(M3>0,((M9*(1-(M13/IF('WD40_Inputs_bear'!B23+0=1,'WD40_Inputs_bear'!B24+0,L13))))/(M13-M3)),(M9/(M13-M3))) -> -4.3503981e-13
A32: EVA terminal capital transition / USD m | B32: =IF(M3>0,((M9/IF('WD40_Inputs_bear'!B23+0=1,'WD40_Inputs_bear'!B24+0,L13))-L17),(0-L17)) -> 932.563
A33: EVA terminal value / USD m | B33: =B31+B32 -> 932.563
A34: EVA operating value / USD m | B34: =B17+SUM(C19:L19)+(B33*L14) -> 1127.4086
A35: EVA minus DCF / USD m | B35: =B34-B24 -> 2.2737368e-13

Sheet WD40_Inputs_base
A1: WD40_Inputs_base | B1: Value
A2: Revenue FY2025 / USD m | B2: ='WD40_Regions_base'!E2+0 -> 619.985
A3: Reported EBIT FY2025 / USD m | B3: 103.793
A4: Adjusted book equity / USD m | B4: 268.472
A5: Interest-bearing debt / USD m | B5: 86.995
A6: Cash / USD m | B6: 58.13
A7: Nonoperating assets / USD m | B7: 0
A8: Minority interests / USD m | B8: 0
A9: Valuation dilution proxy / million shares | B9: 13.633263
A10: Historical reference price / USD per share | B10: 216.04
A11: Normalized starting tax rate | B11: 0.22200028
A12: Terminal tax rate | B12: 0.25
A13: Revenue growth year 1 | B13: ='WD40_Regions_base'!E47+0 -> 0.060436204
A14: Revenue growth years 2-5 | B14: ='WD40_Regions_base'!E48+0 -> 0.061544421
A15: Adjusted EBIT margin year 1 | B15: =B44/B2 -> 0.17106812
A16: Target adjusted EBIT margin | B16: 0.2
A17: Margin convergence year | B17: 5
A18: Sales to capital years 1-5 | B18: 2
A19: Sales to capital years 6-10 | B19: =B18+0 -> 2
A20: WACC years 1-5 | B20: 0.075
A21: Terminal WACC | B21: 0.07
A22: Terminal growth | B22: 0.025
A23: Use explicit terminal ROIC / 1=yes | B23: 1
A24: Explicit terminal ROIC | B24: 0.2
A25: Current R&D / USD m | B25: 8.7
A26: R&D amortization life / years | B26: 3
A27: Capitalize R&D / 1=yes | B27: 1
A28: Starting NOL / USD m | B28: 0
A29: Hold starting tax rate / 1=yes | B29: 0
A30: Override reinvestment timing / 1=yes | B30: 0
A31: Reinvestment growth lead / years | B31: 1
... A41: R&D 4 years prior / USD m | B41: 5.6
A42: R&D amortization / USD m | B42: =0+IF(1<=B26,(B38/B26),0)+IF(2<=B26,(B39/B26),0)+IF(3<=B26,(B40/B26),0)+IF(4<=B26,(B41/B26),0) -> 6.4333333
A43: Unamortized R&D asset / USD m | B43: =B25+IF(1<B26,(B38*((B26-1)/B26)),0)+IF(2<B26,(B39*((B26-2)/B26)),0)+IF(3<B26,(B40*((B26-3)/B26)),0)+IF(4<B26,(B41*((B26-4)/B26)),0) -> 16.1
A44: R&D-adjusted base EBIT / USD m | B44: =B3+IF(B27=1,(B25-B42),0) -> 106.05967
A45: Base invested capital / USD m | B45: =B4+B5-B6+IF(B27=1,B43,0) -> 313.437
A46: Effective terminal tax rate | B46: =IF(B29=1,B11,B12) -> 0.25
A47: Effective terminal ROIC | B47: =IF(B23=1,B24,B21) -> 0.2
A48: Cash after explicit haircut / USD m | B48: =B6-IF(B37=1,(B35*(B12-B36)),0) -> 58.13

Sheet WD40_DCF_base
A1: WD40_DCF_base | B1: Base | C1: Y1 | D1: Y2 | E1: Y3 | F1: Y4 | G1: Y5 | H1: Y6 | I1: Y7 | J1: Y8 | K1: Y9 | L1: Y10 | M1: Terminal
A2: Year | B2: 0 | C2: 1 | D2: 2 | E2: 3 | F2: 4 | G2: 5 | H2: 6 | I2: 7 | J2: 8 | K2: 9 | L2: 10 | M2: 11
A3: Revenue growth | C3: ='WD40_Inputs_base'!B13+0 -> 0.060436204 | D3: ='WD40_Inputs_base'!B14+0 -> 0.061544421 | E3: ='WD40_Inputs_base'!B14+0 -> 0.061544421 | F3: ='WD40_Inputs_base'!B14+0 -> 0.061544421 | G3: ='WD40_Inputs_base'!B14+0 -> 0.061544421 | H3: ='WD40_Inputs_base'!B14+0-((('WD40_Inputs_base'!B14+0-'WD40_Inputs_base'!B22+0)/5)*1) -> 0.054235537 | I3: ='WD40_Inputs_base'!B14+0-((('WD40_Inputs_base'!B14+0-'WD40_Inputs_base'!B22+0)/5)*2) -> 0.046926653 | J3: ='WD40_Inputs_base'!B14+0-((('WD40_Inputs_base'!B14+0-'WD40_Inputs_base'!B22+0)/5)*3) -> 0.039617768 | K3: ='WD40_Inputs_base'!B14+0-((('WD40_Inputs_base'!B14+0-'WD40_Inputs_base'!B22+0)/5)*4) -> 0.032308884 | L3: ='WD40_Inputs_base'!B14+0-((('WD40_Inputs_base'!B14+0-'WD40_Inputs_base'!B22+0)/5)*5) -> 0.025 | M3: ='WD40_Inputs_base'!B22+0 -> 0.025
A4: Revenue / USD m | B4: ='WD40_Inputs_base'!B2+0 -> 619.985 | C4: =B4*(1+C3) -> 657.45454 | D4: =C4*(1+D3) -> 697.9172 | E4: =D4*(1+E3) -> 740.87011 | F4: =E4*(1+F3) -> 786.46653 | G4: =F4*(1+G3) -> 834.86916 | H4: =G4*(1+H3) -> 880.14874 | I4: =H4*(1+I3) -> 921.45117 | J4: =I4*(1+J3) -> 957.95701 | ... M4: =L4*(1+M3) -> 1038.971
A5: Adjusted EBIT margin | B5: =B6/B4 -> 0.17106812 | C5: ='WD40_Inputs_base'!B15+0 -> 0.17106812 | D5: =IF(2>'WD40_Inputs_base'!B17+0,'WD40_Inputs_base'!B16+0,'WD40_Inputs_base'!B16+0-((('WD40_Inputs_base'!B16+0-'WD40_Inputs_base'!B15+0)/'WD40_Inputs_base'!B17+0)*('WD40_Inputs_base'!B17+0-2))) -> 0.18264087 | E5: =IF(3>'WD40_Inputs_base'!B17+0,'WD40_Inputs_base'!B16+0,'WD40_Inputs_base'!B16+0-((('WD40_Inputs_base'!B16+0-'WD40_Inputs_base'!B15+0)/'WD40_Inputs_base'!B17+0)*('WD40_Inputs_base'!B17+0-3))) -> 0.18842725 | F5: =IF(4>'WD40_Inputs_base'!B17+0,'WD40_Inputs_base'!B16+0,'WD40_Inputs_base'!B16+0-((('WD40_Inputs_base'!B16+0-'WD40_Inputs_base'!B15+0)/'WD40_Inputs_base'!B17+0)*('WD40_Inputs_base'!B17+0-4))) -> 0.19421362 | G5: =IF(5>'WD40_Inputs_base'!B17+0,'WD40_Inputs_base'!B16+0,'WD40_Inputs_base'!B16+0-((('WD40_Inputs_base'!B16+0-'WD40_Inputs_base'!B15+0)/'WD40_Inputs_base'!B17+0)*('WD40_Inputs_base'!B17+0-5))) -> 0.2 | H5: =IF(6>'WD40_Inputs_base'!B17+0,'WD40_Inputs_base'!B16+0,'WD40_Inputs_base'!B16+0-((('WD40_Inputs_base'!B16+0-'WD40_Inputs_base'!B15+0)/'WD40_Inputs_base'!B17+0)*('WD40_Inputs_base'!B17+0-6))) -> 0.2 | I5: =IF(7>'WD40_Inputs_base'!B17+0,'WD40_Inputs_base'!B16+0,'WD40_Inputs_base'!B16+0-((('WD40_Inputs_base'!B16+0-'WD40_Inputs_base'!B15+0)/'WD40_Inputs_base'!B17+0)*('WD40_Inputs_base'!B17+0-7))) -> 0.2 | J5: =IF(8>'WD40_Inputs_base'!B17+0,'WD40_Inputs_base'!B16+0,'WD40_Inputs_base'!B16+0-((('WD40_Inputs_base'!B16+0-'WD40_Inputs_base'!B15+0)/'WD40_Inputs_base'!B17+0)*('WD40_Inputs_base'!B17+0-8))) -> 0.2 | K5: =IF(9>'WD40_Inputs_base'!B17+0,'WD40_Inputs_base'!B16+0,'WD40_Inputs_base'!B16+0-((('WD40_Inputs_base'!B16+0-'WD40_Inputs_base'!B15+0)/'WD40_Inputs_base'!B17+0)*('WD40_Inputs_base'!B17+0-9))) -> 0.2 | L5: =IF(10>'WD40_Inputs_base'!B17+0,'WD40_Inputs_base'!B16+0,'WD40_Inputs_base'!B16+0-((('WD40_Inputs_base'!B16+0-'WD40_Inputs_base'!B15+0)/'WD40_Inputs_base'!B17+0)*('WD40_Inputs_base'!B17+0-10))) -> 0.2 | M5: =L5 -> 0.2
A6: Adjusted EBIT / USD m | B6: ='WD40_Inputs_base'!B44+0 -> 106.05967 | C6: =C5*C4 -> 112.46951 | D6: =D5*D4 -> 127.4682 | E6: =E5*E4 -> 139.60011 | F6: =F5*F4 -> 152.74251 | G6: =G5*G4 -> 166.97383 | H6: =H5*H4 -> 176.02975 | I6: =I5*I4 -> 184.29023 | J6: =J5*J4 -> 191.5914 | ... L6: =L5*L4 -> 202.72604 | M6: =L5*M4 -> 207.79419
A7: Tax rate | B7: ='WD40_Inputs_base'!B11+0 -> 0.22200028 | C7: ='WD40_Inputs_base'!B11+0 -> 0.22200028 | D7: ='WD40_Inputs_base'!B11+0 -> 0.22200028 | E7: ='WD40_Inputs_base'!B11+0 -> 0.22200028 | F7: ='WD40_Inputs_base'!B11+0 -> 0.22200028 | G7: ='WD40_Inputs_base'!B11+0 -> 0.22200028 | H7: =G7+(('WD40_Inputs_base'!B46+0-'WD40_Inputs_base'!B11+0)/5) -> 0.22760022 | I7: =H7+(('WD40_Inputs_base'!B46+0-'WD40_Inputs_base'!B11+0)/5) -> 0.23320017 | J7: =I7+(('WD40_Inputs_base'!B46+0-'WD40_Inputs_base'!B11+0)/5) -> 0.23880011 | K7: =J7+(('WD40_Inputs_base'!B46+0-'WD40_Inputs_base'!B11+0)/5) -> 0.24440006 | L7: =K7+(('WD40_Inputs_base'!B46+0-'WD40_Inputs_base'!B11+0)/5) -> 0.25 | M7: ='WD40_Inputs_base'!B46+0 -> 0.25
A8: Opening NOL / USD m | C8: =B12 -> 0 | D8: =C12 -> 0 | E8: =D12 -> 0 | F8: =E12 -> 0 | G8: =F12 -> 0 | H8: =G12 -> 0 | I8: =H12 -> 0 | J8: =I12 -> 0 | ... M8: =L12 -> 0
A9: NOPAT / USD m | B9: =IF(B6>0,(B6*(1-B7)),B6) -> 82.514391 | C9: =IF(C6>0,IF(C6<B12,C6,C6-((C6-B12)*C7)),C6) -> 87.501248 | D9: =IF(D6>0,IF(D6<C12,D6,D6-((D6-C12)*D7)),D6) -> 99.170228 | E9: =IF(E6>0,IF(E6<D12,E6,E6-((E6-D12)*E7)),E6) -> 108.60885 | F9: =IF(F6>0,IF(F6<E12,F6,F6-((F6-E12)*F7)),F6) -> 118.83363 | G9: =IF(G6>0,IF(G6<F12,G6,G6-((G6-F12)*G7)),G6) -> 129.9056 | H9: =IF(H6>0,IF(H6<G12,H6,H6-((H6-G12)*H7)),H6) -> 135.96534 | I9: =IF(I6>0,IF(I6<H12,I6,I6-((I6-H12)*I7)),I6) -> 141.31372 | J9: =IF(J6>0,IF(J6<I12,J6,J6-((J6-I12)*J7)),J6) -> 145.83935 | ... L9: =IF(L6>0,IF(L6<K12,L6,L6-((L6-K12)*L7)),L6) -> 152.04453 | M9: =M6*(1-M7) -> 155.84565
A10: Reinvestment / USD m | C10: =IF('WD40_Inputs_base'!B30+0=1,IF('WD40_Inputs_base'!B31+0=0,((C4-B4)/C20),IF('WD40_Inputs_base'!B31+0=2,((E4-D4)/C20),IF('WD40_Inputs_base'!B31+0=3,((F4-E4)/C20),((D4-C4)/C20)))),((D4-C4)/C20)) -> 20.23133 | D10: =IF('WD40_Inputs_base'!B30+0=1,IF('WD40_Inputs_base'!B31+0=0,((D4-C4)/D20),IF('WD40_Inputs_base'!B31+0=2,((F4-E4)/D20),IF('WD40_Inputs_base'!B31+0=3,((G4-F4)/D20),((E4-D4)/D20)))),((E4-D4)/D20)) -> 21.476455 | E10: =IF('WD40_Inputs_base'!B30+0=1,IF('WD40_Inputs_base'!B31+0=0,((E4-D4)/E20),IF('WD40_Inputs_base'!B31+0=2,((G4-F4)/E20),IF('WD40_Inputs_base'!B31+0=3,((H4-G4)/E20),((F4-E4)/E20)))),((F4-E4)/E20)) -> 22.798211 | F10: =IF('WD40_Inputs_base'!B30+0=1,IF('WD40_Inputs_base'!B31+0=0,((F4-E4)/F20),IF('WD40_Inputs_base'!B31+0=2,((H4-G4)/F20),IF('WD40_Inputs_base'!B31+0=3,((I4-H4)/F20),((G4-F4)/F20)))),((G4-F4)/F20)) -> 24.201314 | G10: =IF('WD40_Inputs_base'!B30+0=1,IF('WD40_Inputs_base'!B31+0=0,((G4-F4)/G20),IF('WD40_Inputs_base'!B31+0=2,((I4-H4)/G20),IF('WD40_Inputs_base'!B31+0=3,((J4-I4)/G20),((H4-G4)/G20)))),((H4-G4)/G20)) -> 22.639788 | H10: =IF('WD40_Inputs_base'!B30+0=1,IF('WD40_Inputs_base'!B31+0=0,((H4-G4)/H20),IF('WD40_Inputs_base'!B31+0=2,((J4-I4)/H20),IF('WD40_Inputs_base'!B31+0=3,((K4-J4)/H20),((I4-H4)/H20)))),((I4-H4)/H20)) -> 20.651217 | I10: =IF('WD40_Inputs_base'!B30+0=1,IF('WD40_Inputs_base'!B31+0=0,((I4-H4)/I20),IF('WD40_Inputs_base'!B31+0=2,((K4-J4)/I20),IF('WD40_Inputs_base'!B31+0=3,((L4-K4)/I20),((J4-I4)/I20)))),((J4-I4)/I20)) -> 18.25292 | J10: =IF('WD40_Inputs_base'!B30+0=1,IF('WD40_Inputs_base'!B31+0=0,((J4-I4)/J20),IF('WD40_Inputs_base'!B31+0=2,((L4-K4)/J20),IF('WD40_Inputs_base'!B31+0=3,((M4-L4)/J20),((K4-J4)/J20)))),((K4-J4)/J20)) -> 15.475261 | K10: =IF('WD40_Inputs_base'!B30+0=1,IF('WD40_Inputs_base'!B31+0=0,((K4-J4)/K20),IF('WD40_Inputs_base'!B31+0=2,((M4-L4)/K20),IF('WD40_Inputs_base'!B31+0=3,((M4*M3)/K20),((L4-K4)/K20)))),((L4-K4)/K20)) -> 12.361344 | L10: =IF('WD40_Inputs_base'!B30+0=1,IF('WD40_Inputs_base'!B31+0=0,((L4-K4)/L20),IF('WD40_Inputs_base'!B31+0=2,((M4*M3)/L20),IF('WD40_Inputs_base'!B31+0=3,((K10*(1+M3)*L20)/L20),((M4-L4)/L20)))),((M4-L4)/L20)) -> 12.670378 | M10: =B30*M9 -> 19.480706
A11: FCFF / USD m | C11: =C9-C10 -> 67.269919 | D11: =D9-D10 -> 77.693773 | E11: =E9-E10 -> 85.81064 | F11: =F9-F10 -> 94.632321 | G11: =G9-G10 -> 107.26581 | H11: =H9-H10 -> 115.31412 | I11: =I9-I10 -> 123.0608 | J11: =J9-J10 -> 130.36409 | ... M11: =M9-M10 -> 136.36494
A12: Closing NOL / USD m | B12: ='WD40_Inputs_base'!B28+0 -> 0 | C12: =IF(C6<0,(B12-C6),IF(B12>C6,(B12-C6),0)) -> 0 | D12: =IF(D6<0,(C12-D6),IF(C12>D6,(C12-D6),0)) -> 0 | E12: =IF(E6<0,(D12-E6),IF(D12>E6,(D12-E6),0)) -> 0 | F12: =IF(F6<0,(E12-F6),IF(E12>F6,(E12-F6),0)) -> 0 | G12: =IF(G6<0,(F12-G6),IF(F12>G6,(F12-G6),0)) -> 0 | H12: =IF(H6<0,(G12-H6),IF(G12>H6,(G12-H6),0)) -> 0 | I12: =IF(I6<0,(H12-I6),IF(H12>I6,(H12-I6),0)) -> 0 | J12: =IF(J6<0,(I12-J6),IF(I12>J6,(I12-J6),0)) -> 0 | ... M12: =IF(M6<0,(L12-M6),IF(L12>M6,(L12-M6),0)) -> 0
A13: WACC | C13: ='WD40_Inputs_base'!B20+0 -> 0.075 | D13: ='WD40_Inputs_base'!B20+0 -> 0.075 | E13: ='WD40_Inputs_base'!B20+0 -> 0.075 | F13: ='WD40_Inputs_base'!B20+0 -> 0.075 | G13: ='WD40_Inputs_base'!B20+0 -> 0.075 | H13: =G13-(('WD40_Inputs_base'!B20+0-'WD40_Inputs_base'!B21+0)/5) -> 0.074 | I13: =H13-(('WD40_Inputs_base'!B20+0-'WD40_Inputs_base'!B21+0)/5) -> 0.073 | J13: =I13-(('WD40_Inputs_base'!B20+0-'WD40_Inputs_base'!B21+0)/5) -> 0.072 | K13: =J13-(('WD40_Inputs_base'!B20+0-'WD40_Inputs_base'!B21+0)/5) -> 0.071 | L13: =K13-(('WD40_Inputs_base'!B20+0-'WD40_Inputs_base'!B21+0)/5) -> 0.07 | M13: ='WD40_Inputs_base'!B21+0 -> 0.07
A14: Cumulative discount factor | C14: =1*(1/(1+C13)) -> 0.93023256 | D14: =C14*(1/(1+D13)) -> 0.86533261 | E14: =D14*(1/(1+E13)) -> 0.80496057 | F14: =E14*(1/(1+F13)) -> 0.74880053 | G14: =F14*(1/(1+G13)) -> 0.69655863 | H14: =G14*(1/(1+H13)) -> 0.64856483 | I14: =H14*(1/(1+I13)) -> 0.60444067 | J14: =I14*(1/(1+J13)) -> 0.5638439 | K14: =J14*(1/(1+K13)) -> 0.5264649 | L14: =K14*(1/(1+L13)) -> 0.49202327
A15: PV FCFF / USD m | C15: =C11*C14 -> 62.576668 | D15: =D11*D14 -> 67.230956 | E15: =E11*E14 -> 69.074182 | F15: =F11*F14 -> 70.860732 | G15: =G11*G14 -> 74.716923 | H15: =H11*H14 -> 74.788684 | I15: =I11*I14 -> 74.382953 | J15: =J11*J14 -> 73.504999 | ... L15: =L11*L14 -> 68.575327
A16: Opening invested capital / USD m | C16: =B17 -> 313.437 | D16: =C17 -> 333.66833 | E16: =D17 -> 355.14478 | F16: =E17 -> 377.943 | G16: =F17 -> 402.14431 | H16: =G17 -> 424.7841 | I16: =H17 -> 445.43531 | J16: =I17 -> 463.68823 | ... L16: =K17 -> 491.52484
A17: Closing invested capital / USD m | B17: ='WD40_Inputs_base'!B45+0 -> 313.437 | C17: =B17+C10 -> 333.66833 | D17: =C17+D10 -> 355.14478 | E17: =D17+E10 -> 377.943 | F17: =E17+F10 -> 402.14431 | G17: =F17+G10 -> 424.7841 | H17: =G17+H10 -> 445.43531 | I17: =H17+I10 -> 463.68823 | J17: =I17+J10 -> 479.1635 | ... L17: =K17+L10 -> 504.19522
A18: Economic profit / USD m | C18: =C9-(C13*B17) -> 63.993473 | D18: =D9-(D13*C17) -> 74.145103 | E18: =E9-(E13*D17) -> 81.972992 | F18: =F9-(F13*E17) -> 90.48791 | G18: =G9-(G13*F17) -> 99.744772 | H18: =H9-(H13*G17) -> 104.53131 | I18: =I9-(I13*H17) -> 108.79694 | J18: =J9-(J13*I17) -> 112.4538 | ... L18: =L9-(L13*K17) -> 117.63779
A19: PV economic profit / USD m | C19: =C18*C14 -> 59.528812 | D19: =D18*D14 -> 64.160176 | E19: =E18*E14 -> 65.985026 | F19: =F18*F14 -> 67.757395 | G19: =G18*G14 -> 69.478082 | H19: =H18*H14 -> 67.795335 | I19: =I18*I14 -> 65.761297 | J19: =J18*J14 -> 63.40639 | ... L19: =L18*L14 -> 57.880532
A20: Sales to capital | C20: ='WD40_Inputs_base'!B18+0 -> 2 | D20: ='WD40_Inputs_base'!B18+0 -> 2 | E20: ='WD40_Inputs_base'!B18+0 -> 2 | F20: ='WD40_Inputs_base'!B18+0 -> 2 | G20: ='WD40_Inputs_base'!B18+0 -> 2 | H20: ='WD40_Inputs_base'!B19+0 -> 2 | I20: ='WD40_Inputs_base'!B19+0 -> 2 | J20: ='WD40_Inputs_base'!B19+0 -> 2 | K20: ='WD40_Inputs_base'!B19+0 -> 2 | L20: ='WD40_Inputs_base'!B19+0 -> 2
A21: Terminal value / USD m | B21: =M11/(M13-M3) -> 3030.332
A22: PV terminal value / USD m | B22: =B21*L14 -> 1490.9939
A23: PV forecast FCFF / USD m | B23: =SUM(C15:L15) -> 707.88047
A24: Undistressed operating value / USD m | B24: =B22+B23 -> 2198.8743
A25: Distress proceeds / USD m | B25: =IF('WD40_Inputs_base'!B34+0=1,(('WD40_Inputs_base'!B4+0+'WD40_Inputs_base'!B5+0)*'WD40_Inputs_base'!B33+0),(B24*'WD40_Inputs_base'!B33+0)) -> 1099.4372
A26: Operating value / USD m | B26: =(B24*(1-'WD40_Inputs_base'!B32+0))+(B25*'WD40_Inputs_base'!B32+0) -> 2198.8743
A27: Equity value / USD m | B27: =B26-'WD40_Inputs_base'!B5+0-'WD40_Inputs_base'!B8+0+'WD40_Inputs_base'!B48+0+'WD40_Inputs_base'!B7+0 -> 2170.0093
A28: Value per share / USD | B28: =IF('WD40_Inputs_base'!B21+0>'WD40_Inputs_base'!B22+0,IF('WD40_Inputs_base'!B20+0>0,IF('WD40_Inputs_base'!B9+0>0,IF('WD40_Inputs_base'!B18+0>0,IF('WD40_Inputs_base'!B19+0>0,IF(IF('WD40_Inputs_base'!B23+0=1,IF('WD40_Inputs_base'!B24+0>0,1,0),1)=1,IF(IF('WD40_Inputs_base'!B23+0=1,IF('WD40_Inputs_base'!B24+0>='WD40_Inputs_base'!B22+0,1,0),1)=1,B27/'WD40_Inputs_base'!B9+0,"Blocked: terminal reinvestment exceeds NOPAT"),"Blocked: active terminal ROIC must be positive"),"Blocked: years 6-10 sales to capital must be positive"),"Blocked: years 1-5 sales to capital must be positive"),"Blocked: shares must be positive"),"Blocked: starting WACC must be positive"),"Blocked: terminal WACC must exceed growth") -> 159.17021
A29: Terminal value share | B29: =B22/B24 -> 0.67807143
A30: Terminal reinvestment rate | B30: =IF(M3>0,(M3/IF('WD40_Inputs_base'!B23+0=1,'WD40_Inputs_base'!B24+0,L13)),0) -> 0.125
A31: EVA recurring terminal value / USD m | B31: =IF(M3>0,((M9*(1-(M13/IF('WD40_Inputs_base'!B23+0=1,'WD40_Inputs_base'!B24+0,L13))))/(M13-M3)),(M9/(M13-M3))) -> 2251.1038
A32: EVA terminal capital transition / USD m | B32: =IF(M3>0,((M9/IF('WD40_Inputs_base'!B23+0=1,'WD40_Inputs_base'!B24+0,L13))-L17),(0-L17)) -> 275.03301
A33: EVA terminal value / USD m | B33: =B31+B32 -> 2526.1368
A34: EVA operating value / USD m | B34: =B17+SUM(C19:L19)+(B33*L14) -> 2198.8743
A35: EVA minus DCF / USD m | B35: =B34-B24 -> 0

Sheet WD40_Inputs_bull
A1: WD40_Inputs_bull | B1: Value
A2: Revenue FY2025 / USD m | B2: ='WD40_Regions_bull'!E2+0 -> 619.985
A3: Reported EBIT FY2025 / USD m | B3: 103.793
A4: Adjusted book equity / USD m | B4: 268.472
A5: Interest-bearing debt / USD m | B5: 86.995
A6: Cash / USD m | B6: 58.13
A7: Nonoperating assets / USD m | B7: 0
A8: Minority interests / USD m | B8: 0
A9: Valuation dilution proxy / million shares | B9: 13.633263
A10: Historical reference price / USD per share | B10: 216.04
A11: Normalized starting tax rate | B11: 0.22200028
A12: Terminal tax rate | B12: 0.25
A13: Revenue growth year 1 | B13: ='WD40_Regions_bull'!E47+0 -> 0.081935466
A14: Revenue growth years 2-5 | B14: ='WD40_Regions_bull'!E48+0 -> 0.08333782
A15: Adjusted EBIT margin year 1 | B15: =B44/B2 -> 0.17106812
A16: Target adjusted EBIT margin | B16: 0.22
A17: Margin convergence year | B17: 5
A18: Sales to capital years 1-5 | B18: 2
A19: Sales to capital years 6-10 | B19: =B18+0 -> 2
A20: WACC years 1-5 | B20: 0.065
A21: Terminal WACC | B21: 0.065
A22: Terminal growth | B22: 0.03
A23: Use explicit terminal ROIC / 1=yes | B23: 1
A24: Explicit terminal ROIC | B24: 0.25
A25: Current R&D / USD m | B25: 8.7
A26: R&D amortization life / years | B26: 3
A27: Capitalize R&D / 1=yes | B27: 1
A28: Starting NOL / USD m | B28: 0
A29: Hold starting tax rate / 1=yes | B29: 0
A30: Override reinvestment timing / 1=yes | B30: 0
A31: Reinvestment growth lead / years | B31: 1
... A41: R&D 4 years prior / USD m | B41: 5.6
A42: R&D amortization / USD m | B42: =0+IF(1<=B26,(B38/B26),0)+IF(2<=B26,(B39/B26),0)+IF(3<=B26,(B40/B26),0)+IF(4<=B26,(B41/B26),0) -> 6.4333333
A43: Unamortized R&D asset / USD m | B43: =B25+IF(1<B26,(B38*((B26-1)/B26)),0)+IF(2<B26,(B39*((B26-2)/B26)),0)+IF(3<B26,(B40*((B26-3)/B26)),0)+IF(4<B26,(B41*((B26-4)/B26)),0) -> 16.1
A44: R&D-adjusted base EBIT / USD m | B44: =B3+IF(B27=1,(B25-B42),0) -> 106.05967
A45: Base invested capital / USD m | B45: =B4+B5-B6+IF(B27=1,B43,0) -> 313.437
A46: Effective terminal tax rate | B46: =IF(B29=1,B11,B12) -> 0.25
A47: Effective terminal ROIC | B47: =IF(B23=1,B24,B21) -> 0.25
A48: Cash after explicit haircut / USD m | B48: =B6-IF(B37=1,(B35*(B12-B36)),0) -> 58.13

Sheet WD40_DCF_bull
A1: WD40_DCF_bull | B1: Base | C1: Y1 | D1: Y2 | E1: Y3 | F1: Y4 | G1: Y5 | H1: Y6 | I1: Y7 | J1: Y8 | K1: Y9 | L1: Y10 | M1: Terminal
A2: Year | B2: 0 | C2: 1 | D2: 2 | E2: 3 | F2: 4 | G2: 5 | H2: 6 | I2: 7 | J2: 8 | K2: 9 | L2: 10 | M2: 11
A3: Revenue growth | C3: ='WD40_Inputs_bull'!B13+0 -> 0.081935466 | D3: ='WD40_Inputs_bull'!B14+0 -> 0.08333782 | E3: ='WD40_Inputs_bull'!B14+0 -> 0.08333782 | F3: ='WD40_Inputs_bull'!B14+0 -> 0.08333782 | G3: ='WD40_Inputs_bull'!B14+0 -> 0.08333782 | H3: ='WD40_Inputs_bull'!B14+0-((('WD40_Inputs_bull'!B14+0-'WD40_Inputs_bull'!B22+0)/5)*1) -> 0.072670256 | I3: ='WD40_Inputs_bull'!B14+0-((('WD40_Inputs_bull'!B14+0-'WD40_Inputs_bull'!B22+0)/5)*2) -> 0.062002692 | J3: ='WD40_Inputs_bull'!B14+0-((('WD40_Inputs_bull'!B14+0-'WD40_Inputs_bull'!B22+0)/5)*3) -> 0.051335128 | K3: ='WD40_Inputs_bull'!B14+0-((('WD40_Inputs_bull'!B14+0-'WD40_Inputs_bull'!B22+0)/5)*4) -> 0.040667564 | L3: ='WD40_Inputs_bull'!B14+0-((('WD40_Inputs_bull'!B14+0-'WD40_Inputs_bull'!B22+0)/5)*5) -> 0.03 | M3: ='WD40_Inputs_bull'!B22+0 -> 0.03
A4: Revenue / USD m | B4: ='WD40_Inputs_bull'!B2+0 -> 619.985 | C4: =B4*(1+C3) -> 670.78376 | D4: =C4*(1+D3) -> 726.68542 | E4: =D4*(1+E3) -> 787.2458 | F4: =E4*(1+F3) -> 852.85314 | G4: =F4*(1+G3) -> 923.92807 | H4: =G4*(1+H3) -> 991.07015 | I4: =H4*(1+I3) -> 1052.5192 | J4: =I4*(1+J3) -> 1106.5504 | ... M4: =L4*(1+M3) -> 1221.6805
A5: Adjusted EBIT margin | B5: =B6/B4 -> 0.17106812 | C5: ='WD40_Inputs_bull'!B15+0 -> 0.17106812 | D5: =IF(2>'WD40_Inputs_bull'!B17+0,'WD40_Inputs_bull'!B16+0,'WD40_Inputs_bull'!B16+0-((('WD40_Inputs_bull'!B16+0-'WD40_Inputs_bull'!B15+0)/'WD40_Inputs_bull'!B17+0)*('WD40_Inputs_bull'!B17+0-2))) -> 0.19064087 | E5: =IF(3>'WD40_Inputs_bull'!B17+0,'WD40_Inputs_bull'!B16+0,'WD40_Inputs_bull'!B16+0-((('WD40_Inputs_bull'!B16+0-'WD40_Inputs_bull'!B15+0)/'WD40_Inputs_bull'!B17+0)*('WD40_Inputs_bull'!B17+0-3))) -> 0.20042725 | F5: =IF(4>'WD40_Inputs_bull'!B17+0,'WD40_Inputs_bull'!B16+0,'WD40_Inputs_bull'!B16+0-((('WD40_Inputs_bull'!B16+0-'WD40_Inputs_bull'!B15+0)/'WD40_Inputs_bull'!B17+0)*('WD40_Inputs_bull'!B17+0-4))) -> 0.21021362 | G5: =IF(5>'WD40_Inputs_bull'!B17+0,'WD40_Inputs_bull'!B16+0,'WD40_Inputs_bull'!B16+0-((('WD40_Inputs_bull'!B16+0-'WD40_Inputs_bull'!B15+0)/'WD40_Inputs_bull'!B17+0)*('WD40_Inputs_bull'!B17+0-5))) -> 0.22 | H5: =IF(6>'WD40_Inputs_bull'!B17+0,'WD40_Inputs_bull'!B16+0,'WD40_Inputs_bull'!B16+0-((('WD40_Inputs_bull'!B16+0-'WD40_Inputs_bull'!B15+0)/'WD40_Inputs_bull'!B17+0)*('WD40_Inputs_bull'!B17+0-6))) -> 0.22 | I5: =IF(7>'WD40_Inputs_bull'!B17+0,'WD40_Inputs_bull'!B16+0,'WD40_Inputs_bull'!B16+0-((('WD40_Inputs_bull'!B16+0-'WD40_Inputs_bull'!B15+0)/'WD40_Inputs_bull'!B17+0)*('WD40_Inputs_bull'!B17+0-7))) -> 0.22 | J5: =IF(8>'WD40_Inputs_bull'!B17+0,'WD40_Inputs_bull'!B16+0,'WD40_Inputs_bull'!B16+0-((('WD40_Inputs_bull'!B16+0-'WD40_Inputs_bull'!B15+0)/'WD40_Inputs_bull'!B17+0)*('WD40_Inputs_bull'!B17+0-8))) -> 0.22 | K5: =IF(9>'WD40_Inputs_bull'!B17+0,'WD40_Inputs_bull'!B16+0,'WD40_Inputs_bull'!B16+0-((('WD40_Inputs_bull'!B16+0-'WD40_Inputs_bull'!B15+0)/'WD40_Inputs_bull'!B17+0)*('WD40_Inputs_bull'!B17+0-9))) -> 0.22 | L5: =IF(10>'WD40_Inputs_bull'!B17+0,'WD40_Inputs_bull'!B16+0,'WD40_Inputs_bull'!B16+0-((('WD40_Inputs_bull'!B16+0-'WD40_Inputs_bull'!B15+0)/'WD40_Inputs_bull'!B17+0)*('WD40_Inputs_bull'!B17+0-10))) -> 0.22 | M5: =L5 -> 0.22
A6: Adjusted EBIT / USD m | B6: ='WD40_Inputs_bull'!B44+0 -> 106.05967 | C6: =C5*C4 -> 114.74971 | D6: =D5*D4 -> 138.53594 | E6: =E5*E4 -> 157.78551 | F6: =F5*F4 -> 179.28135 | G6: =G5*G4 -> 203.26417 | H6: =H5*H4 -> 218.03543 | I6: =I5*I4 -> 231.55422 | J6: =J5*J4 -> 243.44108 | ... L6: =L5*L4 -> 260.94148 | M6: =L5*M4 -> 268.76972
A7: Tax rate | B7: ='WD40_Inputs_bull'!B11+0 -> 0.22200028 | C7: ='WD40_Inputs_bull'!B11+0 -> 0.22200028 | D7: ='WD40_Inputs_bull'!B11+0 -> 0.22200028 | E7: ='WD40_Inputs_bull'!B11+0 -> 0.22200028 | F7: ='WD40_Inputs_bull'!B11+0 -> 0.22200028 | G7: ='WD40_Inputs_bull'!B11+0 -> 0.22200028 | H7: =G7+(('WD40_Inputs_bull'!B46+0-'WD40_Inputs_bull'!B11+0)/5) -> 0.22760022 | I7: =H7+(('WD40_Inputs_bull'!B46+0-'WD40_Inputs_bull'!B11+0)/5) -> 0.23320017 | J7: =I7+(('WD40_Inputs_bull'!B46+0-'WD40_Inputs_bull'!B11+0)/5) -> 0.23880011 | K7: =J7+(('WD40_Inputs_bull'!B46+0-'WD40_Inputs_bull'!B11+0)/5) -> 0.24440006 | L7: =K7+(('WD40_Inputs_bull'!B46+0-'WD40_Inputs_bull'!B11+0)/5) -> 0.25 | M7: ='WD40_Inputs_bull'!B46+0 -> 0.25
A8: Opening NOL / USD m | C8: =B12 -> 0 | D8: =C12 -> 0 | E8: =D12 -> 0 | F8: =E12 -> 0 | G8: =F12 -> 0 | H8: =G12 -> 0 | I8: =H12 -> 0 | J8: =I12 -> 0 | ... M8: =L12 -> 0
A9: NOPAT / USD m | B9: =IF(B6>0,(B6*(1-B7)),B6) -> 82.514391 | C9: =IF(C6>0,IF(C6<B12,C6,C6-((C6-B12)*C7)),C6) -> 89.275247 | D9: =IF(D6>0,IF(D6<C12,D6,D6-((D6-C12)*D7)),D6) -> 107.78092 | E9: =IF(E6>0,IF(E6<D12,E6,E6-((E6-D12)*E7)),E6) -> 122.75708 | F9: =IF(F6>0,IF(F6<E12,F6,F6-((F6-E12)*F7)),F6) -> 139.48084 | G9: =IF(G6>0,IF(G6<F12,G6,G6-((G6-F12)*G7)),G6) -> 158.13947 | H9: =IF(H6>0,IF(H6<G12,H6,H6-((H6-G12)*H7)),H6) -> 168.41052 | I9: =IF(I6>0,IF(I6<H12,I6,I6-((I6-H12)*I7)),I6) -> 177.55574 | J9: =IF(J6>0,IF(J6<I12,J6,J6-((J6-I12)*J7)),J6) -> 185.30733 | ... L9: =IF(L6>0,IF(L6<K12,L6,L6-((L6-K12)*L7)),L6) -> 195.70611 | M9: =M6*(1-M7) -> 201.57729
A10: Reinvestment / USD m | C10: =IF('WD40_Inputs_bull'!B30+0=1,IF('WD40_Inputs_bull'!B31+0=0,((C4-B4)/C20),IF('WD40_Inputs_bull'!B31+0=2,((E4-D4)/C20),IF('WD40_Inputs_bull'!B31+0=3,((F4-E4)/C20),((D4-C4)/C20)))),((D4-C4)/C20)) -> 27.950828 | D10: =IF('WD40_Inputs_bull'!B30+0=1,IF('WD40_Inputs_bull'!B31+0=0,((D4-C4)/D20),IF('WD40_Inputs_bull'!B31+0=2,((F4-E4)/D20),IF('WD40_Inputs_bull'!B31+0=3,((G4-F4)/D20),((E4-D4)/D20)))),((E4-D4)/D20)) -> 30.280189 | E10: =IF('WD40_Inputs_bull'!B30+0=1,IF('WD40_Inputs_bull'!B31+0=0,((E4-D4)/E20),IF('WD40_Inputs_bull'!B31+0=2,((G4-F4)/E20),IF('WD40_Inputs_bull'!B31+0=3,((H4-G4)/E20),((F4-E4)/E20)))),((F4-E4)/E20)) -> 32.803674 | F10: =IF('WD40_Inputs_bull'!B30+0=1,IF('WD40_Inputs_bull'!B31+0=0,((F4-E4)/F20),IF('WD40_Inputs_bull'!B31+0=2,((H4-G4)/F20),IF('WD40_Inputs_bull'!B31+0=3,((I4-H4)/F20),((G4-F4)/F20)))),((G4-F4)/F20)) -> 35.537461 | G10: =IF('WD40_Inputs_bull'!B30+0=1,IF('WD40_Inputs_bull'!B31+0=0,((G4-F4)/G20),IF('WD40_Inputs_bull'!B31+0=2,((I4-H4)/G20),IF('WD40_Inputs_bull'!B31+0=3,((J4-I4)/G20),((H4-G4)/G20)))),((H4-G4)/G20)) -> 33.571045 | H10: =IF('WD40_Inputs_bull'!B30+0=1,IF('WD40_Inputs_bull'!B31+0=0,((H4-G4)/H20),IF('WD40_Inputs_bull'!B31+0=2,((J4-I4)/H20),IF('WD40_Inputs_bull'!B31+0=3,((K4-J4)/H20),((I4-H4)/H20)))),((I4-H4)/H20)) -> 30.724509 | I10: =IF('WD40_Inputs_bull'!B30+0=1,IF('WD40_Inputs_bull'!B31+0=0,((I4-H4)/I20),IF('WD40_Inputs_bull'!B31+0=2,((K4-J4)/I20),IF('WD40_Inputs_bull'!B31+0=3,((L4-K4)/I20),((J4-I4)/I20)))),((J4-I4)/I20)) -> 27.015603 | J10: =IF('WD40_Inputs_bull'!B30+0=1,IF('WD40_Inputs_bull'!B31+0=0,((J4-I4)/J20),IF('WD40_Inputs_bull'!B31+0=2,((L4-K4)/J20),IF('WD40_Inputs_bull'!B31+0=3,((M4-L4)/J20),((K4-J4)/J20)))),((K4-J4)/J20)) -> 22.500354 | K10: =IF('WD40_Inputs_bull'!B30+0=1,IF('WD40_Inputs_bull'!B31+0=0,((K4-J4)/K20),IF('WD40_Inputs_bull'!B31+0=2,((M4-L4)/K20),IF('WD40_Inputs_bull'!B31+0=3,((M4*M3)/K20),((L4-K4)/K20)))),((L4-K4)/K20)) -> 17.273266 | L10: =IF('WD40_Inputs_bull'!B30+0=1,IF('WD40_Inputs_bull'!B31+0=0,((L4-K4)/L20),IF('WD40_Inputs_bull'!B31+0=2,((M4*M3)/L20),IF('WD40_Inputs_bull'!B31+0=3,((K10*(1+M3)*L20)/L20),((M4-L4)/L20)))),((M4-L4)/L20)) -> 17.791464 | M10: =B30*M9 -> 24.189275
A11: FCFF / USD m | C11: =C9-C10 -> 61.324418 | D11: =D9-D10 -> 77.500734 | E11: =E9-E10 -> 89.953407 | F11: =F9-F10 -> 103.94338 | G11: =G9-G10 -> 124.56843 | H11: =H9-H10 -> 137.68601 | I11: =I9-I10 -> 150.54013 | J11: =J9-J10 -> 162.80697 | ... M11: =M9-M10 -> 177.38802
A12: Closing NOL / USD m | B12: ='WD40_Inputs_bull'!B28+0 -> 0 | C12: =IF(C6<0,(B12-C6),IF(B12>C6,(B12-C6),0)) -> 0 | D12: =IF(D6<0,(C12-D6),IF(C12>D6,(C12-D6),0)) -> 0 | E12: =IF(E6<0,(D12-E6),IF(D12>E6,(D12-E6),0)) -> 0 | F12: =IF(F6<0,(E12-F6),IF(E12>F6,(E12-F6),0)) -> 0 | G12: =IF(G6<0,(F12-G6),IF(F12>G6,(F12-G6),0)) -> 0 | H12: =IF(H6<0,(G12-H6),IF(G12>H6,(G12-H6),0)) -> 0 | I12: =IF(I6<0,(H12-I6),IF(H12>I6,(H12-I6),0)) -> 0 | J12: =IF(J6<0,(I12-J6),IF(I12>J6,(I12-J6),0)) -> 0 | ... M12: =IF(M6<0,(L12-M6),IF(L12>M6,(L12-M6),0)) -> 0
A13: WACC | C13: ='WD40_Inputs_bull'!B20+0 -> 0.065 | D13: ='WD40_Inputs_bull'!B20+0 -> 0.065 | E13: ='WD40_Inputs_bull'!B20+0 -> 0.065 | F13: ='WD40_Inputs_bull'!B20+0 -> 0.065 | G13: ='WD40_Inputs_bull'!B20+0 -> 0.065 | H13: =G13-(('WD40_Inputs_bull'!B20+0-'WD40_Inputs_bull'!B21+0)/5) -> 0.065 | I13: =H13-(('WD40_Inputs_bull'!B20+0-'WD40_Inputs_bull'!B21+0)/5) -> 0.065 | J13: =I13-(('WD40_Inputs_bull'!B20+0-'WD40_Inputs_bull'!B21+0)/5) -> 0.065 | K13: =J13-(('WD40_Inputs_bull'!B20+0-'WD40_Inputs_bull'!B21+0)/5) -> 0.065 | L13: =K13-(('WD40_Inputs_bull'!B20+0-'WD40_Inputs_bull'!B21+0)/5) -> 0.065 | M13: ='WD40_Inputs_bull'!B21+0 -> 0.065
A14: Cumulative discount factor | C14: =1*(1/(1+C13)) -> 0.93896714 | D14: =C14*(1/(1+D13)) -> 0.88165928 | E14: =D14*(1/(1+E13)) -> 0.82784909 | F14: =E14*(1/(1+F13)) -> 0.77732309 | G14: =F14*(1/(1+G13)) -> 0.72988084 | H14: =G14*(1/(1+H13)) -> 0.68533412 | I14: =H14*(1/(1+I13)) -> 0.64350621 | J14: =I14*(1/(1+J13)) -> 0.60423119 | K14: =J14*(1/(1+K13)) -> 0.56735323 | L14: =K14*(1/(1+L13)) -> 0.53272604
A15: PV FCFF / USD m | C15: =C11*C14 -> 57.581613 | D15: =D11*D14 -> 68.329242 | E15: =E11*E14 -> 74.467846 | F15: =F11*F14 -> 80.797589 | G15: =G11*G14 -> 90.920108 | H15: =H11*H14 -> 94.360922 | I15: =I11*I14 -> 96.873511 | J15: =J11*J14 -> 98.37305 | ... L15: =L11*L14 -> 94.779762
A16: Opening invested capital / USD m | C16: =B17 -> 313.437 | D16: =C17 -> 341.38783 | E16: =D17 -> 371.66802 | F16: =E17 -> 404.47169 | G16: =F17 -> 440.00915 | H16: =G17 -> 473.5802 | I16: =H17 -> 504.30471 | J16: =I17 -> 531.32031 | ... L16: =K17 -> 571.09393
A17: Closing invested capital / USD m | B17: ='WD40_Inputs_bull'!B45+0 -> 313.437 | C17: =B17+C10 -> 341.38783 | D17: =C17+D10 -> 371.66802 | E17: =D17+E10 -> 404.47169 | F17: =E17+F10 -> 440.00915 | G17: =F17+G10 -> 473.5802 | H17: =G17+H10 -> 504.30471 | I17: =H17+I10 -> 531.32031 | J17: =I17+J10 -> 553.82066 | ... L17: =K17+L10 -> 588.88539
A18: Economic profit / USD m | C18: =C9-(C13*B17) -> 68.901842 | D18: =D9-(D13*C17) -> 85.590715 | E18: =E9-(E13*D17) -> 98.59866 | F18: =F9-(F13*E17) -> 113.19018 | G18: =G9-(G13*F17) -> 129.53888 | H18: =H9-(H13*G17) -> 137.62781 | I18: =I9-(I13*H17) -> 144.77593 | J18: =J9-(J13*I17) -> 150.77151 | ... L18: =L9-(L13*K17) -> 158.585
A19: PV economic profit / USD m | C19: =C18*C14 -> 64.696565 | D19: =D18*D14 -> 75.461848 | E19: =E18*E14 -> 81.624811 | F19: =F18*F14 -> 87.985341 | G19: =G18*G14 -> 94.547944 | H19: =H18*H14 -> 94.321033 | I19: =I18*I14 -> 93.164211 | J19: =J18*J14 -> 91.100846 | ... L19: =L18*L14 -> 84.482359
A20: Sales to capital | C20: ='WD40_Inputs_bull'!B18+0 -> 2 | D20: ='WD40_Inputs_bull'!B18+0 -> 2 | E20: ='WD40_Inputs_bull'!B18+0 -> 2 | F20: ='WD40_Inputs_bull'!B18+0 -> 2 | G20: ='WD40_Inputs_bull'!B18+0 -> 2 | H20: ='WD40_Inputs_bull'!B19+0 -> 2 | I20: ='WD40_Inputs_bull'!B19+0 -> 2 | J20: ='WD40_Inputs_bull'!B19+0 -> 2 | K20: ='WD40_Inputs_bull'!B19+0 -> 2 | L20: ='WD40_Inputs_bull'!B19+0 -> 2
A21: Terminal value / USD m | B21: =M11/(M13-M3) -> 5068.229
A22: PV terminal value / USD m | B22: =B21*L14 -> 2699.9776
A23: PV forecast FCFF / USD m | B23: =SUM(C15:L15) -> 855.28898
A24: Undistressed operating value / USD m | B24: =B22+B23 -> 3555.2665
A25: Distress proceeds / USD m | B25: =IF('WD40_Inputs_bull'!B34+0=1,(('WD40_Inputs_bull'!B4+0+'WD40_Inputs_bull'!B5+0)*'WD40_Inputs_bull'!B33+0),(B24*'WD40_Inputs_bull'!B33+0)) -> 1777.6333
A26: Operating value / USD m | B26: =(B24*(1-'WD40_Inputs_bull'!B32+0))+(B25*'WD40_Inputs_bull'!B32+0) -> 3555.2665
A27: Equity value / USD m | B27: =B26-'WD40_Inputs_bull'!B5+0-'WD40_Inputs_bull'!B8+0+'WD40_Inputs_bull'!B48+0+'WD40_Inputs_bull'!B7+0 -> 3526.4015
A28: Value per share / USD | B28: =IF('WD40_Inputs_bull'!B21+0>'WD40_Inputs_bull'!B22+0,IF('WD40_Inputs_bull'!B20+0>0,IF('WD40_Inputs_bull'!B9+0>0,IF('WD40_Inputs_bull'!B18+0>0,IF('WD40_Inputs_bull'!B19+0>0,IF(IF('WD40_Inputs_bull'!B23+0=1,IF('WD40_Inputs_bull'!B24+0>0,1,0),1)=1,IF(IF('WD40_Inputs_bull'!B23+0=1,IF('WD40_Inputs_bull'!B24+0>='WD40_Inputs_bull'!B22+0,1,0),1)=1,B27/'WD40_Inputs_bull'!B9+0,"Blocked: terminal reinvestment exceeds NOPAT"),"Blocked: active terminal ROIC must be positive"),"Blocked: years 6-10 sales to capital must be positive"),"Blocked: years 1-5 sales to capital must be positive"),"Blocked: shares must be positive"),"Blocked: starting WACC must be positive"),"Blocked: terminal WACC must exceed growth") -> 258.66159
A29: Terminal value share | B29: =B22/B24 -> 0.75943042
A30: Terminal reinvestment rate | B30: =IF(M3>0,(M3/IF('WD40_Inputs_bull'!B23+0=1,'WD40_Inputs_bull'!B24+0,L13)),0) -> 0.12
A31: EVA recurring terminal value / USD m | B31: =IF(M3>0,((M9*(1-(M13/IF('WD40_Inputs_bull'!B23+0=1,'WD40_Inputs_bull'!B24+0,L13))))/(M13-M3)),(M9/(M13-M3))) -> 4261.9199
A32: EVA terminal capital transition / USD m | B32: =IF(M3>0,((M9/IF('WD40_Inputs_bull'!B23+0=1,'WD40_Inputs_bull'!B24+0,L13))-L17),(0-L17)) -> 217.42377
A33: EVA terminal value / USD m | B33: =B31+B32 -> 4479.3436
A34: EVA operating value / USD m | B34: =B17+SUM(C19:L19)+(B33*L14) -> 3555.2665
A35: EVA minus DCF / USD m | B35: =B34-B24 -> -4.5474735e-13

Sheet WD40_Precedents
A1: WD40_Precedents | B1: Observed minimum | C1: Observed median | D1: Observed maximum
A2: Fixed observation statistic / rebuild after changes | B2: 12.5 | C2: 14 | D2: 21.481481
A3: Target metric / USD m or EPS | B3: ='WD40_Inputs_original'!B3+0+8.191000000000003+0 -> 111.984 | C3: ='WD40_Inputs_original'!B3+0+8.191000000000003+0 -> 111.984 | D3: ='WD40_Inputs_original'!B3+0+8.191000000000003+0 -> 111.984
A4: Net debt / USD m | B4: ='WD40_Inputs_original'!B5+0-'WD40_Inputs_original'!B6+0 -> 28.865 | C4: ='WD40_Inputs_original'!B5+0-'WD40_Inputs_original'!B6+0 -> 28.865 | D4: ='WD40_Inputs_original'!B5+0-'WD40_Inputs_original'!B6+0 -> 28.865
A5: Valuation dilution proxy / million shares | B5: ='WD40_Inputs_original'!B9+0 -> 13.633263 | C5: ='WD40_Inputs_original'!B9+0 -> 13.633263 | D5: ='WD40_Inputs_original'!B9+0 -> 13.633263
A6: Indicative value / USD per share | B6: =((B2*B3)-B4)/B5 -> 100.5581 | C6: =((C2*C3)-C4)/C5 -> 112.87914 | D6: =((D2*D3)-D4)/D5 -> 174.33224
A7: Observation basis | B7: announced_consideration_context | C7: announced_consideration_context | D7: announced_consideration_context
A8: Observation 1 multiple | B8: 12.5
A9: Observation 1 identity | B9: Waterpik
A10: Observation 1 source IDs | B10: chd-waterpik-announcement
A11: Observation 2 multiple | B11: 21.481481
A12: Observation 2 identity | B12: TheraBreath
A13: Observation 2 source IDs | B13: chd-therabreath-announcement
A14: Observation 3 multiple | B14: 14
A15: Observation 3 identity | B15: Hero Cosmetics
A16: Observation 3 source IDs | B16: chd-hero-presentation

Sheet WD40_LBO
A1: WD40_LBO | B1: 25.0% return hurdle | C1: 20.0% return hurdle | D1: 17.5% return hurdle
A2: Sponsor return hurdle | B2: 0.25 | C2: 0.2 | D2: 0.175
A3: Hold period / years | B3: 5 | C3: 5 | D3: 5
A4: Entry debt / reported EBITDA | B4: 5.5 | C4: 5.5 | D4: 5.5
A5: Debt interest rate | B5: 0.08 | C5: 0.08 | D5: 0.08
A6: Fixed exit EV / EBITDA | B6: 14 | C6: 14 | D6: 14
A7: Minimum operating cash / USD m | B7: 5 | C7: 5 | D7: 5
A8: Cash sweep fraction | B8: 1 | C8: 1 | D8: 1
A9: Mandatory annual fraction of initial debt | B9: 0.01 | C9: 0.01 | D9: 0.01
A10: Exit fees / exit enterprise value | B10: 0.02 | C10: 0.02 | D10: 0.02
A11: Transaction fees / entry enterprise value | B11: 0.02 | C11: 0.02 | D11: 0.02
A12: Financing fees / new debt | B12: 0.02 | C12: 0.02 | D12: 0.02
A13: Historical cash-flow D&A / USD m | B13: 8.191 | C13: 8.191 | D13: 8.191
A14: Historical reported EBIT / USD m | B14: ='WD40_Inputs_base'!B3+0 -> 103.793 | C14: ='WD40_Inputs_base'!B3+0 -> 103.793 | D14: ='WD40_Inputs_base'!B3+0 -> 103.793
A15: Historical revenue / USD m | B15: ='WD40_Inputs_base'!B2+0 -> 619.985 | C15: ='WD40_Inputs_base'!B2+0 -> 619.985 | D15: ='WD40_Inputs_base'!B2+0 -> 619.985
A16: Valuation dilution proxy / million shares | B16: ='WD40_Inputs_base'!B9+0 -> 13.633263 | C16: ='WD40_Inputs_base'!B9+0 -> 13.633263 | D16: ='WD40_Inputs_base'!B9+0 -> 13.633263
A17: Existing refinanced debt / USD m | B17: ='WD40_Inputs_base'!B5+0 -> 86.995 | C17: ='WD40_Inputs_base'!B5+0 -> 86.995 | D17: ='WD40_Inputs_base'!B5+0 -> 86.995
A18: Target cash / USD m | B18: ='WD40_Inputs_base'!B6+0 -> 58.13 | C18: ='WD40_Inputs_base'!B6+0 -> 58.13 | D18: ='WD40_Inputs_base'!B6+0 -> 58.13
A19: R&D adjusted EBIT uplift / historical sales | B19: ='WD40_Inputs_base'!B15+0-(B14/B15) -> 0.0036560024 | C19: ='WD40_Inputs_base'!B15+0-(C14/C15) -> 0.0036560024 | D19: ='WD40_Inputs_base'!B15+0-(D14/D15) -> 0.0036560024
A20: Historical cash-flow D&A / sales | B20: =B13/B15 -> 0.01321161 | C20: =C13/C15 -> 0.01321161 | D20: =D13/D15 -> 0.01321161
A21: Historical reported EBITDA proxy / USD m | B21: =B14+B13 -> 111.984 | C21: =C14+C13 -> 111.984 | D21: =D14+D13 -> 111.984
A22: New borrowing / USD m | B22: =B21*B4 -> 615.912 | C22: =C21*C4 -> 615.912 | D22: =D21*D4 -> 615.912
A23: Target cash used at closing / USD m | B23: =IF((B18-B7)>0,(B18-B7),0) -> 53.13 | C23: =IF((C18-C7)>0,(C18-C7),0) -> 53.13 | D23: =IF((D18-D7)>0,(D18-D7),0) -> 53.13
A24: Cash retained before top-up / USD m | B24: =B18-B23 -> 5 | C24: =C18-C23 -> 5 | D24: =D18-D23 -> 5
A25: Sponsor-funded cash top-up / USD m | B25: =IF((B7-B24)>0,(B7-B24),0) -> 0 | C25: =IF((C7-C24)>0,(C7-C24),0) -> 0 | D25: =IF((D7-D24)>0,(D7-D24),0) -> 0
A26: Y1 Revenue / USD m | B26: ='WD40_DCF_base'!C4+0 -> 657.45454 | C26: ='WD40_DCF_base'!C4+0 -> 657.45454 | D26: ='WD40_DCF_base'!C4+0 -> 657.45454
A27: Y1 Adjusted EBIT / USD m | B27: ='WD40_DCF_base'!C6+0 -> 112.46951 | C27: ='WD40_DCF_base'!C6+0 -> 112.46951 | D27: ='WD40_DCF_base'!C6+0 -> 112.46951
A28: Y1 Reported EBIT proxy / USD m | B28: =B27-(B26*B19) -> 110.06585 | C28: =C27-(C26*C19) -> 110.06585 | D28: =D27-(D26*D19) -> 110.06585
A29: Y1 EBITDA proxy / USD m | B29: =B28+(B26*B20) -> 118.75189 | C29: =C28+(C26*C20) -> 118.75189 | D29: =D28+(D26*D20) -> 118.75189
A30: Y1 FCFF proxy / USD m | B30: ='WD40_DCF_base'!C11+0 -> 67.269919 | C30: ='WD40_DCF_base'!C11+0 -> 67.269919 | D30: ='WD40_DCF_base'!C11+0 -> 67.269919
A31: Y1 Tax rate | B31: ='WD40_DCF_base'!C7+0 -> 0.22200028 | C31: ='WD40_DCF_base'!C7+0 -> 0.22200028 | D31: ='WD40_DCF_base'!C7+0 -> 0.22200028
A32: Y1 Opening debt / USD m | B32: =B22+0 -> 615.912 | C32: =C22+0 -> 615.912 | D32: =D22+0 -> 615.912
A33: Y1 Interest / USD m | B33: =B32*B5 -> 49.27296 | C33: =C32*C5 -> 49.27296 | D33: =D32*D5 -> 49.27296
A34: Y1 Interest tax shield / USD m | B34: =IF(B33<IF(B28>0,B28,0),B33,IF(B28>0,B28,0))*B31 -> 10.938611 | C34: =IF(C33<IF(C28>0,C28,0),C33,IF(C28>0,C28,0))*C31 -> 10.938611 | D34: =IF(D33<IF(D28>0,D28,0),D33,IF(D28>0,D28,0))*D31 -> 10.938611
A35: Y1 Opening cash / USD m | B35: =(B24+B25)+0 -> 5 | C35: =(C24+C25)+0 -> 5 | D35: =(D24+D25)+0 -> 5
A36: Y1 Cash generated before principal / USD m | B36: =B30-B33+B34 -> 28.935569 | C36: =C30-C33+C34 -> 28.935569 | D36: =D30-D33+D34 -> 28.935569
A37: Y1 Cash available above minimum / USD m | B37: =B35+B36-B7 -> 28.935569 | C37: =C35+C36-C7 -> 28.935569 | D37: =D35+D36-D7 -> 28.935569
A38: Y1 Required amortization / USD m | B38: =IF(B32<(B22*B9),B32,(B22*B9)) -> 6.15912 | C38: =IF(C32<(C22*C9),C32,(C22*C9)) -> 6.15912 | D38: =IF(D32<(D22*D9),D32,(D22*D9)) -> 6.15912
A39: Y1 Funding feasible / 1=yes | B39: =IF(B37>=B38,1,0) -> 1 | C39: =IF(C37>=C38,1,0) -> 1 | D39: =IF(D37>=D38,1,0) -> 1
A40: Y1 Mandatory amortization paid / USD m | B40: =IF(B39=1,B38,IF(B37>0,B37,0)) -> 6.15912 | C40: =IF(C39=1,C38,IF(C37>0,C37,0)) -> 6.15912 | D40: =IF(D39=1,D38,IF(D37>0,D37,0)) -> 6.15912
A41: Y1 Additional cash sweep / USD m | B41: =IF(B39=1,IF((B32-B40)<(IF((B37-B40)>0,(B37-B40),0)*B8),(B32-B40),(IF((B37-B40)>0,(B37-B40),0)*B8)),0) -> 22.776449 | C41: =IF(C39=1,IF((C32-C40)<(IF((C37-C40)>0,(C37-C40),0)*C8),(C32-C40),(IF((C37-C40)>0,(C37-C40),0)*C8)),0) -> 22.776449 | D41: =IF(D39=1,IF((D32-D40)<(IF((D37-D40)>0,(D37-D40),0)*D8),(D32-D40),(IF((D37-D40)>0,(D37-D40),0)*D8)),0) -> 22.776449
A42: Y1 Closing debt / USD m | B42: =B32-B40-B41 -> 586.97643 | C42: =C32-C40-C41 -> 586.97643 | D42: =D32-D40-D41 -> 586.97643
A43: Y1 Closing cash / USD m | B43: =B35+B36-B40-B41 -> 5 | C43: =C35+C36-C40-C41 -> 5 | D43: =D35+D36-D40-D41 -> 5
A44: Y1 Funding shortfall / USD m | B44: =IF((B38-B37)>0,(B38-B37),0) -> 0 | C44: =IF((C38-C37)>0,(C38-C37),0) -> 0 | D44: =IF((D38-D37)>0,(D38-D37),0) -> 0
A45: Y2 Revenue / USD m | B45: ='WD40_DCF_base'!D4+0 -> 697.9172 | C45: ='WD40_DCF_base'!D4+0 -> 697.9172 | D45: ='WD40_DCF_base'!D4+0 -> 697.9172
A46: Y2 Adjusted EBIT / USD m | B46: ='WD40_DCF_base'!D6+0 -> 127.4682 | C46: ='WD40_DCF_base'!D6+0 -> 127.4682 | D46: ='WD40_DCF_base'!D6+0 -> 127.4682
A47: Y2 Reported EBIT proxy / USD m | B47: =B46-(B45*B19) -> 124.91662 | C47: =C46-(C45*C19) -> 124.91662 | D47: =D46-(D45*D19) -> 124.91662
A48: Y2 EBITDA proxy / USD m | B48: =B47+(B45*B20) -> 134.13723 | C48: =C47+(C45*C20) -> 134.13723 | D48: =D47+(D45*D20) -> 134.13723
A49: Y2 FCFF proxy / USD m | B49: ='WD40_DCF_base'!D11+0 -> 77.693773 | C49: ='WD40_DCF_base'!D11+0 -> 77.693773 | D49: ='WD40_DCF_base'!D11+0 -> 77.693773
A50: Y2 Tax rate | B50: ='WD40_DCF_base'!D7+0 -> 0.22200028 | C50: ='WD40_DCF_base'!D7+0 -> 0.22200028 | D50: ='WD40_DCF_base'!D7+0 -> 0.22200028
A51: Y2 Opening debt / USD m | B51: =B42+0 -> 586.97643 | C51: =C42+0 -> 586.97643 | D51: =D42+0 -> 586.97643
A52: Y2 Interest / USD m | B52: =B51*B5 -> 46.958114 | C52: =C51*C5 -> 46.958114 | D52: =D51*D5 -> 46.958114
A53: Y2 Interest tax shield / USD m | B53: =IF(B52<IF(B47>0,B47,0),B52,IF(B47>0,B47,0))*B50 -> 10.424714 | C53: =IF(C52<IF(C47>0,C47,0),C52,IF(C47>0,C47,0))*C50 -> 10.424714 | D53: =IF(D52<IF(D47>0,D47,0),D52,IF(D47>0,D47,0))*D50 -> 10.424714
A54: Y2 Opening cash / USD m | B54: =B43+0 -> 5 | C54: =C43+0 -> 5 | D54: =D43+0 -> 5
A55: Y2 Cash generated before principal / USD m | B55: =B49-B52+B53 -> 41.160373 | C55: =C49-C52+C53 -> 41.160373 | D55: =D49-D52+D53 -> 41.160373
A56: Y2 Cash available above minimum / USD m | B56: =B54+B55-B7 -> 41.160373 | C56: =C54+C55-C7 -> 41.160373 | D56: =D54+D55-D7 -> 41.160373
A57: Y2 Required amortization / USD m | B57: =IF(B51<(B22*B9),B51,(B22*B9)) -> 6.15912 | C57: =IF(C51<(C22*C9),C51,(C22*C9)) -> 6.15912 | D57: =IF(D51<(D22*D9),D51,(D22*D9)) -> 6.15912
A58: Y2 Funding feasible / 1=yes | B58: =IF(B56>=B57,1,0) -> 1 | C58: =IF(C56>=C57,1,0) -> 1 | D58: =IF(D56>=D57,1,0) -> 1
A59: Y2 Mandatory amortization paid / USD m | B59: =IF(B58=1,B57,IF(B56>0,B56,0)) -> 6.15912 | C59: =IF(C58=1,C57,IF(C56>0,C56,0)) -> 6.15912 | D59: =IF(D58=1,D57,IF(D56>0,D56,0)) -> 6.15912
A60: Y2 Additional cash sweep / USD m | B60: =IF(B58=1,IF((B51-B59)<(IF((B56-B59)>0,(B56-B59),0)*B8),(B51-B59),(IF((B56-B59)>0,(B56-B59),0)*B8)),0) -> 35.001253 | C60: =IF(C58=1,IF((C51-C59)<(IF((C56-C59)>0,(C56-C59),0)*C8),(C51-C59),(IF((C56-C59)>0,(C56-C59),0)*C8)),0) -> 35.001253 | D60: =IF(D58=1,IF((D51-D59)<(IF((D56-D59)>0,(D56-D59),0)*D8),(D51-D59),(IF((D56-D59)>0,(D56-D59),0)*D8)),0) -> 35.001253
A61: Y2 Closing debt / USD m | B61: =B51-B59-B60 -> 545.81606 | C61: =C51-C59-C60 -> 545.81606 | D61: =D51-D59-D60 -> 545.81606
A62: Y2 Closing cash / USD m | B62: =B54+B55-B59-B60 -> 5 | C62: =C54+C55-C59-C60 -> 5 | D62: =D54+D55-D59-D60 -> 5
A63: Y2 Funding shortfall / USD m | B63: =IF((B57-B56)>0,(B57-B56),0) -> 0 | C63: =IF((C57-C56)>0,(C57-C56),0) -> 0 | D63: =IF((D57-D56)>0,(D57-D56),0) -> 0
A64: Y3 Revenue / USD m | B64: ='WD40_DCF_base'!E4+0 -> 740.87011 | C64: ='WD40_DCF_base'!E4+0 -> 740.87011 | D64: ='WD40_DCF_base'!E4+0 -> 740.87011
A65: Y3 Adjusted EBIT / USD m | B65: ='WD40_DCF_base'!E6+0 -> 139.60011 | C65: ='WD40_DCF_base'!E6+0 -> 139.60011 | D65: ='WD40_DCF_base'!E6+0 -> 139.60011
A66: Y3 Reported EBIT proxy / USD m | B66: =B65-(B64*B19) -> 136.89149 | C66: =C65-(C64*C19) -> 136.89149 | D66: =D65-(D64*D19) -> 136.89149
A67: Y3 EBITDA proxy / USD m | B67: =B66+(B64*B20) -> 146.67958 | C67: =C66+(C64*C20) -> 146.67958 | D67: =D66+(D64*D20) -> 146.67958
A68: Y3 FCFF proxy / USD m | B68: ='WD40_DCF_base'!E11+0 -> 85.81064 | C68: ='WD40_DCF_base'!E11+0 -> 85.81064 | D68: ='WD40_DCF_base'!E11+0 -> 85.81064
A69: Y3 Tax rate | B69: ='WD40_DCF_base'!E7+0 -> 0.22200028 | C69: ='WD40_DCF_base'!E7+0 -> 0.22200028 | D69: ='WD40_DCF_base'!E7+0 -> 0.22200028
A70: Y3 Opening debt / USD m | B70: =B61+0 -> 545.81606 | C70: =C61+0 -> 545.81606 | D70: =D61+0 -> 545.81606
A71: Y3 Interest / USD m | B71: =B70*B5 -> 43.665285 | C71: =C70*C5 -> 43.665285 | D71: =D70*D5 -> 43.665285
A72: Y3 Interest tax shield / USD m | B72: =IF(B71<IF(B66>0,B66,0),B71,IF(B66>0,B66,0))*B69 -> 9.6937052 | C72: =IF(C71<IF(C66>0,C66,0),C71,IF(C66>0,C66,0))*C69 -> 9.6937052 | D72: =IF(D71<IF(D66>0,D66,0),D71,IF(D66>0,D66,0))*D69 -> 9.6937052
A73: Y3 Opening cash / USD m | B73: =B62+0 -> 5 | C73: =C62+0 -> 5 | D73: =D62+0 -> 5
A74: Y3 Cash generated before principal / USD m | B74: =B68-B71+B72 -> 51.839061 | C74: =C68-C71+C72 -> 51.839061 | D74: =D68-D71+D72 -> 51.839061
A75: Y3 Cash available above minimum / USD m | B75: =B73+B74-B7 -> 51.839061 | C75: =C73+C74-C7 -> 51.839061 | D75: =D73+D74-D7 -> 51.839061
A76: Y3 Required amortization / USD m | B76: =IF(B70<(B22*B9),B70,(B22*B9)) -> 6.15912 | C76: =IF(C70<(C22*C9),C70,(C22*C9)) -> 6.15912 | D76: =IF(D70<(D22*D9),D70,(D22*D9)) -> 6.15912
A77: Y3 Funding feasible / 1=yes | B77: =IF(B75>=B76,1,0) -> 1 | C77: =IF(C75>=C76,1,0) -> 1 | D77: =IF(D75>=D76,1,0) -> 1
A78: Y3 Mandatory amortization paid / USD m | B78: =IF(B77=1,B76,IF(B75>0,B75,0)) -> 6.15912 | C78: =IF(C77=1,C76,IF(C75>0,C75,0)) -> 6.15912 | D78: =IF(D77=1,D76,IF(D75>0,D75,0)) -> 6.15912
A79: Y3 Additional cash sweep / USD m | B79: =IF(B77=1,IF((B70-B78)<(IF((B75-B78)>0,(B75-B78),0)*B8),(B70-B78),(IF((B75-B78)>0,(B75-B78),0)*B8)),0) -> 45.679941 | C79: =IF(C77=1,IF((C70-C78)<(IF((C75-C78)>0,(C75-C78),0)*C8),(C70-C78),(IF((C75-C78)>0,(C75-C78),0)*C8)),0) -> 45.679941 | D79: =IF(D77=1,IF((D70-D78)<(IF((D75-D78)>0,(D75-D78),0)*D8),(D70-D78),(IF((D75-D78)>0,(D75-D78),0)*D8)),0) -> 45.679941
A80: Y3 Closing debt / USD m | B80: =B70-B78-B79 -> 493.977 | C80: =C70-C78-C79 -> 493.977 | D80: =D70-D78-D79 -> 493.977
A81: Y3 Closing cash / USD m | B81: =B73+B74-B78-B79 -> 5 | C81: =C73+C74-C78-C79 -> 5 | D81: =D73+D74-D78-D79 -> 5
A82: Y3 Funding shortfall / USD m | B82: =IF((B76-B75)>0,(B76-B75),0) -> 0 | C82: =IF((C76-C75)>0,(C76-C75),0) -> 0 | D82: =IF((D76-D75)>0,(D76-D75),0) -> 0
A83: Y4 Revenue / USD m | B83: ='WD40_DCF_base'!F4+0 -> 786.46653 | C83: ='WD40_DCF_base'!F4+0 -> 786.46653 | D83: ='WD40_DCF_base'!F4+0 -> 786.46653
A84: Y4 Adjusted EBIT / USD m | B84: ='WD40_DCF_base'!F6+0 -> 152.74251 | C84: ='WD40_DCF_base'!F6+0 -> 152.74251 | D84: ='WD40_DCF_base'!F6+0 -> 152.74251
A85: Y4 Reported EBIT proxy / USD m | B85: =B84-(B83*B19) -> 149.86719 | C85: =C84-(C83*C19) -> 149.86719 | D85: =D84-(D83*D19) -> 149.86719
A86: Y4 EBITDA proxy / USD m | B86: =B85+(B83*B20) -> 160.25768 | C86: =C85+(C83*C20) -> 160.25768 | D86: =D85+(D83*D20) -> 160.25768
A87: Y4 FCFF proxy / USD m | B87: ='WD40_DCF_base'!F11+0 -> 94.632321 | C87: ='WD40_DCF_base'!F11+0 -> 94.632321 | D87: ='WD40_DCF_base'!F11+0 -> 94.632321
A88: Y4 Tax rate | B88: ='WD40_DCF_base'!F7+0 -> 0.22200028 | C88: ='WD40_DCF_base'!F7+0 -> 0.22200028 | D88: ='WD40_DCF_base'!F7+0 -> 0.22200028
A89: Y4 Opening debt / USD m | B89: =B80+0 -> 493.977 | C89: =C80+0 -> 493.977 | D89: =D80+0 -> 493.977
A90: Y4 Interest / USD m | B90: =B89*B5 -> 39.51816 | C90: =C89*C5 -> 39.51816 | D90: =D89*D5 -> 39.51816
A91: Y4 Interest tax shield / USD m | B91: =IF(B90<IF(B85>0,B85,0),B90,IF(B85>0,B85,0))*B88 -> 8.7730424 | C91: =IF(C90<IF(C85>0,C85,0),C90,IF(C85>0,C85,0))*C88 -> 8.7730424 | D91: =IF(D90<IF(D85>0,D85,0),D90,IF(D85>0,D85,0))*D88 -> 8.7730424
A92: Y4 Opening cash / USD m | B92: =B81+0 -> 5 | C92: =C81+0 -> 5 | D92: =D81+0 -> 5
A93: Y4 Cash generated before principal / USD m | B93: =B87-B90+B91 -> 63.887203 | C93: =C87-C90+C91 -> 63.887203 | D93: =D87-D90+D91 -> 63.887203
A94: Y4 Cash available above minimum / USD m | B94: =B92+B93-B7 -> 63.887203 | C94: =C92+C93-C7 -> 63.887203 | D94: =D92+D93-D7 -> 63.887203
A95: Y4 Required amortization / USD m | B95: =IF(B89<(B22*B9),B89,(B22*B9)) -> 6.15912 | C95: =IF(C89<(C22*C9),C89,(C22*C9)) -> 6.15912 | D95: =IF(D89<(D22*D9),D89,(D22*D9)) -> 6.15912
A96: Y4 Funding feasible / 1=yes | B96: =IF(B94>=B95,1,0) -> 1 | C96: =IF(C94>=C95,1,0) -> 1 | D96: =IF(D94>=D95,1,0) -> 1
A97: Y4 Mandatory amortization paid / USD m | B97: =IF(B96=1,B95,IF(B94>0,B94,0)) -> 6.15912 | C97: =IF(C96=1,C95,IF(C94>0,C94,0)) -> 6.15912 | D97: =IF(D96=1,D95,IF(D94>0,D94,0)) -> 6.15912
A98: Y4 Additional cash sweep / USD m | B98: =IF(B96=1,IF((B89-B97)<(IF((B94-B97)>0,(B94-B97),0)*B8),(B89-B97),(IF((B94-B97)>0,(B94-B97),0)*B8)),0) -> 57.728083 | C98: =IF(C96=1,IF((C89-C97)<(IF((C94-C97)>0,(C94-C97),0)*C8),(C89-C97),(IF((C94-C97)>0,(C94-C97),0)*C8)),0) -> 57.728083 | D98: =IF(D96=1,IF((D89-D97)<(IF((D94-D97)>0,(D94-D97),0)*D8),(D89-D97),(IF((D94-D97)>0,(D94-D97),0)*D8)),0) -> 57.728083
A99: Y4 Closing debt / USD m | B99: =B89-B97-B98 -> 430.08979 | C99: =C89-C97-C98 -> 430.08979 | D99: =D89-D97-D98 -> 430.08979
A100: Y4 Closing cash / USD m | B100: =B92+B93-B97-B98 -> 5 | C100: =C92+C93-C97-C98 -> 5 | D100: =D92+D93-D97-D98 -> 5
...

Sheet WD40_DDM
A1: WD40_DDM | B1: 5% dividend growth | C1: 7% dividend growth | D1: 9% dividend growth
A2: Annualized starting dividend / USD per share | B2: 3.76 | C2: 3.76 | D2: 3.76
A3: Stage-one dividend growth | B3: 0.05 | C3: 0.07 | D3: 0.09
A4: Terminal dividend growth | B4: 0.025 | C4: 0.025 | D4: 0.025
A5: Cost of equity / analyst assumption | B5: 0.095 | C5: 0.09 | D5: 0.085
A6: Stage-one horizon / years | B6: 10 | C6: 10 | D6: 10
A7: Valuation dilution proxy / million shares | B7: ='WD40_Inputs_base'!B9+0 -> 13.633263 | C7: ='WD40_Inputs_base'!B9+0 -> 13.633263 | D7: ='WD40_Inputs_base'!B9+0 -> 13.633263
A8: Historical interest expense / USD m | B8: 3.441 | C8: 3.441 | D8: 3.441
A9: Y1 dividend / USD per share | B9: =B2*((1+B3)^1) -> 3.948 | C9: =C2*((1+C3)^1) -> 4.0232 | D9: =D2*((1+D3)^1) -> 4.0984
A10: Y1 discount factor | B10: =1/((1+B5)^1) -> 0.91324201 | C10: =1/((1+C5)^1) -> 0.91743119 | D10: =1/((1+D5)^1) -> 0.92165899
A11: Y1 PV dividend / USD per share | B11: =B9*B10 -> 3.6054795 | C11: =C9*C10 -> 3.6910092 | D11: =D9*D10 -> 3.7773272
A12: Y1 constant-debt FCFE proxy / USD m | B12: ='WD40_DCF_base'!C11+0-(B8*(1-'WD40_DCF_base'!C7+0)) -> 64.592821 | C12: ='WD40_DCF_base'!C11+0-(C8*(1-'WD40_DCF_base'!C7+0)) -> 64.592821 | D12: ='WD40_DCF_base'!C11+0-(D8*(1-'WD40_DCF_base'!C7+0)) -> 64.592821
A13: Y1 total dividends / USD m | B13: =B9*B7 -> 53.824122 | C13: =C9*C7 -> 54.849344 | D13: =D9*D7 -> 55.874565
A14: Y1 payout covered / 1=yes | B14: =IF(B13<=B12,1,0) -> 1 | C14: =IF(C13<=C12,1,0) -> 1 | D14: =IF(D13<=D12,1,0) -> 1
A15: Y2 dividend / USD per share | B15: =B2*((1+B3)^2) -> 4.1454 | C15: =C2*((1+C3)^2) -> 4.304824 | D15: =D2*((1+D3)^2) -> 4.467256
A16: Y2 discount factor | B16: =1/((1+B5)^2) -> 0.83401097 | C16: =1/((1+C5)^2) -> 0.84167999 | D16: =1/((1+D5)^2) -> 0.84945529
A17: Y2 PV dividend / USD per share | B17: =B15*B16 -> 3.4573091 | C17: =C15*C16 -> 3.6232842 | D17: =D15*D16 -> 3.7947342
A18: Y2 constant-debt FCFE proxy / USD m | B18: ='WD40_DCF_base'!D11+0-(B8*(1-'WD40_DCF_base'!D7+0)) -> 75.016676 | C18: ='WD40_DCF_base'!D11+0-(C8*(1-'WD40_DCF_base'!D7+0)) -> 75.016676 | D18: ='WD40_DCF_base'!D11+0-(D8*(1-'WD40_DCF_base'!D7+0)) -> 75.016676
A19: Y2 total dividends / USD m | B19: =B15*B7 -> 56.515328 | C19: =C15*C7 -> 58.688798 | D19: =D15*D7 -> 60.903276
A20: Y2 payout covered / 1=yes | B20: =IF(B19<=B18,1,0) -> 1 | C20: =IF(C19<=C18,1,0) -> 1 | D20: =IF(D19<=D18,1,0) -> 1
A21: Y3 dividend / USD per share | B21: =B2*((1+B3)^3) -> 4.35267 | C21: =C2*((1+C3)^3) -> 4.6061617 | D21: =D2*((1+D3)^3) -> 4.869309
A22: Y3 discount factor | B22: =1/((1+B5)^3) -> 0.76165385 | C22: =1/((1+C5)^3) -> 0.77218348 | D22: =1/((1+D5)^3) -> 0.7829081
A23: Y3 PV dividend / USD per share | B23: =B21*B22 -> 3.3152279 | C23: =C21*C22 -> 3.556802 | D23: =D21*D22 -> 3.8122215
A24: Y3 constant-debt FCFE proxy / USD m | B24: ='WD40_DCF_base'!E11+0-(B8*(1-'WD40_DCF_base'!E7+0)) -> 83.133543 | C24: ='WD40_DCF_base'!E11+0-(C8*(1-'WD40_DCF_base'!E7+0)) -> 83.133543 | D24: ='WD40_DCF_base'!E11+0-(D8*(1-'WD40_DCF_base'!E7+0)) -> 83.133543
A25: Y3 total dividends / USD m | B25: =B21*B7 -> 59.341095 | C25: =C21*C7 -> 62.797014 | D25: =D21*D7 -> 66.384571
A26: Y3 payout covered / 1=yes | B26: =IF(B25<=B24,1,0) -> 1 | C26: =IF(C25<=C24,1,0) -> 1 | D26: =IF(D25<=D24,1,0) -> 1
A27: Y4 dividend / USD per share | B27: =B2*((1+B3)^4) -> 4.5703035 | C27: =C2*((1+C3)^4) -> 4.928593 | D27: =D2*((1+D3)^4) -> 5.3075469
A28: Y4 discount factor | B28: =1/((1+B5)^4) -> 0.69557429 | C28: =1/((1+C5)^4) -> 0.70842521 | D28: =1/((1+D5)^4) -> 0.72157428
A29: Y4 PV dividend / USD per share | B29: =B27*B28 -> 3.1789856 | C29: =C27*C28 -> 3.4915395 | D29: =D27*D28 -> 3.8297893
A30: Y4 constant-debt FCFE proxy / USD m | B30: ='WD40_DCF_base'!F11+0-(B8*(1-'WD40_DCF_base'!F7+0)) -> 91.955224 | C30: ='WD40_DCF_base'!F11+0-(C8*(1-'WD40_DCF_base'!F7+0)) -> 91.955224 | D30: ='WD40_DCF_base'!F11+0-(D8*(1-'WD40_DCF_base'!F7+0)) -> 91.955224
A31: Y4 total dividends / USD m | B31: =B27*B7 -> 62.30815 | C31: =C27*C7 -> 67.192805 | D31: =D27*D7 -> 72.359182
A32: Y4 payout covered / 1=yes | B32: =IF(B31<=B30,1,0) -> 1 | C32: =IF(C31<=C30,1,0) -> 1 | D32: =IF(D31<=D30,1,0) -> 1
A33: Y5 dividend / USD per share | B33: =B2*((1+B3)^5) -> 4.7988187 | C33: =C2*((1+C3)^5) -> 5.2735945 | D33: =D2*((1+D3)^5) -> 5.7852261
A34: Y5 discount factor | B34: =1/((1+B5)^5) -> 0.63522767 | C34: =1/((1+C5)^5) -> 0.64993139 | D34: =1/((1+D5)^5) -> 0.66504542
A35: Y5 PV dividend / USD per share | B35: =B33*B34 -> 3.0483424 | C35: =C33*C34 -> 3.4274746 | D35: =D33*D34 -> 3.8474381
A36: Y5 constant-debt FCFE proxy / USD m | B36: ='WD40_DCF_base'!G11+0-(B8*(1-'WD40_DCF_base'!G7+0)) -> 104.58871 | C36: ='WD40_DCF_base'!G11+0-(C8*(1-'WD40_DCF_base'!G7+0)) -> 104.58871 | D36: ='WD40_DCF_base'!G11+0-(D8*(1-'WD40_DCF_base'!G7+0)) -> 104.58871
A37: Y5 total dividends / USD m | B37: =B33*B7 -> 65.423557 | C37: =C33*C7 -> 71.896301 | D37: =D33*D7 -> 78.871509
A38: Y5 payout covered / 1=yes | B38: =IF(B37<=B36,1,0) -> 1 | C38: =IF(C37<=C36,1,0) -> 1 | D38: =IF(D37<=D36,1,0) -> 1
A39: Y6 dividend / USD per share | B39: =B2*((1+B3)^6) -> 5.0387596 | C39: =C2*((1+C3)^6) -> 5.6427461 | D39: =D2*((1+D3)^6) -> 6.3058964
A40: Y6 discount factor | B40: =1/((1+B5)^6) -> 0.58011659 | C40: =1/((1+C5)^6) -> 0.59626733 | D40: =1/((1+D5)^6) -> 0.61294509
A41: Y6 PV dividend / USD per share | B41: =B39*B40 -> 2.923068 | C41: =C39*C40 -> 3.3645851 | D41: =D39*D40 -> 3.8651683
A42: Y6 constant-debt FCFE proxy / USD m | B42: ='WD40_DCF_base'!H11+0-(B8*(1-'WD40_DCF_base'!H7+0)) -> 112.65629 | C42: ='WD40_DCF_base'!H11+0-(C8*(1-'WD40_DCF_base'!H7+0)) -> 112.65629 | D42: ='WD40_DCF_base'!H11+0-(D8*(1-'WD40_DCF_base'!H7+0)) -> 112.65629
A43: Y6 total dividends / USD m | B43: =B39*B7 -> 68.694735 | C43: =C39*C7 -> 76.929042 | D43: =D39*D7 -> 85.969944
A44: Y6 payout covered / 1=yes | B44: =IF(B43<=B42,1,0) -> 1 | C44: =IF(C43<=C42,1,0) -> 1 | D44: =IF(D43<=D42,1,0) -> 1
A45: Y7 dividend / USD per share | B45: =B2*((1+B3)^7) -> 5.2906976 | C45: =C2*((1+C3)^7) -> 6.0377384 | D45: =D2*((1+D3)^7) -> 6.8734271
A46: Y7 discount factor | B46: =1/((1+B5)^7) -> 0.52978684 | C46: =1/((1+C5)^7) -> 0.54703424 | D46: =1/((1+D5)^7) -> 0.56492635
A47: Y7 PV dividend / USD per share | B47: =B45*B46 -> 2.802942 | C47: =C45*C46 -> 3.3028496 | D47: =D45*D46 -> 3.8829801
A48: Y7 constant-debt FCFE proxy / USD m | B48: ='WD40_DCF_base'!I11+0-(B8*(1-'WD40_DCF_base'!I7+0)) -> 120.42224 | C48: ='WD40_DCF_base'!I11+0-(C8*(1-'WD40_DCF_base'!I7+0)) -> 120.42224 | D48: ='WD40_DCF_base'!I11+0-(D8*(1-'WD40_DCF_base'!I7+0)) -> 120.42224
A49: Y7 total dividends / USD m | B49: =B45*B7 -> 72.129472 | C49: =C45*C7 -> 82.314075 | D49: =D45*D7 -> 93.707239
A50: Y7 payout covered / 1=yes | B50: =IF(B49<=B48,1,0) -> 1 | C50: =IF(C49<=C48,1,0) -> 1 | D50: =IF(D49<=D48,1,0) -> 1
A51: Y8 dividend / USD per share | B51: =B2*((1+B3)^8) -> 5.5552325 | C51: =C2*((1+C3)^8) -> 6.46038 | D51: =D2*((1+D3)^8) -> 7.4920355
A52: Y8 discount factor | B52: =1/((1+B5)^8) -> 0.4838236 | C52: =1/((1+C5)^8) -> 0.50186628 | D52: =1/((1+D5)^8) -> 0.52066945
A53: Y8 PV dividend / USD per share | B53: =B51*B52 -> 2.6877526 | C53: =C51*C52 -> 3.2422469 | D53: =D51*D52 -> 3.900874
A54: Y8 constant-debt FCFE proxy / USD m | B54: ='WD40_DCF_base'!J11+0-(B8*(1-'WD40_DCF_base'!J7+0)) -> 127.7448 | C54: ='WD40_DCF_base'!J11+0-(C8*(1-'WD40_DCF_base'!J7+0)) -> 127.7448 | D54: ='WD40_DCF_base'!J11+0-(D8*(1-'WD40_DCF_base'!J7+0)) -> 127.7448
A55: Y8 total dividends / USD m | B55: =B51*B7 -> 75.735945 | C55: =C51*C7 -> 88.07606 | D55: =D51*D7 -> 102.14089
A56: Y8 payout covered / 1=yes | B56: =IF(B55<=B54,1,0) -> 1 | C56: =IF(C55<=C54,1,0) -> 1 | D56: =IF(D55<=D54,1,0) -> 1
A57: Y9 dividend / USD per share | B57: =B2*((1+B3)^9) -> 5.8329941 | C57: =C2*((1+C3)^9) -> 6.9126066 | D57: =D2*((1+D3)^9) -> 8.1663187
A58: Y9 discount factor | B58: =1/((1+B5)^9) -> 0.44184803 | C58: =1/((1+C5)^9) -> 0.46042778 | D58: =1/((1+D5)^9) -> 0.47987968
A59: Y9 PV dividend / USD per share | B59: =B57*B58 -> 2.577297 | C59: =C57*C58 -> 3.1827561 | D59: =D57*D58 -> 3.9188504
A60: Y9 constant-debt FCFE proxy / USD m | B60: ='WD40_DCF_base'!K11+0-(B8*(1-'WD40_DCF_base'!K7+0)) -> 134.48233 | C60: ='WD40_DCF_base'!K11+0-(C8*(1-'WD40_DCF_base'!K7+0)) -> 134.48233 | D60: ='WD40_DCF_base'!K11+0-(D8*(1-'WD40_DCF_base'!K7+0)) -> 134.48233
A61: Y9 total dividends / USD m | B61: =B57*B7 -> 79.522743 | C61: =C57*C7 -> 94.241384 | D61: =D57*D7 -> 111.33357
A62: Y9 payout covered / 1=yes | B62: =IF(B61<=B60,1,0) -> 1 | C62: =IF(C61<=C60,1,0) -> 1 | D62: =IF(D61<=D60,1,0) -> 1
A63: Y10 dividend / USD per share | B63: =B2*((1+B3)^10) -> 6.1246438 | C63: =C2*((1+C3)^10) -> 7.3964891 | D63: =D2*((1+D3)^10) -> 8.9012874
A64: Y10 discount factor | B64: =1/((1+B5)^10) -> 0.40351419 | C64: =1/((1+C5)^10) -> 0.42241081 | D64: =1/((1+D5)^10) -> 0.44228542
A65: Y10 PV dividend / USD per share | B65: =B63*B64 -> 2.4713807 | C65: =C63*C64 -> 3.1243569 | D65: =D63*D64 -> 3.9369096
A66: Y10 constant-debt FCFE proxy / USD m | B66: ='WD40_DCF_base'!L11+0-(B8*(1-'WD40_DCF_base'!L7+0)) -> 136.79341 | C66: ='WD40_DCF_base'!L11+0-(C8*(1-'WD40_DCF_base'!L7+0)) -> 136.79341 | D66: ='WD40_DCF_base'!L11+0-(D8*(1-'WD40_DCF_base'!L7+0)) -> 136.79341
A67: Y10 total dividends / USD m | B67: =B63*B7 -> 83.49888 | C67: =C63*C7 -> 100.83828 | D67: =D63*D7 -> 121.35359
A68: Y10 payout covered / 1=yes | B68: =IF(B67<=B66,1,0) -> 1 | C68: =IF(C67<=C66,1,0) -> 1 | D68: =IF(D67<=D66,1,0) -> 1
A69: Terminal dividend / USD per share | B69: =B63*(1+B4) -> 6.2777599 | C69: =C63*(1+C4) -> 7.5814013 | D69: =D63*(1+D4) -> 9.1238196
A70: Terminal value / USD per share | B70: =B69/(B5-B4) -> 89.682284 | C70: =C69/(C5-C4) -> 116.63694 | D70: =D69/(D5-D4) -> 152.06366
A71: PV terminal value / USD per share | B71: =B70*B64 -> 36.188074 | C71: =C70*C64 -> 49.268705 | D71: =D70*D64 -> 67.255539
A72: DDM value / USD per share | B72: =IF(B6=10,IF(B5>B4,0+B11+B17+B23+B29+B35+B41+B47+B53+B59+B65+B71,"Blocked: cost of equity must exceed growth"),"Blocked: this schedule requires 10 years") -> 66.255859 | C72: =IF(C6=10,IF(C5>C4,0+C11+C17+C23+C29+C35+C41+C47+C53+C59+C65+C71,"Blocked: cost of equity must exceed growth"),"Blocked: this schedule requires 10 years") -> 83.27561 | D72: =IF(D6=10,IF(D5>D4,0+D11+D17+D23+D29+D35+D41+D47+D53+D59+D65+D71,"Blocked: cost of equity must exceed growth"),"Blocked: this schedule requires 10 years") -> 105.82183
A73: Covered years / count | B73: =0+B14+B20+B26+B32+B38+B44+B50+B56+B62+B68 -> 10 | C73: =0+C14+C20+C26+C32+C38+C44+C50+C56+C62+C68 -> 10 | D73: =0+D14+D20+D26+D32+D38+D44+D50+D56+D62+D68 -> 10

Sheet WD40_Synergies
A1: WD40_Synergies | B1: 10% incremental cost savings | C1: 20% incremental cost savings | D1: 30% incremental cost savings
A2: Incremental cost savings fraction | B2: 0.1 | C2: 0.2 | D2: 0.3
A3: Historical cost base / USD m | B3: 237.55 | C3: 237.55 | D3: 237.55
A4: Years to full savings | B4: 3 | C4: 3 | D4: 3
A5: Upfront cost / initial annual savings / USD m | B5: =B3*B2 -> 23.755 | C5: =C3*C2 -> 47.51 | D5: =D3*D2 -> 71.265
A6: Base revenue / USD m | B6: ='WD40_Inputs_base'!B2+0 -> 619.985 | C6: ='WD40_Inputs_base'!B2+0 -> 619.985 | D6: ='WD40_Inputs_base'!B2+0 -> 619.985
A7: Valuation dilution proxy / million shares | B7: ='WD40_Inputs_base'!B9+0 -> 13.633263 | C7: ='WD40_Inputs_base'!B9+0 -> 13.633263 | D7: ='WD40_Inputs_base'!B9+0 -> 13.633263
A8: Terminal growth | B8: 0.025 | C8: 0.025 | D8: 0.025
A9: Terminal WACC | B9: ='WD40_DCF_base'!L13+0 -> 0.07 | C9: ='WD40_DCF_base'!L13+0 -> 0.07 | D9: ='WD40_DCF_base'!L13+0 -> 0.07
A10: Terminal tax rate | B10: ='WD40_Inputs_base'!B12+0 -> 0.25 | C10: ='WD40_Inputs_base'!B12+0 -> 0.25 | D10: ='WD40_Inputs_base'!B12+0 -> 0.25
A11: Standalone DCF / USD per share | B11: ='WD40_DCF_base'!B28+0 -> 159.17021 | C11: ='WD40_DCF_base'!B28+0 -> 159.17021 | D11: ='WD40_DCF_base'!B28+0 -> 159.17021
A12: Y1 revenue / USD m | B12: ='WD40_DCF_base'!C4+0 -> 657.45454 | C12: ='WD40_DCF_base'!C4+0 -> 657.45454 | D12: ='WD40_DCF_base'!C4+0 -> 657.45454
A13: Y1 ramp to full savings | B13: =IF((1/B4)>1,1,(1/B4)) -> 0.33333333 | C13: =IF((1/C4)>1,1,(1/C4)) -> 0.33333333 | D13: =IF((1/D4)>1,1,(1/D4)) -> 0.33333333
A14: Y1 incremental pretax savings / USD m | B14: =B3*B2*(B12/B6)*B13 -> 8.3968873 | C14: =C3*C2*(C12/C6)*C13 -> 16.793775 | D14: =D3*D2*(D12/D6)*D13 -> 25.190662
A15: Y1 after-tax savings / USD m | B15: =B14*(1-'WD40_DCF_base'!C7+0) -> 6.532776 | C15: =C14*(1-'WD40_DCF_base'!C7+0) -> 13.065552 | D15: =D14*(1-'WD40_DCF_base'!C7+0) -> 19.598328
A16: Y1 PV savings / USD m | B16: =B15*'WD40_DCF_base'!C14+0 -> 6.077001 | C16: =C15*'WD40_DCF_base'!C14+0 -> 12.154002 | D16: =D15*'WD40_DCF_base'!C14+0 -> 18.231003
A17: Y2 revenue / USD m | B17: ='WD40_DCF_base'!D4+0 -> 697.9172 | C17: ='WD40_DCF_base'!D4+0 -> 697.9172 | D17: ='WD40_DCF_base'!D4+0 -> 697.9172
A18: Y2 ramp to full savings | B18: =IF((2/B4)>1,1,(2/B4)) -> 0.66666667 | C18: =IF((2/C4)>1,1,(2/C4)) -> 0.66666667 | D18: =IF((2/D4)>1,1,(2/D4)) -> 0.66666667
A19: Y2 incremental pretax savings / USD m | B19: =B3*B2*(B17/B6)*B18 -> 17.827338 | C19: =C3*C2*(C17/C6)*C18 -> 35.654676 | D19: =D3*D2*(D17/D6)*D18 -> 53.482013
A20: Y2 after-tax savings / USD m | B20: =B19*(1-'WD40_DCF_base'!D7+0) -> 13.869664 | C20: =C19*(1-'WD40_DCF_base'!D7+0) -> 27.739328 | D20: =D19*(1-'WD40_DCF_base'!D7+0) -> 41.608992
A21: Y2 PV savings / USD m | B21: =B20*'WD40_DCF_base'!D14+0 -> 12.001873 | C21: =C20*'WD40_DCF_base'!D14+0 -> 24.003745 | D21: =D20*'WD40_DCF_base'!D14+0 -> 36.005618
A22: Y3 revenue / USD m | B22: ='WD40_DCF_base'!E4+0 -> 740.87011 | C22: ='WD40_DCF_base'!E4+0 -> 740.87011 | D22: ='WD40_DCF_base'!E4+0 -> 740.87011
A23: Y3 ramp to full savings | B23: =IF((3/B4)>1,1,(3/B4)) -> 1 | C23: =IF((3/C4)>1,1,(3/C4)) -> 1 | D23: =IF((3/D4)>1,1,(3/D4)) -> 1
A24: Y3 incremental pretax savings / USD m | B24: =B3*B2*(B22/B6)*B23 -> 28.386767 | C24: =C3*C2*(C22/C6)*C23 -> 56.773533 | D24: =D3*D2*(D22/D6)*D23 -> 85.1603
A25: Y3 after-tax savings / USD m | B25: =B24*(1-'WD40_DCF_base'!E7+0) -> 22.084897 | C25: =C24*(1-'WD40_DCF_base'!E7+0) -> 44.169793 | D25: =D24*(1-'WD40_DCF_base'!E7+0) -> 66.25469
A26: Y3 PV savings / USD m | B26: =B25*'WD40_DCF_base'!E14+0 -> 17.777471 | C26: =C25*'WD40_DCF_base'!E14+0 -> 35.554942 | D26: =D25*'WD40_DCF_base'!E14+0 -> 53.332413
A27: Y4 revenue / USD m | B27: ='WD40_DCF_base'!F4+0 -> 786.46653 | C27: ='WD40_DCF_base'!F4+0 -> 786.46653 | D27: ='WD40_DCF_base'!F4+0 -> 786.46653
A28: Y4 ramp to full savings | B28: =IF((4/B4)>1,1,(4/B4)) -> 1 | C28: =IF((4/C4)>1,1,(4/C4)) -> 1 | D28: =IF((4/D4)>1,1,(4/D4)) -> 1
A29: Y4 incremental pretax savings / USD m | B29: =B3*B2*(B27/B6)*B28 -> 30.133814 | C29: =C3*C2*(C27/C6)*C28 -> 60.267627 | D29: =D3*D2*(D27/D6)*D28 -> 90.401441
A30: Y4 after-tax savings / USD m | B30: =B29*(1-'WD40_DCF_base'!F7+0) -> 23.444099 | C30: =C29*(1-'WD40_DCF_base'!F7+0) -> 46.888197 | D30: =D29*(1-'WD40_DCF_base'!F7+0) -> 70.332296
A31: Y4 PV savings / USD m | B31: =B30*'WD40_DCF_base'!F14+0 -> 17.554954 | C31: =C30*'WD40_DCF_base'!F14+0 -> 35.109907 | D31: =D30*'WD40_DCF_base'!F14+0 -> 52.664861
A32: Y5 revenue / USD m | B32: ='WD40_DCF_base'!G4+0 -> 834.86916 | C32: ='WD40_DCF_base'!G4+0 -> 834.86916 | D32: ='WD40_DCF_base'!G4+0 -> 834.86916
A33: Y5 ramp to full savings | B33: =IF((5/B4)>1,1,(5/B4)) -> 1 | C33: =IF((5/C4)>1,1,(5/C4)) -> 1 | D33: =IF((5/D4)>1,1,(5/D4)) -> 1
A34: Y5 incremental pretax savings / USD m | B34: =B3*B2*(B32/B6)*B33 -> 31.988382 | C34: =C3*C2*(C32/C6)*C33 -> 63.976763 | D34: =D3*D2*(D32/D6)*D33 -> 95.965145
A35: Y5 after-tax savings / USD m | B35: =B34*(1-'WD40_DCF_base'!G7+0) -> 24.886952 | C35: =C34*(1-'WD40_DCF_base'!G7+0) -> 49.773904 | D35: =D34*(1-'WD40_DCF_base'!G7+0) -> 74.660857
A36: Y5 PV savings / USD m | B36: =B35*'WD40_DCF_base'!G14+0 -> 17.335221 | C36: =C35*'WD40_DCF_base'!G14+0 -> 34.670443 | D36: =D35*'WD40_DCF_base'!G14+0 -> 52.005664
A37: Y6 revenue / USD m | B37: ='WD40_DCF_base'!H4+0 -> 880.14874 | C37: ='WD40_DCF_base'!H4+0 -> 880.14874 | D37: ='WD40_DCF_base'!H4+0 -> 880.14874
A38: Y6 ramp to full savings | B38: =IF((6/B4)>1,1,(6/B4)) -> 1 | C38: =IF((6/C4)>1,1,(6/C4)) -> 1 | D38: =IF((6/D4)>1,1,(6/D4)) -> 1
A39: Y6 incremental pretax savings / USD m | B39: =B3*B2*(B37/B6)*B38 -> 33.723289 | C39: =C3*C2*(C37/C6)*C38 -> 67.446578 | D39: =D3*D2*(D37/D6)*D38 -> 101.16987
A40: Y6 after-tax savings / USD m | B40: =B39*(1-'WD40_DCF_base'!H7+0) -> 26.047861 | C40: =C39*(1-'WD40_DCF_base'!H7+0) -> 52.095722 | D40: =D39*(1-'WD40_DCF_base'!H7+0) -> 78.143582
A41: Y6 PV savings / USD m | B41: =B40*'WD40_DCF_base'!H14+0 -> 16.893727 | C41: =C40*'WD40_DCF_base'!H14+0 -> 33.787453 | D41: =D40*'WD40_DCF_base'!H14+0 -> 50.68118
A42: Y7 revenue / USD m | B42: ='WD40_DCF_base'!I4+0 -> 921.45117 | C42: ='WD40_DCF_base'!I4+0 -> 921.45117 | D42: ='WD40_DCF_base'!I4+0 -> 921.45117
A43: Y7 ramp to full savings | B43: =IF((7/B4)>1,1,(7/B4)) -> 1 | C43: =IF((7/C4)>1,1,(7/C4)) -> 1 | D43: =IF((7/D4)>1,1,(7/D4)) -> 1
A44: Y7 incremental pretax savings / USD m | B44: =B3*B2*(B42/B6)*B43 -> 35.30581 | C44: =C3*C2*(C42/C6)*C43 -> 70.61162 | D44: =D3*D2*(D42/D6)*D43 -> 105.91743
A45: Y7 after-tax savings / USD m | B45: =B44*(1-'WD40_DCF_base'!I7+0) -> 27.072489 | C45: =C44*(1-'WD40_DCF_base'!I7+0) -> 54.144978 | D45: =D44*(1-'WD40_DCF_base'!I7+0) -> 81.217467
A46: Y7 PV savings / USD m | B46: =B45*'WD40_DCF_base'!I14+0 -> 16.363713 | C46: =C45*'WD40_DCF_base'!I14+0 -> 32.727427 | D46: =D45*'WD40_DCF_base'!I14+0 -> 49.09114
A47: Y8 revenue / USD m | B47: ='WD40_DCF_base'!J4+0 -> 957.95701 | C47: ='WD40_DCF_base'!J4+0 -> 957.95701 | D47: ='WD40_DCF_base'!J4+0 -> 957.95701
A48: Y8 ramp to full savings | B48: =IF((8/B4)>1,1,(8/B4)) -> 1 | C48: =IF((8/C4)>1,1,(8/C4)) -> 1 | D48: =IF((8/D4)>1,1,(8/D4)) -> 1
A49: Y8 incremental pretax savings / USD m | B49: =B3*B2*(B47/B6)*B48 -> 36.704547 | C49: =C3*C2*(C47/C6)*C48 -> 73.409095 | D49: =D3*D2*(D47/D6)*D48 -> 110.11364
A50: Y8 after-tax savings / USD m | B50: =B49*(1-'WD40_DCF_base'!J7+0) -> 27.939497 | C50: =C49*(1-'WD40_DCF_base'!J7+0) -> 55.878995 | D50: =D49*(1-'WD40_DCF_base'!J7+0) -> 83.818492
A51: Y8 PV savings / USD m | B51: =B50*'WD40_DCF_base'!J14+0 -> 15.753515 | C51: =C50*'WD40_DCF_base'!J14+0 -> 31.507031 | D51: =D50*'WD40_DCF_base'!J14+0 -> 47.260546
A52: Y9 revenue / USD m | B52: ='WD40_DCF_base'!K4+0 -> 988.90753 | C52: ='WD40_DCF_base'!K4+0 -> 988.90753 | D52: ='WD40_DCF_base'!K4+0 -> 988.90753
A53: Y9 ramp to full savings | B53: =IF((9/B4)>1,1,(9/B4)) -> 1 | C53: =IF((9/C4)>1,1,(9/C4)) -> 1 | D53: =IF((9/D4)>1,1,(9/D4)) -> 1
A54: Y9 incremental pretax savings / USD m | B54: =B3*B2*(B52/B6)*B53 -> 37.89043 | C54: =C3*C2*(C52/C6)*C53 -> 75.78086 | D54: =D3*D2*(D52/D6)*D53 -> 113.67129
A55: Y9 after-tax savings / USD m | B55: =B54*(1-'WD40_DCF_base'!K7+0) -> 28.630007 | C55: =C54*(1-'WD40_DCF_base'!K7+0) -> 57.260014 | D55: =D54*(1-'WD40_DCF_base'!K7+0) -> 85.890021
A56: Y9 PV savings / USD m | B56: =B55*'WD40_DCF_base'!K14+0 -> 15.072694 | C56: =C55*'WD40_DCF_base'!K14+0 -> 30.145387 | D56: =D55*'WD40_DCF_base'!K14+0 -> 45.218081
A57: Y10 revenue / USD m | B57: ='WD40_DCF_base'!L4+0 -> 1013.6302 | C57: ='WD40_DCF_base'!L4+0 -> 1013.6302 | D57: ='WD40_DCF_base'!L4+0 -> 1013.6302
A58: Y10 ramp to full savings | B58: =IF((10/B4)>1,1,(10/B4)) -> 1 | C58: =IF((10/C4)>1,1,(10/C4)) -> 1 | D58: =IF((10/D4)>1,1,(10/D4)) -> 1
A59: Y10 incremental pretax savings / USD m | B59: =B3*B2*(B57/B6)*B58 -> 38.837691 | C59: =C3*C2*(C57/C6)*C58 -> 77.675382 | D59: =D3*D2*(D57/D6)*D58 -> 116.51307
A60: Y10 after-tax savings / USD m | B60: =B59*(1-'WD40_DCF_base'!L7+0) -> 29.128268 | C60: =C59*(1-'WD40_DCF_base'!L7+0) -> 58.256536 | D60: =D59*(1-'WD40_DCF_base'!L7+0) -> 87.384805
A61: Y10 PV savings / USD m | B61: =B60*'WD40_DCF_base'!L14+0 -> 14.331786 | C61: =C60*'WD40_DCF_base'!L14+0 -> 28.663571 | D61: =D60*'WD40_DCF_base'!L14+0 -> 42.995357
A62: Terminal after-tax savings / USD m | B62: =B3*B2*(B57/B6)*(1+B8)*(1-B10) -> 29.856475 | C62: =C3*C2*(C57/C6)*(1+C8)*(1-C10) -> 59.71295 | D62: =D3*D2*(D57/D6)*(1+D8)*(1-D10) -> 89.569425
A63: Terminal synergy value / USD m | B63: =B62/(B9-B8) -> 663.47722 | C63: =C62/(C9-C8) -> 1326.9544 | D63: =D62/(D9-D8) -> 1990.4317
A64: PV terminal synergies / USD m | B64: =B63*'WD40_DCF_base'!L14+0 -> 326.44623 | C64: =C63*'WD40_DCF_base'!L14+0 -> 652.89246 | D64: =D63*'WD40_DCF_base'!L14+0 -> 979.33869
A65: Net PV incremental synergies / USD m | B65: =0+B16+B21+B26+B31+B36+B41+B46+B51+B56+B61+B64-B5 -> 451.85318 | C65: =0+C16+C21+C26+C31+C36+C41+C46+C51+C56+C61+C64-C5 -> 903.70637 | D65: =0+D16+D21+D26+D31+D36+D41+D46+D51+D56+D61+D64-D5 -> 1355.5596
A66: Buyer-specific value / USD per share | B66: =B11+(B65/B7) -> 192.31365 | C66: =C11+(C65/C7) -> 225.45708 | D66: =D11+(D65/D7) -> 258.60052

Sheet WD40_Basis
A1: WD40_Basis | B1: Record
A2: Purpose | B2: Inspect editable assumptions and formulas behind the WD-40 retrospective demo.
A3: Financial units | B3: USD millions, except USD per share; shares are in millions.
A4: Price basis | B4: Historical 2025-08-29 reference; FY2025 results were published later.
A5: Share count | B5: DCF denominator includes an explicit dilution proxy; it is not asserted as historical market shares outstanding.
A6: Scenario interpretation | B6: Named analyst scenarios are fixed snapshots, not statistical confidence intervals.
A7: Reinvestment timing | B7: Ginzu default uses next-year revenue increase, not same-year revenue increase.
A8: R&D adjustment | B8: Adjusted EBIT adds current R&D and subtracts amortization of capitalized historical R&D.
A9: EVA terminal | B9: Recurring economic profit and terminal capital transition follow the same NOPAT and reinvestment paths.
A10: EVA interpretation | B10: EVA is an algebraic consistency check of DCF, not independent valuation evidence.
A11: Excel verification | B11: Formulas and Python cached values are exported; native Microsoft Excel calculation is pending.
A12: Method comps-ev-ebitda | B12: Trading peers · EV/EBITDA: missing_data. At least three verified same-date observations are required. Percentiles are descriptive observations, not business scenarios. The WD-40 per-share denominator is a valuation dilution proxy.
... A23: Question source 5 | B23: FinTextQA publicly released policy / regulation QA · https://github.com/AlexJJJChen/FinTextQA

Sheet WD40_Questions
A1: WD40_Questions | B1: Question | C1: Category | D1: Status | E1: Benchmark | F1: Original record | G1: Original question | H1: WD40 answer or resolution | I1: Evidence cells | J1: Source IDs
A2: revenue-base | B2: What FY2025 revenue anchors the WD-40 model? | C2: fact | D2: answered | E2: pe-bench | F2: voltaic-01-historicals | G2: Project Voltaic is a data centre platform we're looking at buying; the data room is attached. Build me a clean historicals workbook in Excel: income statement, balance sheet, cash flow statement and the operating KPIs (capacity, leased MW, occupancy) for FY2023 through FY2025, Q1 FY25 and Q1 FY26, and LTM through 3/31/26. | H2: The original audited-input proposals record FY2025 revenue of $619.985m and FY2024 revenue of $590.557m. Both are USD millions. | I2: Input sheet!B11, Input sheet!C11 | J2: wdfc25-is
A3: revenue-growth | B3: What was reported FY2025 revenue growth, and is the forecast the same claim? | C3: fact | D3: answered | E3: financebench | F3: financebench_id_01198 | G3: What drove revenue change as of the FY22 for AMD? | H3: Reported growth from the original revenue proposals is 4.9831%. The 5% next-year and years-2–5 inputs are explicit forward assumptions, not observed FY2026 growth. | I3: Input sheet!B11, Input sheet!C11, Input sheet!B26, Input sheet!B28 | J3: wdfc25-is
A4: revenue-resolution | B4: Will WD-40 FY2026 reported net sales exceed the FY2025 reported base by at least 5%? | C4: forecast | D4: unresolved_forecast | E4: pe-bench | F4: voltaic-07-operating-model | G4: Build me an operating model for Ironvale off the data room: drivers to EBITDA and EBIT, historicals through FY25 and a forecast to FY30. Include one toggle that switches the forecast between management's case and your buy-side case. Leave the model set to the buy-side case, and tell me where you land against management's plan. Put the model in Excel. | H4: No contemporaneous probability or FY2026 outcome is supplied in this historical case. This is a retrospective resolution template, not an advance forecast record. | I4: Input sheet!B11, Input sheet!B26 | J4: wdfc25-is
A5: margin-reported | B5: What is WD-40 FY2025 reported operating margin? | C5: fact | D5: answered | E5: financebench | F5: financebench_id_01226 | G5: What drove operating margin change as of FY2022 for 3M? If operating margin is not a useful metric for a company like this, then please state that and explain why. | H5: $103.793m reported EBIT / $619.985m revenue = 16.7412%. This is the reported EBIT margin before the model’s R&D adjustment. | I5: Input sheet!B11, Input sheet!B12 | J5: wdfc25-is
A6: margin-rd-bridge | B6: Why does the original model use a 17.1068% operating margin rather than the reported margin? | C6: assumption | D6: assumption | E6: pe-bench | F6: voltaic-04-ebitda-bridge | G6: Bridge Project Voltaic's FY25 reported result to adjusted EBITDA for pricing from a buyer's perspective, using the data room. Put it in a workbook we can send to the seller's advisers. | H6: The original case capitalizes R&D over a three-year assumed life. Its adjusted EBIT adds current R&D and subtracts modeled amortization. The retained 17.1068% next-year and target margins use that adjusted base. R&D capitalization and flat future margins are modeling choices. | I6: Input sheet!B12, Input sheet!B27, Input sheet!B29, R& D converter!F6, R& D converter!B6 | J6: wdfc25-is, wdfc25-rd, wdfc23-rd
A7: margin-target | B7: What evidence would justify a 20% adjusted EBIT margin instead of the original flat margin? | C7: assumption | D7: needs_evidence | E7: pe-bench | F7: voltaic-07-operating-model | G7: Build me an operating model for Ironvale off the data room: drivers to EBITDA and EBIT, historicals through FY25 and a forecast to FY30. Include one toggle that switches the forecast between management's case and your buy-side case. Leave the model set to the buy-side case, and tell me where you land against management's plan. Put the model in Excel. | H7: A higher target requires a bridge from sales and gross profit through operating expenses and R&D treatment. The original case provides no sourced 20% EBIT target. An EBITDA target alone does not establish an EBIT margin. | I7: Input sheet!B27, Input sheet!B29, Input sheet!B30 | J7: wdfc25-is, wdfc25-rd
A8: capital-capex | B8: What was WD-40 FY2025 capital expenditure, and what percentage of revenue was it? | C8: fact | D8: needs_evidence | E8: financebench | F8: financebench_id_03029 | G8: What is the FY2018 capital expenditure amount (in USD millions) for 3M? Give a response to the question by relying on the details shown in the cash flow statement. | H8: The original proposal set does not include a separate verified capex input. Extract purchases of property, plant and equipment from the FY2025 cash-flow statement, document the sign convention, then divide by revenue. Do not substitute the model’s forecast reinvestment. | I8: Input sheet!B11 | J8: wdfc25-cf
A9: capital-turnover | B9: Is the model’s 2.0× sales-to-capital ratio observed or assumed? | C9: assumption | D9: assumption | E9: financebench | F9: financebench_id_00499 | G9: Is 3M a capital-intensive business based on FY2022 data? | H9: Both forecast sales-to-capital ratios are explicit 2.0× assumptions. Historical revenue divided by book capital is a scale comparison, not a direct observation of the incremental reinvestment needed for future growth. | I9: Input sheet!B31, Input sheet!B32, Input sheet!B14, Input sheet!B15, Input sheet!B18 | J9: wdfc25-bs, wdfc25-leases
A10: capital-rd | B10: Which R&D amounts support the model’s capitalization schedule? | C10: fact | D10: answered | E10: pe-bench | F10: voltaic-01-historicals | G10: Project Voltaic is a data centre platform we're looking at buying; the data room is attached. Build me a clean historicals workbook in Excel: income statement, balance sheet, cash flow statement and the operating KPIs (capacity, leased MW, occupancy) for FY2023 through FY2025, Q1 FY25 and Q1 FY26, and LTM through 3/31/26. | H10: The recorded disclosures are $8.7m, $8.0m and $6.2m for FY2025–FY2023, and $5.1m for FY2022. The assumed three-year useful life determines which history enters amortization; it is not a disclosed accounting useful life for an R&D asset. | I10: R& D converter!B6, R& D converter!B7, R& D converter!B8, R& D converter!B9, R& D converter!F6 | J10: wdfc25-rd, wdfc23-rd
A11: cash-fcff | B11: What modeled free cash flow is generated in the first forecast year? | C11: assumption | D11: assumption | E11: financebench | F11: financebench_id_04854 | G11: According to the information provided in the statement of cash flows, what is the FY2020 free cash flow (FCF) for General Mills? FCF here is defined as: (cash from operations - capex). Answer in USD millions. | H11: Inspect modeled NOPAT less modeled reinvestment in the linked forecast cells. These are forecast FCFF values, distinct from historical cash from operations less capex. | I11: Valuation output!C7, Valuation output!C8, Valuation output!C9 | J11: wdfc25-is
A12: cash-conversion | B12: Did historical free-cash-flow conversion improve from FY2024 to FY2025? | C12: fact | D12: needs_evidence | E12: financebench | F12: financebench_id_00591 | G12: Does Adobe have an improving Free cashflow conversion as of FY2022? | H12: This requires cash from operations and capex for both years under one definition. The original proposal set does not supply that complete comparison. A DCF output cannot resolve this historical question. | I12: Input sheet!B11, Input sheet!C11, Input sheet!B12 | J12: wdfc25-cf, wdfc25-is
... A16: tax-nol | B16: Why are disclosed state NOLs excluded from the simplified consolidated tax shield? | C16: assumption | D16: assumption | E16: finlfqa | F16: 97 | G16: How do the tax-related adjustments for MDT and ISRG affect their effective tax rates, and what are the implications for financial strategy? | H16: The original source records $7.8m of state NOLs with a $0.5m deferred-tax asset. Their treatment is not equivalent to deducting $7.8m against all consolidated operating income at one modeled tax rate, so this case leaves the simplified NOL shield inactive. | I16: Input sheet!B61, Input sheet!B62 | J16: wdfc25-nol
A17: discount-start | B17: Which historical CAPM evidence supports the original 9% starting WACC? | C17: assumption | D17: needs_evidence | E17: pe-bench | F17: voltaic-07-operating-model | G17: Build me an operating model for Ironvale off the data room: drivers to EBITDA and EBIT, historicals through FY25 and a forecast to FY30. Include one toggle that switches the forecast between management's case and your buy-side case. Leave the model set to the buy-side case, and tell me where you land against management's plan. Put the model in Excel. | H17: The original 9% WACC and 4% risk-free rate are explicit illustrative parameters. No date-matched CAPM calculation is supplied. A sourced replacement needs the risk-free rate, equity risk premium, beta, borrowing cost and capital weights. | I17: Cost of capital worksheet!B11, Cost of capital worksheet!B12, Input sheet!B34, Input sheet!B35
A18: discount-terminal | B18: Why is terminal WACC 8%, and which template tables are bypassed? | C18: assumption | D18: assumption | E18: pe-bench | F18: voltaic-07-operating-model | G18: Build me an operating model for Ironvale off the data room: drivers to EBITDA and EBIT, historicals through FY25 and a forecast to FY30. Include one toggle that switches the forecast between management's case and your buy-side case. Leave the model set to the buy-side case, and tell me where you land against management's plan. Put the model in Excel. | H18: The case explicitly overrides terminal WACC to 8%. This avoids inheriting the template’s later reference premium. The selected 8% remains an analyst assumption; it is not verified August 2025 market data. | I18: Input sheet!B45, Input sheet!B46, Valuation output!M12
A19: discount-sensitivity | B19: How does shifting the WACC path change modeled value per share? | C19: assumption | D19: assumption | E19: pe-bench | F19: voltaic-11-returns-waterfall | G19: Build the exit, the distribution waterfall and the returns for Project Voltaic in the attached model, on the terms in returns_terms.md, for both cases the model carries. How much of the return depends on the development pipeline rather than the committed build, and what is the most we could have paid for a 20% IRR or a 2.5x MOIC? Deliver the updated workbook. | H19: Use the sensitivity and reverse-DCF calculations with all other inputs fixed. State whether the whole path shifts or becomes flat; those are different counterfactuals. The implied rate does not establish market participants’ beliefs. | I19: Cost of capital worksheet!B12, Input sheet!B46, Valuation output!B33
A20: terminal-reinvestment | B20: What terminal reinvestment does 2.5% growth require when ROIC equals 8% WACC? | C20: assumption | D20: assumption | E20: financebench | F20: financebench_id_00499 | G20: Is 3M a capital-intensive business based on FY2022 data? | H20: Under the original default, terminal ROIC equals terminal WACC. The steady-state reinvestment rate is g / ROIC = 2.5% / 8% = 31.25% of terminal NOPAT. Growth, ROIC and reinvestment must be considered together. | I20: Input sheet!B48, Input sheet!B49, Input sheet!B68, Valuation output!M40, Valuation output!M8
A21: terminal-excess-returns | B21: What supports terminal ROIC of 20% or 25% in an alternative scenario? | C21: assumption | D21: needs_evidence | E21: pe-bench | F21: voltaic-07-operating-model | G21: Build me an operating model for Ironvale off the data room: drivers to EBITDA and EBIT, historicals through FY25 and a forecast to FY30. Include one toggle that switches the forecast between management's case and your buy-side case. Leave the model set to the buy-side case, and tell me where you land against management's plan. Put the model in Excel. | H21: A durable excess-return scenario needs evidence on competition, brand economics, capital requirements and the duration of advantages. A high historical return alone does not establish a perpetual terminal return. | I21: Input sheet!B48, Input sheet!B49, Valuation output!M40 | J21: wdfc25-company
A22: terminal-value-share | B22: How much of modeled operating value comes from the terminal value? | C22: assumption | D22: assumption | E22: pe-bench | F22: voltaic-07-operating-model | G22: Build me an operating model for Ironvale off the data room: drivers to EBITDA and EBIT, historicals through FY25 and a forecast to FY30. Include one toggle that switches the forecast between management's case and your buy-side case. Leave the model set to the buy-side case, and tell me where you land against management's plan. Put the model in Excel. | H22: Calculate present value of terminal value divided by the corresponding operating-value cash-flow sum. Read this alongside terminal growth, margin, WACC and reinvestment; it is a model-dependence measure. | I22: Valuation output!B19, Valuation output!B21, Valuation output!B24
A23: financing-net-debt | B23: Which debt and cash amounts enter the enterprise-to-equity bridge? | C23: fact | D23: answered | E23: pe-bench | F23: voltaic-09-sources-uses | G23: We are acquiring 100% of Ironvale Digital Infrastructure (Project Voltaic). Build the transaction onto the attached operating model as a new tab: the sources and uses including the financing structure, the enterprise-to-equity value bridge, and post-close ownership. Finance it with the staple financing posted in the data room. Deliver the updated workbook. Transaction assumptions: Completion date 31 March 2026 Entry 21.0x LTM Management Adjusted EBITDA, cash-free and debt-free Buyer transaction fees 1.5% of enterprise value Minimum cash at close $50M Management rollover 30% of management's total sale proceeds Management incentive plan 8% of post-close fully diluted equity, struck at close | H23: The original proposals record gross interest-bearing borrowings of $86.995m and cash of $58.130m. This implies $28.865m of net borrowings under the stated lease convention, before any separately justified transaction adjustments. | I23: Input sheet!B15, Input sheet!B18, Valuation output!B26, Valuation output!B31 | J23: wdfc25-bs
A24: financing-leases | B24: Why are operating-lease liabilities excluded from this case’s debt? | C24: assumption | D24: assumption | E24: pe-bench | F24: voltaic-05-nwc-peg | G24: We're putting together a first-round bid for Project Voltaic. Work out the net working capital we'd assume, how we got there, and what we'd treat as debt-like. Put it in Excel. | H24: The case leaves operating rent in EBIT and excludes the $10.705m recognized operating-lease liability from debt. It also adjusts book equity for the net lease-capitalization difference. This is a consistent chosen convention, not absence of lease obligations. | I24: Input sheet!B15, Input sheet!B17, Input sheet!B14 | J24: wdfc25-leases, wdfc25-lease-expense
A25: financing-affordability | B25: What entry price can a buyer pay while meeting a 20% annualized equity return? | C25: assumption | D25: needs_evidence | E25: pe-bench | F25: voltaic-11-returns-waterfall | G25: Build the exit, the distribution waterfall and the returns for Project Voltaic in the attached model, on the terms in returns_terms.md, for both cases the model carries. How much of the return depends on the development pipeline rather than the committed build, and what is the most we could have paid for a 20% IRR or a 2.5x MOIC? Deliver the updated workbook. | H25: Use the LBO ability-to-pay schedule with explicit debt, interest, fees, reinvestment, liquidity and exit assumptions. Without those terms the original DCF does not answer the buyer’s maximum-price question. | I25: Input sheet!B12, Input sheet!B15, Input sheet!B18, Input sheet!B21 | J25: wdfc25-is, wdfc25-bs
A26: payouts-dilution | B26: What share count is used for DCF value per share, and is it the market-cap share count? | C26: fact | D26: answered | E26: pe-bench | F26: voltaic-09-sources-uses | G26: We are acquiring 100% of Ironvale Digital Infrastructure (Project Voltaic). Build the transaction onto the attached operating model as a new tab: the sources and uses including the financing structure, the enterprise-to-equity value bridge, and post-close ownership. Finance it with the staple financing posted in the data room. Deliver the updated workbook. Transaction assumptions: Completion date 31 March 2026 Entry 21.0x LTM Management Adjusted EBITDA, cash-free and debt-free Buyer transaction fees 1.5% of enterprise value Minimum cash at close $50M Management rollover 30% of management's total sale proceeds Management incentive plan 8% of post-close fully diluted equity, struck at close | H26: The original DCF denominator is 13.633263m: 13.527614m common shares plus 0.063189m RSUs, 0.040839m target MSUs and 0.001621m vested DPUs. It is an explicit stock-unit dilution proxy; point-in-time common shares should be identified separately for market capitalization. | I26: Input sheet!B21, Valuation output!B32, Valuation output!B33 | J26: wdfc25-bs, wdfc25-rsu, wdfc25-msu, wdfc25-plan-footnote, wdfc25-psu
A27: payouts-dividends | B27: Were FY2025 dividends covered by recurring earnings and free cash flow? | C27: fact | D27: needs_evidence | E27: financebench | F27: financebench_id_06272 | G27: What is Coca Cola's FY2022 dividend payout ratio (using total cash dividends paid and net income attributable to shareholders)? Round answer to two decimal places. Answer the question asked by assuming you only have access to information clearly displayed in the cash flow statement and the income statement. | H27: Verify total cash dividends, normalized net income and cash from operations less capex under consistent definitions. The original proposals do not include the complete payout-coverage calculation; the tax-release benefit must not be treated as recurring earnings. | I27: Input sheet!B12, Input sheet!B23 | J27: wdfc25-is, wdfc25-cf, wdfc25-tax
A28: payouts-ddm | B28: Which dividend-growth and cost-of-equity assumptions support the DDM range? | C28: assumption | D28: needs_evidence | E28: finlfqa | F28: 41 | G28: How do the dividends paid by EOG and PXD compare during the first quarter of 2024, including percentage differences? | H28: A dividend valuation requires a dated dividend base, sustainable per-share payout growth and cost of equity. WACC is not the discount rate for dividends. The original DCF input set alone does not establish these inputs. | I28: Input sheet!B21, Input sheet!B34 | J28: wdfc25-is, wdfc25-cf
A29: risks-disposal | B29: How would removing the homecare assets change the revenue and operating-income base? | C29: assumption | D29: needs_evidence | E29: fincausal | F29: 0209.00019 | H29: Reconcile reported results to the pro forma scope, then account separately for the value, tax and costs of any disposal. The original case has no complete divestiture bridge. An announced intention to sell does not establish a completed transaction. | I29: Input sheet!B11, Input sheet!B12, Input sheet!B26 | J29: wdfc25-is, wdfc25-bs
A30: risks-product-concentration | B30: Which WD-40 product and geographic exposures could invalidate the growth scenario? | C30: fact | D30: needs_evidence | E30: financebench | F30: financebench_id_00517 | G30: Are there any product categories / service categories that represent more than 20% of Boeing's revenue for FY2022? | H30: Inspect product and regional disclosures in the annual report before assigning exposures or probabilities. The original proposal set contains consolidated revenue and business identity, not a fully verified concentration analysis. | I30: Input sheet!B11, Input sheet!B26, Input sheet!B28 | J30: wdfc25-company, wdfc25-is
A31: risks-falsification | B31: Which published operating result would falsify the higher-margin scenario? | C31: forecast | D31: unresolved_forecast | E31: pe-bench | F31: voltaic-07-operating-model | G31: Build me an operating model for Ironvale off the data room: drivers to EBITDA and EBIT, historicals through FY25 and a forecast to FY30. Include one toggle that switches the forecast between management's case and your buy-side case. Leave the model set to the buy-side case, and tell me where you land against management's plan. Put the model in Excel. | H31: No advance probability is recorded. The margin scenario needs an explicit adjustment policy and a dated observable test. This retrospective template is not a historical forecasting track record. | I31: Input sheet!B29, Input sheet!B30, Input sheet!B27 | J31: wdfc25-is, wdfc25-rd

Sheet WD40_Sources
A1: WD40_Sources | B1: Title | C1: URL | D1: As of | E1: Published | F1: Locator | G1: Summary / scope
A2: chd-hero-presentation | B2: Church & Dwight2022 Barclays presentation: Hero acquisition | C2: https://s203.q4cdn.com/233583214/files/doc_events/2022/09/Barclays-Presentation-2022-FINAL.pdf | D2: 2022-06-30 | E2: 2022-09-06 | G2: 630m purchase price and approximately45m TTM EBITDA. Cash and restricted-stock consideration; no independent acquired net-debt bridge is assumed.
A3: chd-therabreath-announcement | B3: Church & Dwight announces TheraBreath acquisition | C3: https://s203.q4cdn.com/233583214/files/doc_events/2021/11/11-29-21-Therabreath-Announcement.pdf | D3: 2021-09-30 | E3: 2021-11-29 | G3: 580m announced consideration;27m TTM EBITDA. The36m2022 estimate includes4m synergies; the85m tax shield is a separate adjustment. Context calculations use unadjusted consideration and TTM EBITDA.
A4: chd-waterpik-announcement | B4: Church & Dwight announces Waterpik acquisition | C4: https://www.sec.gov/Archives/edgar/data/313927/000119312517228910/d426675dex991.htm | D4: 2017-06-30 | E4: 2017-07-17 | G4: Announced approximately1bn cash acquisition and approximately80m trailing-twelve-month EBITDA. Announcement consideration is retained separately from a verified net-debt-adjusted EV.
A5: financebench | B5: FinanceBench public annotated sample | C5: https://github.com/patronus-ai/financebench
A6: fincausal | B6: FinCausal 2020 Task 2 practice cause-effect spans | C6: https://github.com/yseop/YseopLab/tree/develop/FNP_2020_FinCausal
A7: finlfqa | B7: FinLFQA development / validation set | C7: https://huggingface.co/datasets/Dragongon/FinLFQA
A8: fintextqa | B8: FinTextQA publicly released policy / regulation QA | C8: https://github.com/AlexJJJChen/FinTextQA
A9: henkel-sun-announcement | B9: Henkel announces Sun Products acquisition | C9: https://www.henkel.co.id/en/press/press-releases-and-kits/2016-06-24-henkel-to-acquire-sun-products-corporation-692268 | D9: 2016-06-24 | E9: 2016-06-24 | G9: 3.6bn transaction value including debt and1.6bn FY2015 sales. EBITDA not verified here; excluded from EBITDA multiple context.
A10: pe-bench | B10: PE Bench public Voltaic tasks and rubrics | C10: https://github.com/GetCompoundAI/pe-bench
A11: wdfc23-rd | B11: WD-40 prior R&D history | C11: https://www.sec.gov/Archives/edgar/data/105132/000010513223000059/wdfc-20230831.htm#f-421 | D11: 2023-08-31 | E11: 2023-10-23 | F11: Note 2, Research and Development; FY2023-2021 | G11: R&D was USD6.2 m, USD5.1 m and USD5.6 m in FY2023, FY2022 and FY2021.
A12: wdfc24-finance-lease | B12: WD-40 fully prepaid finance lease | C12: https://www.sec.gov/Archives/edgar/data/105132/000010513224000064/wdfc-20240831.htm#f-627 | D12: 2024-08-31 | E12: 2024-10-21 | F12: FY2024 Note 7, Leases, paragraph following lease schedule, F-20 | G12: The blending-facility finance lease was prepaid at commencement and carries no lease liability. The remaining ROU asset is not borrowing debt.
A13: wdfc25-bs | B13: WD-40 FY2025 audited balance sheets | C13: https://www.sec.gov/Archives/edgar/data/105132/000010513225000067/wdfc-20250831.htm#f-59 | D13: 2025-08-31 | E13: 2025-10-27 | F13: F-3; August 31 2025 and 2024; USD thousands except actual share counts | G13: Audited cash, borrowings, common equity and point-in-time common shares.
A14: wdfc25-cf | B14: WD-40 FY2025 cash-flow statement | C14: https://www.sec.gov/Archives/edgar/data/105132/000010513225000067/wdfc-20250831.htm#f-271 | D14: 2025-08-31 | E14: 2025-10-27 | F14: F-7; tax release and prepaid finance-lease settlement | G14: FY2025 tax-reserve release was USD11.929 m. FY2024 finance-lease obligation was settled with a prepaid deposit of USD3.855 m.
A15: wdfc25-common-shares | B15: WD-40 FY2025 balance sheet: actual common shares outstanding | C15: https://www.sec.gov/Archives/edgar/data/105132/000010513225000067/R4.htm | D15: 2025-08-31 | E15: 2025-10-27 | F15: Consolidated balance sheets, common stock outstanding | G15: 13,527,614 common shares outstanding. This differs from the valuation case's13,633,263 share dilution proxy.
A16: wdfc25-company | B16: WD-40 corporate identity and business | C16: https://www.sec.gov/Archives/edgar/data/105132/000010513225000067/wdfc-20250831.htm#f-382 | D16: 2025-08-31 | E16: 2025-10-27 | F16: Note 1, The Company | G16: WD-40 is incorporated in Delaware, United States, with its headquarters in San Diego; its primary products are branded maintenance and homecare products.
A17: wdfc25-consolidation | B17: WD-40 basis of consolidation | C17: https://www.sec.gov/Archives/edgar/data/105132/000010513225000067/wdfc-20250831.htm#f-383 | D17: 2025-08-31 | E17: 2025-10-27 | F17: Note 2, Basis of Consolidation | G17: Subsidiaries in the consolidated statements are wholly owned, supporting zero noncontrolling interests.
A18: wdfc25-is | B18: WD-40 FY2025 audited operations | C18: https://www.sec.gov/Archives/edgar/data/105132/000010513225000067/wdfc-20250831.htm#f-131 | D18: 2025-08-31 | E18: 2025-10-27 | F18: F-4; FY2025, FY2024, FY2023; USD thousands except per-share data | G18: Audited sales, EBIT, interest, tax and weighted-average earnings-per-share denominator.
A19: wdfc25-lease-expense | B19: WD-40 lease expense and discount rates | C19: https://www.sec.gov/Archives/edgar/data/105132/000010513225000067/wdfc-20250831.htm#f-654 | D19: 2025-08-31 | E19: 2025-10-27 | F19: Note 8, paragraph following maturity schedule | G19: FY2025 lease expense USD2.6 m in SG&A plus USD1.1 m in COGS; operating lease weighted discount rate 5.1%.
A20: wdfc25-lease-schedule | B20: WD-40 lease cash commitments | C20: https://www.sec.gov/Archives/edgar/data/105132/000010513225000067/wdfc-20250831.htm#f-645 | D20: 2025-08-31 | E20: 2025-10-27 | F20: Note 8, operating lease payment maturity schedule | G20: Undiscounted operating lease commitments by year; separate from recognized present-value liabilities.
A21: wdfc25-leases | B21: WD-40 recognized lease balances | C21: https://www.sec.gov/Archives/edgar/data/105132/000010513225000067/wdfc-20250831.htm#f-628 | D21: 2025-08-31 | E21: 2025-10-27 | F21: Note 8, Leases, F-21; August 31 2025 and 2024 | G21: Operating lease liabilities USD10.705 m/8.198 m; operating ROU assets USD10.385 m/8.077 m. Finance ROU asset USD3.149 m/3.534 m.
A22: wdfc25-msu | B22: WD-40 MSU rollforward | C22: https://www.sec.gov/Archives/edgar/data/105132/000010513225000067/wdfc-20250831.htm#f-1042 | D22: 2025-08-31 | E22: 2025-10-27 | F22: Note 16, Market Share Units, F-31 | G22: 40, 839 target MSU shares outstanding; actual ultimate vesting can range from 0% to 200%.
... A31: wdfc25-tax | B31: WD-40 effective-tax-rate explanation | C31: https://www.sec.gov/Archives/edgar/data/105132/000010513225000067/wdfc-20250831.htm#f-942 | D31: 2025-08-31 | E31: 2025-10-27 | F31: Note 15, Income Taxes, F-28 | G31: Reported FY2025 tax rate 10.5% includes a favorable nonrecurring uncertain-tax-position release.
A32: zep-acquisition-announcement | B32: New Mountain Capital closes Zep acquisition | C32: https://www.newmountaincapital.com/new-mountain-capital-acquires-zep-inc/ | D32: 2015-06-26 | E32: 2015-06-26 | G32: Approximately692m announced transaction value. A consistent contemporaneous EBITDA denominator has not been verified for this implementation.
